Workbook

Sheet cleaned_orders_calculations
A1: order_id | B1: order_date | C1: ship_date | D1: customer_id | E1: customer_name | F1: segment | G1: region | H1: state | I1: city | J1: category | K1: sub_category | L1: product_name | M1: ship_mode | N1: quantity | O1: unit_price | P1: discount | Q1: sales | R1: cost | S1: profit | T1: payment_status | U1: order_status | V1: shipping_delay_days | W1: cleaned_discount | X1: calculated_sales | Y1: calculated_profit | Z1: profit_margin | AA1: order_month | AB1: order_year | AC1: data_quality_flag | AD1: row_text | AE1: duplicate_flag | AF1: negative_discount_flag | AG1: discount_above_range_flag | AH1: shipping_record_flag | AI1: sales_mismatch_check | AJ1: profit_mismatch_check | AK1: copy of region | AL1: copy of ship_mode
A2: ORD-2024-10001 | B2: 45494 | C2: 45500 | D2: CUST-4655 | E2: =PROPER(TRIM(raw_orders!E2)) -> Karan Malhotra | F2: =PROPER(TRIM(raw_orders!F2)) -> Consumer | G2: =PROPER(TRIM(raw_orders!G2)) -> North | H2: =PROPER(TRIM(raw_orders!H2)) -> Rajasthan | I2: =PROPER(TRIM(raw_orders!I2)) -> Jaipur | J2: =PROPER(TRIM(raw_orders!J2)) -> Office Supplies | K2: =PROPER(TRIM(raw_orders!K2)) -> Paper | L2: Pro Paper 122 | M2: =PROPER(TRIM(raw_orders!M2)) -> Second Class | N2: 8 | O2: 2976.45 | P2: 0.2 | Q2: 19049.28 | R2: 15841.89 | S2: 3207.39 | T2: =PROPER(TRIM(raw_orders!T2)) -> Paid | U2: =PROPER(TRIM(raw_orders!U2)) -> Completed | V2: =C2-B2 -> 6 | W2: =IF(AND(P2="",Q2<>"",N2<>"",S2<>""),0,IF(OR(P2<0,P2>1),P2,P2)) -> 0.2 | X2: =N2*O2*(1-P2) -> 19049.28 | Y2: =X2-R2 -> 3207.39 | Z2: =Y2/X2 -> 0.16837329 | AA2: =TEXT(B2,"MMMM") -> July | AB2: =YEAR(B2) -> 2024 | AC2: =IF(OR(AF2 = "Invalid Discount",AG2="Invalid Discount",AH2="Invalid Shipping Record",AE2="Review Required"),"Invalid",IF(OR(G2="Unknown",M2="Unknown",ISBLANK(P2)),"Warning","Clean")) -> Clean | AD2: =A2&B2&C2&D2&E2&F2&G2&H2&I2&J2&K2&L2&M2&N2&O2&P2&Q2&R2&S2&T2&U2&V2 -> ORD-2024-100014549445500CUST-4655Karan MalhotraConsumerNorthRajasthanJaipurOffice SuppliesPaperPro Paper 122Second Class82976.450.219049.2815841.893207.39PaidCompleted6 | AE2: =IF(COUNTIF($A$2:$A$933,A2)=1,"OK",IF(COUNTIF($AD$2:$AD$933,AD2)>1,"Exact Duplicate", "Review Required")) -> OK | AF2: =IF(P2<0,"Invalid Discount","") | AG2: =IF(P2>1,"Invalid Discount","") | AH2: =IF(V2<1,"Invalid Shipping Record","") | AI2: =IF(ROUND(Q2,2)=ROUND(X2,2),"Match","Mismatch") -> Match | AJ2: =IF(ROUND(S2,2)=ROUND(Y2,2),"Match","Mismatch") -> Match | AK2: =PROPER(TRIM(raw_orders!G2)) -> North | AL2: =PROPER(TRIM(raw_orders!M2)) -> Second Class
A3: ORD-2024-10002 | B3: 45535 | C3: 45540 | D3: CUST-2054 | E3: =PROPER(TRIM(raw_orders!E3)) -> Mira Das | F3: =PROPER(TRIM(raw_orders!F3)) -> Small Business | G3: =PROPER(TRIM(raw_orders!G3)) -> East | H3: =PROPER(TRIM(raw_orders!H3)) -> Odisha | I3: =PROPER(TRIM(raw_orders!I3)) -> Bhubaneswar | J3: =PROPER(TRIM(raw_orders!J3)) -> Furniture | K3: =PROPER(TRIM(raw_orders!K3)) -> Tables | L3: Pro Tables 258 | M3: =PROPER(TRIM(raw_orders!M3)) -> Same Day | N3: 3 | O3: 2437.5 | P3: 0 | Q3: 7312.5 | R3: 4904.73 | S3: 2407.77 | T3: =PROPER(TRIM(raw_orders!T3)) -> Paid | U3: =PROPER(TRIM(raw_orders!U3)) -> Completed | V3: =C3-B3 -> 5 | W3: =IF(AND(P3="",Q3<>"",N3<>"",S3<>""),0,IF(OR(P3<0,P3>1),P3,P3)) -> 0 | X3: =N3*O3*(1-P3) -> 7312.5 | Y3: =X3-R3 -> 2407.77 | Z3: =Y3/X3 -> 0.32926769 | AA3: =TEXT(B3,"MMMM") -> August | AB3: =YEAR(B3) -> 2024 | AC3: =IF(OR(AF3 = "Invalid Discount",AG3="Invalid Discount",AH3="Invalid Shipping Record",AE3="Review Required"),"Invalid",IF(OR(G3="Unknown",M3="Unknown",ISBLANK(P3)),"Warning","Clean")) -> Clean | AD3: =A3&B3&C3&D3&E3&F3&G3&H3&I3&J3&K3&L3&M3&N3&O3&P3&Q3&R3&S3&T3&U3&V3 -> ORD-2024-100024553545540CUST-2054Mira DasSmall BusinessEastOdishaBhubaneswarFurnitureTablesPro Tables 258Same Day32437.507312.54904.732407.77PaidCompleted5 | AE3: =IF(COUNTIF($A$2:$A$933,A3)=1,"OK",IF(COUNTIF($AD$2:$AD$933,AD3)>1,"Exact Duplicate", "Review Required")) -> OK | AF3: =IF(P3<0,"Invalid Discount","") | AG3: =IF(P3>1,"Invalid Discount","") | AH3: =IF(V3<1,"Invalid Shipping Record","") | AI3: =IF(ROUND(Q3,2)=ROUND(X3,2),"Match","Mismatch") -> Match | AJ3: =IF(ROUND(S3,2)=ROUND(Y3,2),"Match","Mismatch") -> Match | AK3: =PROPER(TRIM(raw_orders!G3)) -> East | AL3: =PROPER(TRIM(raw_orders!M3)) -> Same Day | AN3: Missing Region | AO3: =COUNTBLANK(AK2:AK913) -> 25
A4: ORD-2024-10003 | B4: 45451 | C4: 45458 | D4: CUST-6843 | E4: =PROPER(TRIM(raw_orders!E4)) -> Isha Nair | F4: =PROPER(TRIM(raw_orders!F4)) -> Consumer | G4: =PROPER(TRIM(raw_orders!G4)) -> East | H4: =PROPER(TRIM(raw_orders!H4)) -> Odisha | I4: =PROPER(TRIM(raw_orders!I4)) -> Bhubaneswar | J4: =PROPER(TRIM(raw_orders!J4)) -> Office Supplies | K4: =PROPER(TRIM(raw_orders!K4)) -> Art | L4: Elite Art 525 | M4: =PROPER(TRIM(raw_orders!M4)) -> First Class | N4: 4 | O4: 1065.43 | P4: 0.55 | Q4: 4261.72 | R4: 2465.69 | S4: 1796.03 | T4: =PROPER(TRIM(raw_orders!T4)) -> Paid | U4: =PROPER(TRIM(raw_orders!U4)) -> Completed | V4: =C4-B4 -> 7 | W4: =IF(AND(P4="",Q4<>"",N4<>"",S4<>""),0,IF(OR(P4<0,P4>1),P4,P4)) -> 0.55 | X4: =N4*O4*(1-P4) -> 1917.774 | Y4: =X4-R4 -> -547.916 | Z4: =Y4/X4 -> -0.28570415 | AA4: =TEXT(B4,"MMMM") -> June | AB4: =YEAR(B4) -> 2024 | AC4: =IF(OR(AF4 = "Invalid Discount",AG4="Invalid Discount",AH4="Invalid Shipping Record",AE4="Review Required"),"Invalid",IF(OR(G4="Unknown",M4="Unknown",ISBLANK(P4)),"Warning","Clean")) -> Clean | AD4: =A4&B4&C4&D4&E4&F4&G4&H4&I4&J4&K4&L4&M4&N4&O4&P4&Q4&R4&S4&T4&U4&V4 -> ORD-2024-100034545145458CUST-6843Isha NairConsumerEastOdishaBhubaneswarOffice SuppliesArtElite Art 525First Class41065.430.554261.722465.691796.03PaidCompleted7 | AE4: =IF(COUNTIF($A$2:$A$933,A4)=1,"OK",IF(COUNTIF($AD$2:$AD$933,AD4)>1,"Exact Duplicate", "Review Required")) -> OK | AF4: =IF(P4<0,"Invalid Discount","") | AG4: =IF(P4>1,"Invalid Discount","") | AH4: =IF(V4<1,"Invalid Shipping Record","") | AI4: =IF(ROUND(Q4,2)=ROUND(X4,2),"Match","Mismatch") -> Mismatch | AJ4: =IF(ROUND(S4,2)=ROUND(Y4,2),"Match","Mismatch") -> Mismatch | AK4: =PROPER(TRIM(raw_orders!G4)) -> East | AL4: =PROPER(TRIM(raw_orders!M4)) -> First Class | AN4: Missing Ship Mode | AO4: =COUNTBLANK(AL2:AL913) -> 21
A5: ORD-2024-10004 | B5: 45624 | C5: 45625 | D5: CUST-3722 | E5: =PROPER(TRIM(raw_orders!E5)) -> Arjun Bose | F5: =PROPER(TRIM(raw_orders!F5)) -> Small Business | G5: =PROPER(TRIM(raw_orders!G5)) -> South | H5: =PROPER(TRIM(raw_orders!H5)) -> Telangana | I5: =PROPER(TRIM(raw_orders!I5)) -> Hyderabad | J5: =PROPER(TRIM(raw_orders!J5)) -> Furniture | K5: =PROPER(TRIM(raw_orders!K5)) -> Furnishings | L5: Smart Furnishings 294 | M5: =PROPER(TRIM(raw_orders!M5)) -> Standard Class | N5: 6 | O5: 1848.43 | P5: 0.25 | Q5: 8317.93 | R5: 6796.77 | S5: 1521.16 | T5: =PROPER(TRIM(raw_orders!T5)) -> Paid | U5: =PROPER(TRIM(raw_orders!U5)) -> Completed | V5: =C5-B5 -> 1 | W5: =IF(AND(P5="",Q5<>"",N5<>"",S5<>""),0,IF(OR(P5<0,P5>1),P5,P5)) -> 0.25 | X5: =N5*O5*(1-P5) -> 8317.935 | Y5: =X5-R5 -> 1521.165 | Z5: =Y5/X5 -> 0.18287772 | AA5: =TEXT(B5,"MMMM") -> November | AB5: =YEAR(B5) -> 2024 | AC5: =IF(OR(AF5 = "Invalid Discount",AG5="Invalid Discount",AH5="Invalid Shipping Record",AE5="Review Required"),"Invalid",IF(OR(G5="Unknown",M5="Unknown",ISBLANK(P5)),"Warning","Clean")) -> Clean | AD5: =A5&B5&C5&D5&E5&F5&G5&H5&I5&J5&K5&L5&M5&N5&O5&P5&Q5&R5&S5&T5&U5&V5 -> ORD-2024-100044562445625CUST-3722Arjun BoseSmall BusinessSouthTelanganaHyderabadFurnitureFurnishingsSmart Furnishings 294Standard Class61848.430.258317.936796.771521.16PaidCompleted1 | AE5: =IF(COUNTIF($A$2:$A$933,A5)=1,"OK",IF(COUNTIF($AD$2:$AD$933,AD5)>1,"Exact Duplicate", "Review Required")) -> OK | AF5: =IF(P5<0,"Invalid Discount","") | AG5: =IF(P5>1,"Invalid Discount","") | AH5: =IF(V5<1,"Invalid Shipping Record","") | AI5: =IF(ROUND(Q5,2)=ROUND(X5,2),"Match","Mismatch") -> Mismatch | AJ5: =IF(ROUND(S5,2)=ROUND(Y5,2),"Match","Mismatch") -> Mismatch | AK5: =PROPER(TRIM(raw_orders!G5)) -> South | AL5: =PROPER(TRIM(raw_orders!M5)) -> Standard Class | AN5: Missing Discount | AO5: =COUNTBLANK(P2:P913) -> 18
A6: ORD-2025-10005 | B6: 45898 | C6: 45901 | D6: CUST-8130 | E6: =PROPER(TRIM(raw_orders!E6)) -> Ananya Rao | F6: =PROPER(TRIM(raw_orders!F6)) -> Small Business | G6: =PROPER(TRIM(raw_orders!G6)) -> West | H6: =PROPER(TRIM(raw_orders!H6)) -> Maharashtra | I6: =PROPER(TRIM(raw_orders!I6)) -> Mumbai | J6: =PROPER(TRIM(raw_orders!J6)) -> Furniture | K6: =PROPER(TRIM(raw_orders!K6)) -> Chairs | L6: Elite Chairs 543 | M6: =PROPER(TRIM(raw_orders!M6)) -> First Class | N6: 7 | O6: 2973.76 | P6: 0 | Q6: 20816.32 | R6: 17705.37 | S6: 3110.95 | T6: =PROPER(TRIM(raw_orders!T6)) -> Paid | U6: =PROPER(TRIM(raw_orders!U6)) -> Cancelled | V6: =C6-B6 -> 3 | W6: =IF(AND(P6="",Q6<>"",N6<>"",S6<>""),0,IF(OR(P6<0,P6>1),P6,P6)) -> 0 | X6: =N6*O6*(1-P6) -> 20816.32 | Y6: =X6-R6 -> 3110.95 | Z6: =Y6/X6 -> 0.14944764 | AA6: =TEXT(B6,"MMMM") -> August | AB6: =YEAR(B6) -> 2025 | AC6: =IF(OR(AF6 = "Invalid Discount",AG6="Invalid Discount",AH6="Invalid Shipping Record",AE6="Review Required"),"Invalid",IF(OR(G6="Unknown",M6="Unknown",ISBLANK(P6)),"Warning","Clean")) -> Clean | AD6: =A6&B6&C6&D6&E6&F6&G6&H6&I6&J6&K6&L6&M6&N6&O6&P6&Q6&R6&S6&T6&U6&V6 -> ORD-2025-100054589845901CUST-8130Ananya RaoSmall BusinessWestMaharashtraMumbaiFurnitureChairsElite Chairs 543First Class72973.76020816.3217705.373110.95PaidCancelled3 | AE6: =IF(COUNTIF($A$2:$A$933,A6)=1,"OK",IF(COUNTIF($AD$2:$AD$933,AD6)>1,"Exact Duplicate", "Review Required")) -> OK | AF6: =IF(P6<0,"Invalid Discount","") | AG6: =IF(P6>1,"Invalid Discount","") | AH6: =IF(V6<1,"Invalid Shipping Record","") | AI6: =IF(ROUND(Q6,2)=ROUND(X6,2),"Match","Mismatch") -> Match | AJ6: =IF(ROUND(S6,2)=ROUND(Y6,2),"Match","Mismatch") -> Match | AK6: =PROPER(TRIM(raw_orders!G6)) -> West | AL6: =PROPER(TRIM(raw_orders!M6)) -> First Class | AN6: Negative discount | AO6: =COUNTIF(P2:P913,"<0") -> 15
A7: ORD-2024-10006 | B7: 45436 | C7: 45440 | D7: CUST-6056 | E7: =PROPER(TRIM(raw_orders!E7)) -> Vikram Iyer | F7: =PROPER(TRIM(raw_orders!F7)) -> Small Business | G7: =PROPER(TRIM(raw_orders!G7)) -> West | H7: =PROPER(TRIM(raw_orders!H7)) -> Madhya Pradesh | I7: =PROPER(TRIM(raw_orders!I7)) -> Indore | J7: =PROPER(TRIM(raw_orders!J7)) -> Technology | K7: =PROPER(TRIM(raw_orders!K7)) -> Accessories | L7: Pro Accessories 821 | M7: =PROPER(TRIM(raw_orders!M7)) -> Same Day | N7: 3 | O7: 1053.11 | P7: 0.2 | Q7: 2527.46 | R7: 1533.58 | S7: 993.88 | T7: =PROPER(TRIM(raw_orders!T7)) -> Paid | U7: =PROPER(TRIM(raw_orders!U7)) -> Completed | V7: =C7-B7 -> 4 | W7: =IF(AND(P7="",Q7<>"",N7<>"",S7<>""),0,IF(OR(P7<0,P7>1),P7,P7)) -> 0.2 | X7: =N7*O7*(1-P7) -> 2527.464 | Y7: =X7-R7 -> 993.884 | Z7: =Y7/X7 -> 0.39323369 | AA7: =TEXT(B7,"MMMM") -> May | AB7: =YEAR(B7) -> 2024 | AC7: =IF(OR(AF7 = "Invalid Discount",AG7="Invalid Discount",AH7="Invalid Shipping Record",AE7="Review Required"),"Invalid",IF(OR(G7="Unknown",M7="Unknown",ISBLANK(P7)),"Warning","Clean")) -> Clean | AD7: =A7&B7&C7&D7&E7&F7&G7&H7&I7&J7&K7&L7&M7&N7&O7&P7&Q7&R7&S7&T7&U7&V7 -> ORD-2024-100064543645440CUST-6056Vikram IyerSmall BusinessWestMadhya PradeshIndoreTechnologyAccessoriesPro Accessories 821Same Day31053.110.22527.461533.58993.88PaidCompleted4 | AE7: =IF(COUNTIF($A$2:$A$933,A7)=1,"OK",IF(COUNTIF($AD$2:$AD$933,AD7)>1,"Exact Duplicate", "Review Required")) -> OK | AF7: =IF(P7<0,"Invalid Discount","") | AG7: =IF(P7>1,"Invalid Discount","") | AH7: =IF(V7<1,"Invalid Shipping Record","") | AI7: =IF(ROUND(Q7,2)=ROUND(X7,2),"Match","Mismatch") -> Match | AJ7: =IF(ROUND(S7,2)=ROUND(Y7,2),"Match","Mismatch") -> Match | AK7: =PROPER(TRIM(raw_orders!G7)) -> West | AL7: =PROPER(TRIM(raw_orders!M7)) -> Same Day | AN7: Discount Above Range | AO7: =COUNTIF(AG2:AG913,"Invalid Discount") -> 0
A8: ORD-2025-10007 | B8: 45757 | C8: 45763 | D8: CUST-3656 | E8: =PROPER(TRIM(raw_orders!E8)) -> Neha Gupta | F8: =PROPER(TRIM(raw_orders!F8)) -> Consumer | G8: =PROPER(TRIM(raw_orders!G8)) -> East | H8: =PROPER(TRIM(raw_orders!H8)) -> Odisha | I8: =PROPER(TRIM(raw_orders!I8)) -> Bhubaneswar | J8: =PROPER(TRIM(raw_orders!J8)) -> Technology | K8: =PROPER(TRIM(raw_orders!K8)) -> Copiers | L8: Eco Copiers 790 | M8: =PROPER(TRIM(raw_orders!M8)) -> Standard Class | N8: 4 | O8: 1719.87 | P8: 0.15 | Q8: 5847.56 | R8: 4727.25 | S8: 1120.31 | T8: =PROPER(TRIM(raw_orders!T8)) -> Paid | U8: =PROPER(TRIM(raw_orders!U8)) -> Completed | V8: =C8-B8 -> 6 | W8: =IF(AND(P8="",Q8<>"",N8<>"",S8<>""),0,IF(OR(P8<0,P8>1),P8,P8)) -> 0.15 | X8: =N8*O8*(1-P8) -> 5847.558 | Y8: =X8-R8 -> 1120.308 | Z8: =Y8/X8 -> 0.19158562 | AA8: =TEXT(B8,"MMMM") -> April | AB8: =YEAR(B8) -> 2025 | AC8: =IF(OR(AF8 = "Invalid Discount",AG8="Invalid Discount",AH8="Invalid Shipping Record",AE8="Review Required"),"Invalid",IF(OR(G8="Unknown",M8="Unknown",ISBLANK(P8)),"Warning","Clean")) -> Clean | AD8: =A8&B8&C8&D8&E8&F8&G8&H8&I8&J8&K8&L8&M8&N8&O8&P8&Q8&R8&S8&T8&U8&V8 -> ORD-2025-100074575745763CUST-3656Neha GuptaConsumerEastOdishaBhubaneswarTechnologyCopiersEco Copiers 790Standard Class41719.870.155847.564727.251120.31PaidCompleted6 | AE8: =IF(COUNTIF($A$2:$A$933,A8)=1,"OK",IF(COUNTIF($AD$2:$AD$933,AD8)>1,"Exact Duplicate", "Review Required")) -> OK | AF8: =IF(P8<0,"Invalid Discount","") | AG8: =IF(P8>1,"Invalid Discount","") | AH8: =IF(V8<1,"Invalid Shipping Record","") | AI8: =IF(ROUND(Q8,2)=ROUND(X8,2),"Match","Mismatch") -> Match | AJ8: =IF(ROUND(S8,2)=ROUND(Y8,2),"Match","Mismatch") -> Match | AK8: =PROPER(TRIM(raw_orders!G8)) -> East | AL8: =PROPER(TRIM(raw_orders!M8)) -> Standard Class
A9: ORD-2025-10008 | B9: 45711 | C9: 45714 | D9: CUST-4683 | E9: =PROPER(TRIM(raw_orders!E9)) -> Isha Nair | F9: =PROPER(TRIM(raw_orders!F9)) -> Small Business | G9: =PROPER(TRIM(raw_orders!G9)) -> South | H9: =PROPER(TRIM(raw_orders!H9)) -> Andhra Pradesh | I9: =PROPER(TRIM(raw_orders!I9)) -> Vijayawada | J9: =PROPER(TRIM(raw_orders!J9)) -> Office Supplies | K9: =PROPER(TRIM(raw_orders!K9)) -> Art | L9: Eco Art 848 | M9: =PROPER(TRIM(raw_orders!M9)) -> First Class | N9: 1 | O9: 2980.71 | P9: 0 | Q9: 2980.71 | R9: 2357.22 | S9: 623.49 | T9: =PROPER(TRIM(raw_orders!T9)) -> Paid | U9: =PROPER(TRIM(raw_orders!U9)) -> Completed | V9: =C9-B9 -> 3 | W9: =IF(AND(P9="",Q9<>"",N9<>"",S9<>""),0,IF(OR(P9<0,P9>1),P9,P9)) -> 0 | X9: =N9*O9*(1-P9) -> 2980.71 | Y9: =X9-R9 -> 623.49 | Z9: =Y9/X9 -> 0.209175 | AA9: =TEXT(B9,"MMMM") -> February | AB9: =YEAR(B9) -> 2025 | AC9: =IF(OR(AF9 = "Invalid Discount",AG9="Invalid Discount",AH9="Invalid Shipping Record",AE9="Review Required"),"Invalid",IF(OR(G9="Unknown",M9="Unknown",ISBLANK(P9)),"Warning","Clean")) -> Clean | AD9: =A9&B9&C9&D9&E9&F9&G9&H9&I9&J9&K9&L9&M9&N9&O9&P9&Q9&R9&S9&T9&U9&V9 -> ORD-2025-100084571145714CUST-4683Isha NairSmall BusinessSouthAndhra PradeshVijayawadaOffice SuppliesArtEco Art 848First Class12980.7102980.712357.22623.49PaidCompleted3 | AE9: =IF(COUNTIF($A$2:$A$933,A9)=1,"OK",IF(COUNTIF($AD$2:$AD$933,AD9)>1,"Exact Duplicate", "Review Required")) -> OK | AF9: =IF(P9<0,"Invalid Discount","") | AG9: =IF(P9>1,"Invalid Discount","") | AH9: =IF(V9<1,"Invalid Shipping Record","") | AI9: =IF(ROUND(Q9,2)=ROUND(X9,2),"Match","Mismatch") -> Match | AJ9: =IF(ROUND(S9,2)=ROUND(Y9,2),"Match","Mismatch") -> Match | AK9: =PROPER(TRIM(raw_orders!G9)) -> South | AL9: =PROPER(TRIM(raw_orders!M9)) -> First Class | AN9: Cancelled Orders | AO9: =COUNTIF(U:U,"Cancelled") -> 145
A10: ORD-2024-10009 | B10: 45601 | C10: 45606 | D10: CUST-2598 | E10: =PROPER(TRIM(raw_orders!E10)) -> Aditi Sen | F10: =PROPER(TRIM(raw_orders!F10)) -> Corporate | G10: =PROPER(TRIM(raw_orders!G10)) -> South | H10: =PROPER(TRIM(raw_orders!H10)) -> Telangana | I10: =PROPER(TRIM(raw_orders!I10)) -> Hyderabad | J10: =PROPER(TRIM(raw_orders!J10)) -> Office Supplies | K10: =PROPER(TRIM(raw_orders!K10)) -> Labels | L10: Classic Labels 815 | M10: =PROPER(TRIM(raw_orders!M10)) -> First Class | N10: 8 | O10: 3134.2 | P10: 0 | Q10: 25073.6 | R10: 17347.23 | S10: 7726.37 | T10: =PROPER(TRIM(raw_orders!T10)) -> Paid | U10: =PROPER(TRIM(raw_orders!U10)) -> Completed | V10: =C10-B10 -> 5 | W10: =IF(AND(P10="",Q10<>"",N10<>"",S10<>""),0,IF(OR(P10<0,P10>1),P10,P10)) -> 0 | X10: =N10*O10*(1-P10) -> 25073.6 | Y10: =X10-R10 -> 7726.37 | Z10: =Y10/X10 -> 0.30814761 | AA10: =TEXT(B10,"MMMM") -> November | AB10: =YEAR(B10) -> 2024 | AC10: =IF(OR(AF10 = "Invalid Discount",AG10="Invalid Discount",AH10="Invalid Shipping Record",AE10="Review Required"),"Invalid",IF(OR(G10="Unknown",M10="Unknown",ISBLANK(P10)),"Warning","Clean")) -> Clean | AD10: =A10&B10&C10&D10&E10&F10&G10&H10&I10&J10&K10&L10&M10&N10&O10&P10&Q10&R10&S10&T10&U10&V10 -> ORD-2024-100094560145606CUST-2598Aditi SenCorporateSouthTelanganaHyderabadOffice SuppliesLabelsClassic Labels 815First Class83134.2025073.617347.237726.37PaidCompleted5 | AE10: =IF(COUNTIF($A$2:$A$933,A10)=1,"OK",IF(COUNTIF($AD$2:$AD$933,AD10)>1,"Exact Duplicate", "Review Required")) -> OK | AF10: =IF(P10<0,"Invalid Discount","") | AG10: =IF(P10>1,"Invalid Discount","") | AH10: =IF(V10<1,"Invalid Shipping Record","") | AI10: =IF(ROUND(Q10,2)=ROUND(X10,2),"Match","Mismatch") -> Match | AJ10: =IF(ROUND(S10,2)=ROUND(Y10,2),"Match","Mismatch") -> Match | AK10: =PROPER(TRIM(raw_orders!G10)) -> South | AL10: =PROPER(TRIM(raw_orders!M10)) -> First Class | AN10: Completed Orders | AO10: =COUNTIF(U:U,"Completed") -> 604
A11: ORD-2025-10010 | B11: 45847 | C11: 45912 | D11: CUST-2483 | E11: =PROPER(TRIM(raw_orders!E11)) -> Mira Das | F11: =PROPER(TRIM(raw_orders!F11)) -> Home Office | G11: =PROPER(TRIM(raw_orders!G11)) -> South | H11: =PROPER(TRIM(raw_orders!H11)) -> Telangana | I11: =PROPER(TRIM(raw_orders!I11)) -> Hyderabad | J11: =PROPER(TRIM(raw_orders!J11)) -> Office Supplies | K11: =PROPER(TRIM(raw_orders!K11)) -> Paper | L11: Pro Paper 622 | M11: =PROPER(TRIM(raw_orders!M11)) -> Second Class | N11: 9 | O11: 852.04 | P11: 0.2 | Q11: 6134.69 | R11: 3800.19 | S11: 2334.5 | T11: =PROPER(TRIM(raw_orders!T11)) -> Paid | U11: =PROPER(TRIM(raw_orders!U11)) -> Completed | V11: =C11-B11 -> 65 | W11: =IF(AND(P11="",Q11<>"",N11<>"",S11<>""),0,IF(OR(P11<0,P11>1),P11,P11)) -> 0.2 | X11: =N11*O11*(1-P11) -> 6134.688 | Y11: =X11-R11 -> 2334.498 | Z11: =Y11/X11 -> 0.38054062 | AA11: =TEXT(B11,"MMMM") -> July | AB11: =YEAR(B11) -> 2025 | AC11: =IF(OR(AF11 = "Invalid Discount",AG11="Invalid Discount",AH11="Invalid Shipping Record",AE11="Review Required"),"Invalid",IF(OR(G11="Unknown",M11="Unknown",ISBLANK(P11)),"Warning","Clean")) -> Clean | AD11: =A11&B11&C11&D11&E11&F11&G11&H11&I11&J11&K11&L11&M11&N11&O11&P11&Q11&R11&S11&T11&U11&V11 -> ORD-2025-100104584745912CUST-2483Mira DasHome OfficeSouthTelanganaHyderabadOffice SuppliesPaperPro Paper 622Second Class9852.040.26134.693800.192334.5PaidCompleted65 | AE11: =IF(COUNTIF($A$2:$A$933,A11)=1,"OK",IF(COUNTIF($AD$2:$AD$933,AD11)>1,"Exact Duplicate", "Review Required")) -> OK | AF11: =IF(P11<0,"Invalid Discount","") | AG11: =IF(P11>1,"Invalid Discount","") | AH11: =IF(V11<1,"Invalid Shipping Record","") | AI11: =IF(ROUND(Q11,2)=ROUND(X11,2),"Match","Mismatch") -> Match | AJ11: =IF(ROUND(S11,2)=ROUND(Y11,2),"Match","Mismatch") -> Match | AK11: =PROPER(TRIM(raw_orders!G11)) -> South | AL11: =PROPER(TRIM(raw_orders!M11)) -> Second Class | AN11: Refunded Orders | AO11: =COUNTIF(U:U,"Returned") -> 163
A12: ORD-2025-10011 | B12: 45797 | C12: 45797 | D12: CUST-8092 | E12: =PROPER(TRIM(raw_orders!E12)) -> Ananya Rao | F12: =PROPER(TRIM(raw_orders!F12)) -> Corporate | G12: =PROPER(TRIM(raw_orders!G12)) -> East | H12: =PROPER(TRIM(raw_orders!H12)) -> West Bengal | I12: =PROPER(TRIM(raw_orders!I12)) -> Kolkata | J12: =PROPER(TRIM(raw_orders!J12)) -> Office Supplies | K12: =PROPER(TRIM(raw_orders!K12)) -> Labels | L12: Prime Labels 644 | M12: =PROPER(TRIM(raw_orders!M12)) -> Second Class | N12: 3 | O12: 3534.83 | P12: 0.05 | Q12: 10074.27 | R12: 6048.27 | S12: 4026 | T12: =PROPER(TRIM(raw_orders!T12)) -> Refunded | U12: =PROPER(TRIM(raw_orders!U12)) -> Returned | V12: =C12-B12 -> 0 | W12: =IF(AND(P12="",Q12<>"",N12<>"",S12<>""),0,IF(OR(P12<0,P12>1),P12,P12)) -> 0.05 | X12: =N12*O12*(1-P12) -> 10074.265 | Y12: =X12-R12 -> 4025.9955 | Z12: =Y12/X12 -> 0.39963167 | AA12: =TEXT(B12,"MMMM") -> May | AB12: =YEAR(B12) -> 2025 | AC12: =IF(OR(AF12 = "Invalid Discount",AG12="Invalid Discount",AH12="Invalid Shipping Record",AE12="Review Required"),"Invalid",IF(OR(G12="Unknown",M12="Unknown",ISBLANK(P12)),"Warning","Clean")) -> Clean | AD12: =A12&B12&C12&D12&E12&F12&G12&H12&I12&J12&K12&L12&M12&N12&O12&P12&Q12&R12&S12&T12&U12&V12 -> ORD-2025-100114579745797CUST-8092Ananya RaoCorporateEastWest BengalKolkataOffice SuppliesLabelsPrime Labels 644Second Class33534.830.0510074.276048.274026RefundedReturned0 | AE12: =IF(COUNTIF($A$2:$A$933,A12)=1,"OK",IF(COUNTIF($AD$2:$AD$933,AD12)>1,"Exact Duplicate", "Review Required")) -> OK | AF12: =IF(P12<0,"Invalid Discount","") | AG12: =IF(P12>1,"Invalid Discount","") | AH12: =IF(V12<0,"Invalid Shipping Record","") | AI12: =IF(ROUND(Q12,2)=ROUND(X12,2),"Match","Mismatch") -> Match | AJ12: =IF(ROUND(S12,2)=ROUND(Y12,2),"Match","Mismatch") -> Match | AK12: =PROPER(TRIM(raw_orders!G12)) -> East | AL12: =PROPER(TRIM(raw_orders!M12)) -> Second Class | AN12: Failed Payments | AO12: =COUNTIF(T:T,"Failed") -> 69
A13: ORD-2024-10012 | B13: 45495 | C13: 45496 | D13: CUST-6528 | E13: =PROPER(TRIM(raw_orders!E13)) -> Vikram Iyer | F13: =PROPER(TRIM(raw_orders!F13)) -> Small Business | G13: =PROPER(TRIM(raw_orders!G13)) -> East | H13: =PROPER(TRIM(raw_orders!H13)) -> Odisha | I13: =PROPER(TRIM(raw_orders!I13)) -> Bhubaneswar | J13: =PROPER(TRIM(raw_orders!J13)) -> Technology | K13: =PROPER(TRIM(raw_orders!K13)) -> Accessories | L13: Smart Accessories 603 | M13: =PROPER(TRIM(raw_orders!M13)) -> Same Day | N13: 6 | O13: 2005.95 | P13: 0.2 | Q13: 9628.56 | R13: 8038.59 | S13: 1589.97 | T13: =PROPER(TRIM(raw_orders!T13)) -> Paid | U13: =PROPER(TRIM(raw_orders!U13)) -> Completed | V13: =C13-B13 -> 1 | W13: =IF(AND(P13="",Q13<>"",N13<>"",S13<>""),0,IF(OR(P13<0,P13>1),P13,P13)) -> 0.2 | X13: =N13*O13*(1-P13) -> 9628.56 | Y13: =X13-R13 -> 1589.97 | Z13: =Y13/X13 -> 0.16513061 | AA13: =TEXT(B13,"MMMM") -> July | AB13: =YEAR(B13) -> 2024 | AC13: =IF(OR(AF13 = "Invalid Discount",AG13="Invalid Discount",AH13="Invalid Shipping Record",AE13="Review Required"),"Invalid",IF(OR(G13="Unknown",M13="Unknown",ISBLANK(P13)),"Warning","Clean")) -> Clean | AD13: =A13&B13&C13&D13&E13&F13&G13&H13&I13&J13&K13&L13&M13&N13&O13&P13&Q13&R13&S13&T13&U13&V13 -> ORD-2024-100124549545496CUST-6528Vikram IyerSmall BusinessEastOdishaBhubaneswarTechnologyAccessoriesSmart Accessories 603Same Day62005.950.29628.568038.591589.97PaidCompleted1 | AE13: =IF(COUNTIF($A$2:$A$933,A13)=1,"OK",IF(COUNTIF($AD$2:$AD$933,AD13)>1,"Exact Duplicate", "Review Required")) -> OK | AF13: =IF(P13<0,"Invalid Discount","") | AG13: =IF(P13>1,"Invalid Discount","") | AH13: =IF(V13<1,"Invalid Shipping Record","") | AI13: =IF(ROUND(Q13,2)=ROUND(X13,2),"Match","Mismatch") -> Match | AJ13: =IF(ROUND(S13,2)=ROUND(Y13,2),"Match","Mismatch") -> Match | AK13: =PROPER(TRIM(raw_orders!G13)) -> East | AL13: =PROPER(TRIM(raw_orders!M13)) -> Same Day | AN13: Refunded Orders | AO13: =COUNTIF(T:T,"Refunded") -> 71
A14: ORD-2024-10013 | B14: 45646 | C14: 45647 | D14: CUST-2648 | E14: =PROPER(TRIM(raw_orders!E14)) -> Ananya Rao | F14: =PROPER(TRIM(raw_orders!F14)) -> Corporate | G14: =PROPER(TRIM(raw_orders!G14)) -> West | H14: =PROPER(TRIM(raw_orders!H14)) -> Rajasthan | I14: =PROPER(TRIM(raw_orders!I14)) -> Udaipur | J14: =PROPER(TRIM(raw_orders!J14)) -> Office Supplies | K14: =PROPER(TRIM(raw_orders!K14)) -> Paper | L14: Pro Paper 481 | M14: =PROPER(TRIM(raw_orders!M14)) -> First Class | N14: 1 | O14: 702.14 | P14: 0.15 | Q14: 596.82 | R14: 380.25 | S14: 216.57 | T14: =PROPER(TRIM(raw_orders!T14)) -> Pending | U14: =PROPER(TRIM(raw_orders!U14)) -> Returned | V14: =C14-B14 -> 1 | W14: =IF(AND(P14="",Q14<>"",N14<>"",S14<>""),0,IF(OR(P14<0,P14>1),P14,P14)) -> 0.15 | X14: =N14*O14*(1-P14) -> 596.819 | Y14: =X14-R14 -> 216.569 | Z14: =Y14/X14 -> 0.36287216 | AA14: =TEXT(B14,"MMMM") -> December | AB14: =YEAR(B14) -> 2024 | AC14: =IF(OR(AF14 = "Invalid Discount",AG14="Invalid Discount",AH14="Invalid Shipping Record",AE14="Review Required"),"Invalid",IF(OR(G14="Unknown",M14="Unknown",ISBLANK(P14)),"Warning","Clean")) -> Clean | AD14: =A14&B14&C14&D14&E14&F14&G14&H14&I14&J14&K14&L14&M14&N14&O14&P14&Q14&R14&S14&T14&U14&V14 -> ORD-2024-100134564645647CUST-2648Ananya RaoCorporateWestRajasthanUdaipurOffice SuppliesPaperPro Paper 481First Class1702.140.15596.82380.25216.57PendingReturned1 | AE14: =IF(COUNTIF($A$2:$A$933,A14)=1,"OK",IF(COUNTIF($AD$2:$AD$933,AD14)>1,"Exact Duplicate", "Review Required")) -> OK | AF14: =IF(P14<0,"Invalid Discount","") | AG14: =IF(P14>1,"Invalid Discount","") | AH14: =IF(V14<1,"Invalid Shipping Record","") | AI14: =IF(ROUND(Q14,2)=ROUND(X14,2),"Match","Mismatch") -> Match | AJ14: =IF(ROUND(S14,2)=ROUND(Y14,2),"Match","Mismatch") -> Match | AK14: =PROPER(TRIM(raw_orders!G14)) -> West | AL14: =PROPER(TRIM(raw_orders!M14)) -> First Class
A15: ORD-2025-10014 | B15: 45942 | C15: 45946 | D15: CUST-7482 | E15: =PROPER(TRIM(raw_orders!E15)) -> Priya Menon | F15: =PROPER(TRIM(raw_orders!F15)) -> Small Business | G15: =PROPER(TRIM(raw_orders!G15)) -> West | H15: =PROPER(TRIM(raw_orders!H15)) -> Maharashtra | I15: =PROPER(TRIM(raw_orders!I15)) -> Mumbai | J15: =PROPER(TRIM(raw_orders!J15)) -> Office Supplies | K15: =PROPER(TRIM(raw_orders!K15)) -> Art | L15: Smart Art 795 | M15: =PROPER(TRIM(raw_orders!M15)) -> Second Class | N15: 7 | O15: 3964.72 | P15: 0.05 | Q15: 26365.39 | R15: 22306.24 | S15: 4059.15 | T15: =PROPER(TRIM(raw_orders!T15)) -> Paid | U15: =PROPER(TRIM(raw_orders!U15)) -> Completed | V15: =C15-B15 -> 4 | W15: =IF(AND(P15="",Q15<>"",N15<>"",S15<>""),0,IF(OR(P15<0,P15>1),P15,P15)) -> 0.05 | X15: =N15*O15*(1-P15) -> 26365.388 | Y15: =X15-R15 -> 4059.148 | Z15: =Y15/X15 -> 0.15395745 | AA15: =TEXT(B15,"MMMM") -> October | AB15: =YEAR(B15) -> 2025 | AC15: =IF(OR(AF15 = "Invalid Discount",AG15="Invalid Discount",AH15="Invalid Shipping Record",AE15="Review Required"),"Invalid",IF(OR(G15="Unknown",M15="Unknown",ISBLANK(P15)),"Warning","Clean")) -> Clean | AD15: =A15&B15&C15&D15&E15&F15&G15&H15&I15&J15&K15&L15&M15&N15&O15&P15&Q15&R15&S15&T15&U15&V15 -> ORD-2025-100144594245946CUST-7482Priya MenonSmall BusinessWestMaharashtraMumbaiOffice SuppliesArtSmart Art 795Second Class73964.720.0526365.3922306.244059.15PaidCompleted4 | AE15: =IF(COUNTIF($A$2:$A$933,A15)=1,"OK",IF(COUNTIF($AD$2:$AD$933,AD15)>1,"Exact Duplicate", "Review Required")) -> OK | AF15: =IF(P15<0,"Invalid Discount","") | AG15: =IF(P15>1,"Invalid Discount","") | AH15: =IF(V15<1,"Invalid Shipping Record","") | AI15: =IF(ROUND(Q15,2)=ROUND(X15,2),"Match","Mismatch") -> Match | AJ15: =IF(ROUND(S15,2)=ROUND(Y15,2),"Match","Mismatch") -> Match | AK15: =PROPER(TRIM(raw_orders!G15)) -> West | AL15: =PROPER(TRIM(raw_orders!M15)) -> Second Class
A16: ORD-2024-10015 | B16: 45653 | C16: 45654 | D16: CUST-4912 | E16: =PROPER(TRIM(raw_orders!E16)) -> Rahul Verma | F16: =PROPER(TRIM(raw_orders!F16)) -> Consumer | G16: =PROPER(TRIM(raw_orders!G16)) -> West | H16: =PROPER(TRIM(raw_orders!H16)) -> Rajasthan | I16: =PROPER(TRIM(raw_orders!I16)) -> Udaipur | J16: =PROPER(TRIM(raw_orders!J16)) -> Technology | K16: =PROPER(TRIM(raw_orders!K16)) -> Copiers | L16: Max Copiers 983 | M16: =PROPER(TRIM(raw_orders!M16)) -> Standard Class | N16: 2 | O16: 2737.83 | P16: 0.25 | Q16: 4106.74 | R16: 2666.3 | S16: 1440.44 | T16: =PROPER(TRIM(raw_orders!T16)) -> Paid | U16: =PROPER(TRIM(raw_orders!U16)) -> Completed | V16: =C16-B16 -> 1 | W16: =IF(AND(P16="",Q16<>"",N16<>"",S16<>""),0,IF(OR(P16<0,P16>1),P16,P16)) -> 0.25 | X16: =N16*O16*(1-P16) -> 4106.745 | Y16: =X16-R16 -> 1440.445 | Z16: =Y16/X16 -> 0.35075102 | AA16: =TEXT(B16,"MMMM") -> December | AB16: =YEAR(B16) -> 2024 | AC16: =IF(OR(AF16 = "Invalid Discount",AG16="Invalid Discount",AH16="Invalid Shipping Record",AE16="Review Required"),"Invalid",IF(OR(G16="Unknown",M16="Unknown",ISBLANK(P16)),"Warning","Clean")) -> Clean | AD16: =A16&B16&C16&D16&E16&F16&G16&H16&I16&J16&K16&L16&M16&N16&O16&P16&Q16&R16&S16&T16&U16&V16 -> ORD-2024-100154565345654CUST-4912Rahul VermaConsumerWestRajasthanUdaipurTechnologyCopiersMax Copiers 983Standard Class22737.830.254106.742666.31440.44PaidCompleted1 | AE16: =IF(COUNTIF($A$2:$A$933,A16)=1,"OK",IF(COUNTIF($AD$2:$AD$933,AD16)>1,"Exact Duplicate", "Review Required")) -> OK | AF16: =IF(P16<0,"Invalid Discount","") | AG16: =IF(P16>1,"Invalid Discount","") | AH16: =IF(V16<1,"Invalid Shipping Record","") | AI16: =IF(ROUND(Q16,2)=ROUND(X16,2),"Match","Mismatch") -> Mismatch | AJ16: =IF(ROUND(S16,2)=ROUND(Y16,2),"Match","Mismatch") -> Mismatch | AK16: =PROPER(TRIM(raw_orders!G16)) -> West | AL16: =PROPER(TRIM(raw_orders!M16)) -> Standard Class | AN16: Ship date before order date | AO16: =COUNTIF(V:V,"<0") -> 93
A17: ORD-2024-10016 | B17: 45482 | C17: 45482 | D17: CUST-7656 | E17: =PROPER(TRIM(raw_orders!E17)) -> Karan Malhotra | F17: =PROPER(TRIM(raw_orders!F17)) -> Small Business | G17: =PROPER(TRIM(raw_orders!G17)) -> North | H17: =PROPER(TRIM(raw_orders!H17)) -> Punjab | I17: =PROPER(TRIM(raw_orders!I17)) -> Ludhiana | J17: =PROPER(TRIM(raw_orders!J17)) -> Office Supplies | K17: =PROPER(TRIM(raw_orders!K17)) -> Storage | L17: Classic Storage 198 | M17: =PROPER(TRIM(raw_orders!M17)) -> Second Class | N17: 6 | O17: 3965.76 | P17: 0 | Q17: 23794.56 | R17: 15698.47 | S17: 8096.09 | T17: =PROPER(TRIM(raw_orders!T17)) -> Paid | U17: =PROPER(TRIM(raw_orders!U17)) -> Completed | V17: =C17-B17 -> 0 | W17: =IF(AND(P17="",Q17<>"",N17<>"",S17<>""),0,IF(OR(P17<0,P17>1),P17,P17)) -> 0 | X17: =N17*O17*(1-P17) -> 23794.56 | Y17: =X17-R17 -> 8096.09 | Z17: =Y17/X17 -> 0.34024962 | AA17: =TEXT(B17,"MMMM") -> July | AB17: =YEAR(B17) -> 2024 | AC17: =IF(OR(AF17 = "Invalid Discount",AG17="Invalid Discount",AH17="Invalid Shipping Record",AE17="Review Required"),"Invalid",IF(OR(G17="Unknown",M17="Unknown",ISBLANK(P17)),"Warning","Clean")) -> Clean | AD17: =A17&B17&C17&D17&E17&F17&G17&H17&I17&J17&K17&L17&M17&N17&O17&P17&Q17&R17&S17&T17&U17&V17 -> ORD-2024-100164548245482CUST-7656Karan MalhotraSmall BusinessNorthPunjabLudhianaOffice SuppliesStorageClassic Storage 198Second Class63965.76023794.5615698.478096.09PaidCompleted0 | AE17: =IF(COUNTIF($A$2:$A$933,A17)=1,"OK",IF(COUNTIF($AD$2:$AD$933,AD17)>1,"Exact Duplicate", "Review Required")) -> OK | AF17: =IF(P17<0,"Invalid Discount","") | AG17: =IF(P17>1,"Invalid Discount","") | AH17: =IF(V17<0,"Invalid Shipping Record","") | AI17: =IF(ROUND(Q17,2)=ROUND(X17,2),"Match","Mismatch") -> Match | AJ17: =IF(ROUND(S17,2)=ROUND(Y17,2),"Match","Mismatch") -> Match | AK17: =PROPER(TRIM(raw_orders!G17)) -> North | AL17: =PROPER(TRIM(raw_orders!M17)) -> Second Class
A18: ORD-2024-10017 | B18: 45420 | C18: 45427 | D18: CUST-6214 | E18: =PROPER(TRIM(raw_orders!E18)) -> Aarav Sharma | F18: =PROPER(TRIM(raw_orders!F18)) -> Consumer | G18: =PROPER(TRIM(raw_orders!G18)) -> South | H18: =PROPER(TRIM(raw_orders!H18)) -> Telangana | I18: =PROPER(TRIM(raw_orders!I18)) -> Hyderabad | J18: =PROPER(TRIM(raw_orders!J18)) -> Office Supplies | K18: =PROPER(TRIM(raw_orders!K18)) -> Art | L18: Basic Art 204 | M18: =PROPER(TRIM(raw_orders!M18)) -> First Class | N18: 4 | O18: 3323.51 | P18: 0.25 | Q18: 9970.53 | R18: 5668.17 | S18: 4302.36 | T18: =PROPER(TRIM(raw_orders!T18)) -> Paid | U18: =PROPER(TRIM(raw_orders!U18)) -> Completed | V18: =C18-B18 -> 7 | W18: =IF(AND(P18="",Q18<>"",N18<>"",S18<>""),0,IF(OR(P18<0,P18>1),P18,P18)) -> 0.25 | X18: =N18*O18*(1-P18) -> 9970.53 | Y18: =X18-R18 -> 4302.36 | Z18: =Y18/X18 -> 0.43150765 | AA18: =TEXT(B18,"MMMM") -> May | AB18: =YEAR(B18) -> 2024 | AC18: =IF(OR(AF18 = "Invalid Discount",AG18="Invalid Discount",AH18="Invalid Shipping Record",AE18="Review Required"),"Invalid",IF(OR(G18="Unknown",M18="Unknown",ISBLANK(P18)),"Warning","Clean")) -> Clean | AD18: =A18&B18&C18&D18&E18&F18&G18&H18&I18&J18&K18&L18&M18&N18&O18&P18&Q18&R18&S18&T18&U18&V18 -> ORD-2024-100174542045427CUST-6214Aarav SharmaConsumerSouthTelanganaHyderabadOffice SuppliesArtBasic Art 204First Class43323.510.259970.535668.174302.36PaidCompleted7 | AE18: =IF(COUNTIF($A$2:$A$933,A18)=1,"OK",IF(COUNTIF($AD$2:$AD$933,AD18)>1,"Exact Duplicate", "Review Required")) -> OK | AF18: =IF(P18<0,"Invalid Discount","") | AG18: =IF(P18>1,"Invalid Discount","") | AH18: =IF(V18<1,"Invalid Shipping Record","") | AI18: =IF(ROUND(Q18,2)=ROUND(X18,2),"Match","Mismatch") -> Match | AJ18: =IF(ROUND(S18,2)=ROUND(Y18,2),"Match","Mismatch") -> Match | AK18: =PROPER(TRIM(raw_orders!G18)) -> South | AL18: =PROPER(TRIM(raw_orders!M18)) -> First Class
A19: ORD-2024-10018 | B19: 45298 | C19: 45299 | D19: CUST-1626 | E19: =PROPER(TRIM(raw_orders!E19)) -> Sneha Kapoor | F19: =PROPER(TRIM(raw_orders!F19)) -> Small Business | G19: =PROPER(TRIM(raw_orders!G19)) -> North | H19: =PROPER(TRIM(raw_orders!H19)) -> Rajasthan | I19: =PROPER(TRIM(raw_orders!I19)) -> Jaipur | J19: =PROPER(TRIM(raw_orders!J19)) -> Furniture | K19: =PROPER(TRIM(raw_orders!K19)) -> Furnishings | L19: Basic Furnishings 434 | M19: =PROPER(TRIM(raw_orders!M19)) -> Same Day | N19: 5 | O19: 1526.78 | P19: 0 | Q19: 7633.9 | R19: 4706.91 | S19: 2926.99 | T19: =PROPER(TRIM(raw_orders!T19)) -> Paid | U19: =PROPER(TRIM(raw_orders!U19)) -> Completed | V19: =C19-B19 -> 1 | W19: =IF(AND(P19="",Q19<>"",N19<>"",S19<>""),0,IF(OR(P19<0,P19>1),P19,P19)) -> 0 | X19: =N19*O19*(1-P19) -> 7633.9 | Y19: =X19-R19 -> 2926.99 | Z19: =Y19/X19 -> 0.38342001 | AA19: =TEXT(B19,"MMMM") -> January | AB19: =YEAR(B19) -> 2024 | AC19: =IF(OR(AF19 = "Invalid Discount",AG19="Invalid Discount",AH19="Invalid Shipping Record",AE19="Review Required"),"Invalid",IF(OR(G19="Unknown",M19="Unknown",ISBLANK(P19)),"Warning","Clean")) -> Clean | AD19: =A19&B19&C19&D19&E19&F19&G19&H19&I19&J19&K19&L19&M19&N19&O19&P19&Q19&R19&S19&T19&U19&V19 -> ORD-2024-100184529845299CUST-1626Sneha KapoorSmall BusinessNorthRajasthanJaipurFurnitureFurnishingsBasic Furnishings 434Same Day51526.7807633.94706.912926.99PaidCompleted1 | AE19: =IF(COUNTIF($A$2:$A$933,A19)=1,"OK",IF(COUNTIF($AD$2:$AD$933,AD19)>1,"Exact Duplicate", "Review Required")) -> OK | AF19: =IF(P19<0,"Invalid Discount","") | AG19: =IF(P19>1,"Invalid Discount","") | AH19: =IF(V19<1,"Invalid Shipping Record","") | AI19: =IF(ROUND(Q19,2)=ROUND(X19,2),"Match","Mismatch") -> Match | AJ19: =IF(ROUND(S19,2)=ROUND(Y19,2),"Match","Mismatch") -> Match | AK19: =PROPER(TRIM(raw_orders!G19)) -> North | AL19: =PROPER(TRIM(raw_orders!M19)) -> Same Day | AN19: Clean | AO19: =COUNTIF(AC:AC,"Clean") -> 732
A20: ORD-2025-10019 | B20: 45853 | C20: 45855 | D20: CUST-2110 | E20: =PROPER(TRIM(raw_orders!E20)) -> Aarav Sharma | F20: =PROPER(TRIM(raw_orders!F20)) -> Home Office | G20: =PROPER(TRIM(raw_orders!G20)) -> North | H20: =PROPER(TRIM(raw_orders!H20)) -> Uttar Pradesh | I20: =PROPER(TRIM(raw_orders!I20)) -> Noida | J20: =PROPER(TRIM(raw_orders!J20)) -> Technology | K20: =PROPER(TRIM(raw_orders!K20)) -> Copiers | L20: Eco Copiers 755 | M20: =PROPER(TRIM(raw_orders!M20)) -> First Class | N20: 2 | O20: 1997.99 | P20: 0 | Q20: 3995.98 | R20: 2633.2 | S20: 1362.78 | T20: =PROPER(TRIM(raw_orders!T20)) -> Refunded | U20: =PROPER(TRIM(raw_orders!U20)) -> Cancelled | V20: =C20-B20 -> 2 | W20: =IF(AND(P20="",Q20<>"",N20<>"",S20<>""),0,IF(OR(P20<0,P20>1),P20,P20)) -> 0 | X20: =N20*O20*(1-P20) -> 3995.98 | Y20: =X20-R20 -> 1362.78 | Z20: =Y20/X20 -> 0.34103774 | AA20: =TEXT(B20,"MMMM") -> July | AB20: =YEAR(B20) -> 2025 | AC20: =IF(OR(AF20 = "Invalid Discount",AG20="Invalid Discount",AH20="Invalid Shipping Record",AE20="Review Required"),"Invalid",IF(OR(G20="Unknown",M20="Unknown",ISBLANK(P20)),"Warning","Clean")) -> Clean | AD20: =A20&B20&C20&D20&E20&F20&G20&H20&I20&J20&K20&L20&M20&N20&O20&P20&Q20&R20&S20&T20&U20&V20 -> ORD-2025-100194585345855CUST-2110Aarav SharmaHome OfficeNorthUttar PradeshNoidaTechnologyCopiersEco Copiers 755First Class21997.9903995.982633.21362.78RefundedCancelled2 | AE20: =IF(COUNTIF($A$2:$A$933,A20)=1,"OK",IF(COUNTIF($AD$2:$AD$933,AD20)>1,"Exact Duplicate", "Review Required")) -> OK | AF20: =IF(P20<0,"Invalid Discount","") | AG20: =IF(P20>1,"Invalid Discount","") | AH20: =IF(V20<1,"Invalid Shipping Record","") | AI20: =IF(ROUND(Q20,2)=ROUND(X20,2),"Match","Mismatch") -> Match | AJ20: =IF(ROUND(S20,2)=ROUND(Y20,2),"Match","Mismatch") -> Match | AK20: =PROPER(TRIM(raw_orders!G20)) -> North | AL20: =PROPER(TRIM(raw_orders!M20)) -> First Class | AN20: Warning | AO20: =COUNTIF(AC:AC,"Warning") -> 52
A21: ORD-2024-10020 | B21: 45500 | C21: 45504 | D21: CUST-3186 | E21: =PROPER(TRIM(raw_orders!E21)) -> Rohan Mehta | F21: =PROPER(TRIM(raw_orders!F21)) -> Home Office | G21: =PROPER(TRIM(raw_orders!G21)) -> West | H21: =PROPER(TRIM(raw_orders!H21)) -> Madhya Pradesh | I21: =PROPER(TRIM(raw_orders!I21)) -> Indore | J21: =PROPER(TRIM(raw_orders!J21)) -> Office Supplies | K21: =PROPER(TRIM(raw_orders!K21)) -> Storage | L21: Prime Storage 121 | M21: =PROPER(TRIM(raw_orders!M21)) -> Second Class | N21: 3 | O21: 3887.94 | P21: -0.19 | Q21: 9331.06 | R21: 7529.31 | S21: 1801.75 | T21: =PROPER(TRIM(raw_orders!T21)) -> Paid | U21: =PROPER(TRIM(raw_orders!U21)) -> Completed | V21: =C21-B21 -> 4 | W21: =IF(AND(P21="",Q21<>"",N21<>"",S21<>""),0,IF(OR(P21<0,P21>1),P21,P21)) -> -0.19 | X21: =N21*O21*(1-P21) -> 13879.946 | Y21: =X21-R21 -> 6350.6358 | Z21: =Y21/X21 -> 0.45754039 | AA21: =TEXT(B21,"MMMM") -> July | AB21: =YEAR(B21) -> 2024 | AC21: =IF(OR(AF21 = "Invalid Discount",AG21="Invalid Discount",AH21="Invalid Shipping Record",AE21="Review Required"),"Invalid",IF(OR(G21="Unknown",M21="Unknown",ISBLANK(P21)),"Warning","Clean")) -> Invalid | AD21: =A21&B21&C21&D21&E21&F21&G21&H21&I21&J21&K21&L21&M21&N21&O21&P21&Q21&R21&S21&T21&U21&V21 -> ORD-2024-100204550045504CUST-3186Rohan MehtaHome OfficeWestMadhya PradeshIndoreOffice SuppliesStoragePrime Storage 121Second Class33887.94-0.199331.067529.311801.75PaidCompleted4 | AE21: =IF(COUNTIF($A$2:$A$933,A21)=1,"OK",IF(COUNTIF($AD$2:$AD$933,AD21)>1,"Exact Duplicate", "Review Required")) -> OK | AF21: =IF(P21<0,"Invalid Discount","") -> Invalid Discount | AG21: =IF(P21>1,"Invalid Discount","") | AH21: =IF(V21<1,"Invalid Shipping Record","") | AI21: =IF(ROUND(Q21,2)=ROUND(X21,2),"Match","Mismatch") -> Mismatch | AJ21: =IF(ROUND(S21,2)=ROUND(Y21,2),"Match","Mismatch") -> Mismatch | AK21: =PROPER(TRIM(raw_orders!G21)) -> West | AL21: =PROPER(TRIM(raw_orders!M21)) -> Second Class | AN21: Invalid | AO21: =COUNTIF(AC:AC,"Invalid") -> 128
A22: ORD-2025-10021 | B22: 45678 | C22: 45680 | D22: CUST-3190 | E22: =PROPER(TRIM(raw_orders!E22)) -> Aditi Sen | F22: =PROPER(TRIM(raw_orders!F22)) -> Home Office | G22: =PROPER(TRIM(raw_orders!G22)) -> East | H22: =PROPER(TRIM(raw_orders!H22)) -> Bihar | I22: =PROPER(TRIM(raw_orders!I22)) -> Patna | J22: =PROPER(TRIM(raw_orders!J22)) -> Technology | K22: =PROPER(TRIM(raw_orders!K22)) -> Copiers | L22: Elite Copiers 233 | M22: =PROPER(TRIM(raw_orders!M22)) -> First Class | N22: 5 | O22: 4373.06 | P22: 0.25 | Q22: 16398.98 | R22: 9556.52 | S22: 6842.46 | T22: =PROPER(TRIM(raw_orders!T22)) -> Paid | U22: =PROPER(TRIM(raw_orders!U22)) -> Completed | V22: =C22-B22 -> 2 | W22: =IF(AND(P22="",Q22<>"",N22<>"",S22<>""),0,IF(OR(P22<0,P22>1),P22,P22)) -> 0.25 | X22: =N22*O22*(1-P22) -> 16398.975 | Y22: =X22-R22 -> 6842.455 | Z22: =Y22/X22 -> 0.41724894 | AA22: =TEXT(B22,"MMMM") -> January | AB22: =YEAR(B22) -> 2025 | AC22: =IF(OR(AF22 = "Invalid Discount",AG22="Invalid Discount",AH22="Invalid Shipping Record",AE22="Review Required"),"Invalid",IF(OR(G22="Unknown",M22="Unknown",ISBLANK(P22)),"Warning","Clean")) -> Clean | AD22: =A22&B22&C22&D22&E22&F22&G22&H22&I22&J22&K22&L22&M22&N22&O22&P22&Q22&R22&S22&T22&U22&V22 -> ORD-2025-100214567845680CUST-3190Aditi SenHome OfficeEastBiharPatnaTechnologyCopiersElite Copiers 233First Class54373.060.2516398.989556.526842.46PaidCompleted2 | AE22: =IF(COUNTIF($A$2:$A$933,A22)=1,"OK",IF(COUNTIF($AD$2:$AD$933,AD22)>1,"Exact Duplicate", "Review Required")) -> OK | AF22: =IF(P22<0,"Invalid Discount","") | AG22: =IF(P22>1,"Invalid Discount","") | AH22: =IF(V22<1,"Invalid Shipping Record","") | AI22: =IF(ROUND(Q22,2)=ROUND(X22,2),"Match","Mismatch") -> Match | AJ22: =IF(ROUND(S22,2)=ROUND(Y22,2),"Match","Mismatch") -> Match | AK22: =PROPER(TRIM(raw_orders!G22)) -> East | AL22: =PROPER(TRIM(raw_orders!M22)) -> First Class
A23: ORD-2025-10022 | B23: 45681 | C23: 45687 | D23: CUST-3036 | E23: =PROPER(TRIM(raw_orders!E23)) -> Sneha Kapoor | F23: =PROPER(TRIM(raw_orders!F23)) -> Consumer | G23: =PROPER(TRIM(raw_orders!G23)) -> West | H23: =PROPER(TRIM(raw_orders!H23)) -> Madhya Pradesh | I23: =PROPER(TRIM(raw_orders!I23)) -> Indore | J23: =PROPER(TRIM(raw_orders!J23)) -> Furniture | K23: =PROPER(TRIM(raw_orders!K23)) -> Furnishings | L23: Eco Furnishings 897 | M23: =PROPER(TRIM(raw_orders!M23)) -> Second Class | N23: 4 | O23: 697.69 | P23: -0.23 | Q23: 2790.76 | R23: 2037.71 | S23: 753.05 | T23: =PROPER(TRIM(raw_orders!T23)) -> Paid | U23: =PROPER(TRIM(raw_orders!U23)) -> Completed | V23: =C23-B23 -> 6 | W23: =IF(AND(P23="",Q23<>"",N23<>"",S23<>""),0,IF(OR(P23<0,P23>1),P23,P23)) -> -0.23 | X23: =N23*O23*(1-P23) -> 3432.6348 | Y23: =X23-R23 -> 1394.9248 | Z23: =Y23/X23 -> 0.40637146 | AA23: =TEXT(B23,"MMMM") -> January | AB23: =YEAR(B23) -> 2025 | AC23: =IF(OR(AF23 = "Invalid Discount",AG23="Invalid Discount",AH23="Invalid Shipping Record",AE23="Review Required"),"Invalid",IF(OR(G23="Unknown",M23="Unknown",ISBLANK(P23)),"Warning","Clean")) -> Invalid | AD23: =A23&B23&C23&D23&E23&F23&G23&H23&I23&J23&K23&L23&M23&N23&O23&P23&Q23&R23&S23&T23&U23&V23 -> ORD-2025-100224568145687CUST-3036Sneha KapoorConsumerWestMadhya PradeshIndoreFurnitureFurnishingsEco Furnishings 897Second Class4697.69-0.232790.762037.71753.05PaidCompleted6 | AE23: =IF(COUNTIF($A$2:$A$933,A23)=1,"OK",IF(COUNTIF($AD$2:$AD$933,AD23)>1,"Exact Duplicate", "Review Required")) -> OK | AF23: =IF(P23<0,"Invalid Discount","") -> Invalid Discount | AG23: =IF(P23>1,"Invalid Discount","") | AH23: =IF(V23<1,"Invalid Shipping Record","") | AI23: =IF(ROUND(Q23,2)=ROUND(X23,2),"Match","Mismatch") -> Mismatch | AJ23: =IF(ROUND(S23,2)=ROUND(Y23,2),"Match","Mismatch") -> Mismatch | AK23: =PROPER(TRIM(raw_orders!G23)) -> West | AL23: =PROPER(TRIM(raw_orders!M23)) -> Second Class | AN23: Duplicate Check
A24: ORD-2025-10023 | B24: 45676 | C24: 45678 | D24: CUST-3588 | E24: =PROPER(TRIM(raw_orders!E24)) -> Mira Das | F24: =PROPER(TRIM(raw_orders!F24)) -> Consumer | G24: =PROPER(TRIM(raw_orders!G24)) -> South | H24: =PROPER(TRIM(raw_orders!H24)) -> Telangana | I24: =PROPER(TRIM(raw_orders!I24)) -> Hyderabad | J24: =PROPER(TRIM(raw_orders!J24)) -> Office Supplies | K24: =PROPER(TRIM(raw_orders!K24)) -> Binders | L24: Max Binders 355 | M24: =PROPER(TRIM(raw_orders!M24)) -> Standard Class | N24: 8 | O24: 1219.34 | P24: 0.15 | Q24: 8291.51 | R24: 6685.03 | S24: 1606.48 | T24: =PROPER(TRIM(raw_orders!T24)) -> Failed | U24: =PROPER(TRIM(raw_orders!U24)) -> Returned | V24: =C24-B24 -> 2 | W24: =IF(AND(P24="",Q24<>"",N24<>"",S24<>""),0,IF(OR(P24<0,P24>1),P24,P24)) -> 0.15 | X24: =N24*O24*(1-P24) -> 8291.512 | Y24: =X24-R24 -> 1606.482 | Z24: =Y24/X24 -> 0.19375019 | AA24: =TEXT(B24,"MMMM") -> January | AB24: =YEAR(B24) -> 2025 | AC24: =IF(OR(AF24 = "Invalid Discount",AG24="Invalid Discount",AH24="Invalid Shipping Record",AE24="Review Required"),"Invalid",IF(OR(G24="Unknown",M24="Unknown",ISBLANK(P24)),"Warning","Clean")) -> Clean | AD24: =A24&B24&C24&D24&E24&F24&G24&H24&I24&J24&K24&L24&M24&N24&O24&P24&Q24&R24&S24&T24&U24&V24 -> ORD-2025-100234567645678CUST-3588Mira DasConsumerSouthTelanganaHyderabadOffice SuppliesBindersMax Binders 355Standard Class81219.340.158291.516685.031606.48FailedReturned2 | AE24: =IF(COUNTIF($A$2:$A$933,A24)=1,"OK",IF(COUNTIF($AD$2:$AD$933,AD24)>1,"Exact Duplicate", "Review Required")) -> OK | AF24: =IF(P24<0,"Invalid Discount","") | AG24: =IF(P24>1,"Invalid Discount","") | AH24: =IF(V24<1,"Invalid Shipping Record","") | AI24: =IF(ROUND(Q24,2)=ROUND(X24,2),"Match","Mismatch") -> Match | AJ24: =IF(ROUND(S24,2)=ROUND(Y24,2),"Match","Mismatch") -> Match | AK24: =PROPER(TRIM(raw_orders!G24)) -> South | AL24: =PROPER(TRIM(raw_orders!M24)) -> Standard Class | AN24: OK | AO24: =COUNTIF(AE:AE,"OK") -> 888
A25: ORD-2025-10024 | B25: 45898 | C25: 45900 | D25: CUST-7098 | E25: =PROPER(TRIM(raw_orders!E25)) -> Rahul Verma | F25: =PROPER(TRIM(raw_orders!F25)) -> Home Office | G25: =PROPER(TRIM(raw_orders!G25)) -> East | H25: =PROPER(TRIM(raw_orders!H25)) -> Bihar | I25: =PROPER(TRIM(raw_orders!I25)) -> Patna | J25: =PROPER(TRIM(raw_orders!J25)) -> Furniture | K25: =PROPER(TRIM(raw_orders!K25)) -> Bookcases | L25: Pro Bookcases 394 | M25: =PROPER(TRIM(raw_orders!M25)) -> First Class | N25: 4 | O25: 1958.01 | P25: 0.2 | Q25: 6265.63 | R25: 4321.86 | S25: 1943.77 | T25: =PROPER(TRIM(raw_orders!T25)) -> Paid | U25: =PROPER(TRIM(raw_orders!U25)) -> Completed | V25: =C25-B25 -> 2 | W25: =IF(AND(P25="",Q25<>"",N25<>"",S25<>""),0,IF(OR(P25<0,P25>1),P25,P25)) -> 0.2 | X25: =N25*O25*(1-P25) -> 6265.632 | Y25: =X25-R25 -> 1943.772 | Z25: =Y25/X25 -> 0.3102276 | AA25: =TEXT(B25,"MMMM") -> August | AB25: =YEAR(B25) -> 2025 | AC25: =IF(OR(AF25 = "Invalid Discount",AG25="Invalid Discount",AH25="Invalid Shipping Record",AE25="Review Required"),"Invalid",IF(OR(G25="Unknown",M25="Unknown",ISBLANK(P25)),"Warning","Clean")) -> Clean | AD25: =A25&B25&C25&D25&E25&F25&G25&H25&I25&J25&K25&L25&M25&N25&O25&P25&Q25&R25&S25&T25&U25&V25 -> ORD-2025-100244589845900CUST-7098Rahul VermaHome OfficeEastBiharPatnaFurnitureBookcasesPro Bookcases 394First Class41958.010.26265.634321.861943.77PaidCompleted2 | AE25: =IF(COUNTIF($A$2:$A$933,A25)=1,"OK",IF(COUNTIF($AD$2:$AD$933,AD25)>1,"Exact Duplicate", "Review Required")) -> OK | AF25: =IF(P25<0,"Invalid Discount","") | AG25: =IF(P25>1,"Invalid Discount","") | AH25: =IF(V25<1,"Invalid Shipping Record","") | AI25: =IF(ROUND(Q25,2)=ROUND(X25,2),"Match","Mismatch") -> Match | AJ25: =IF(ROUND(S25,2)=ROUND(Y25,2),"Match","Mismatch") -> Match | AK25: =PROPER(TRIM(raw_orders!G25)) -> East | AL25: =PROPER(TRIM(raw_orders!M25)) -> First Class | AN25: Review Required | AO25: =COUNTIF(AE:AE,"Review Required") -> 24
A26: ORD-2024-10025 | B26: 45355 | C26: 45352 | D26: CUST-1747 | E26: =PROPER(TRIM(raw_orders!E26)) -> Diya Patel | F26: =PROPER(TRIM(raw_orders!F26)) -> Consumer | G26: =PROPER(TRIM(raw_orders!G26)) -> North | H26: =PROPER(TRIM(raw_orders!H26)) -> Punjab | I26: =PROPER(TRIM(raw_orders!I26)) -> Ludhiana | J26: =PROPER(TRIM(raw_orders!J26)) -> Office Supplies | K26: =PROPER(TRIM(raw_orders!K26)) -> Art | L26: Max Art 215 | M26: =PROPER(TRIM(raw_orders!M26)) -> Standard Class | N26: 4 | O26: 4492.94 | P26: 0.25 | Q26: 13478.82 | R26: 10937.35 | S26: 2541.47 | T26: =PROPER(TRIM(raw_orders!T26)) -> Pending | U26: =PROPER(TRIM(raw_orders!U26)) -> Cancelled | V26: =C26-B26 -> -3 | W26: =IF(AND(P26="",Q26<>"",N26<>"",S26<>""),0,IF(OR(P26<0,P26>1),P26,P26)) -> 0.25 | X26: =N26*O26*(1-P26) -> 13478.82 | Y26: =X26-R26 -> 2541.47 | Z26: =Y26/X26 -> 0.18855286 | AA26: =TEXT(B26,"MMMM") -> March | AB26: =YEAR(B26) -> 2024 | AC26: =IF(OR(AF26 = "Invalid Discount",AG26="Invalid Discount",AH26="Invalid Shipping Record",AE26="Review Required"),"Invalid",IF(OR(G26="Unknown",M26="Unknown",ISBLANK(P26)),"Warning","Clean")) -> Invalid | AD26: =A26&B26&C26&D26&E26&F26&G26&H26&I26&J26&K26&L26&M26&N26&O26&P26&Q26&R26&S26&T26&U26&V26 -> ORD-2024-100254535545352CUST-1747Diya PatelConsumerNorthPunjabLudhianaOffice SuppliesArtMax Art 215Standard Class44492.940.2513478.8210937.352541.47PendingCancelled-3 | AE26: =IF(COUNTIF($A$2:$A$933,A26)=1,"OK",IF(COUNTIF($AD$2:$AD$933,AD26)>1,"Exact Duplicate", "Review Required")) -> OK | AF26: =IF(P26<0,"Invalid Discount","") | AG26: =IF(P26>1,"Invalid Discount","") | AH26: =IF(V26<0,"Invalid Shipping Record","") -> Invalid Shipping Record | AI26: =IF(ROUND(Q26,2)=ROUND(X26,2),"Match","Mismatch") -> Match | AJ26: =IF(ROUND(S26,2)=ROUND(Y26,2),"Match","Mismatch") -> Match | AK26: =PROPER(TRIM(raw_orders!G26)) -> North | AL26: =PROPER(TRIM(raw_orders!M26)) -> Standard Class
A27: ORD-2024-10026 | B27: 45606 | C27: 45584 | D27: CUST-1731 | E27: =PROPER(TRIM(raw_orders!E27)) -> Arjun Bose | F27: =PROPER(TRIM(raw_orders!F27)) -> Corporate | G27: =PROPER(TRIM(raw_orders!G27)) -> East | H27: =PROPER(TRIM(raw_orders!H27)) -> Assam | I27: =PROPER(TRIM(raw_orders!I27)) -> Guwahati | J27: =PROPER(TRIM(raw_orders!J27)) -> Technology | K27: =PROPER(TRIM(raw_orders!K27)) -> Accessories | L27: Classic Accessories 478 | M27: =PROPER(TRIM(raw_orders!M27)) -> First Class | N27: 2 | O27: 4315.2 | P27: 0.15 | Q27: 7335.84 | R27: 4968.41 | S27: 2367.43 | T27: =PROPER(TRIM(raw_orders!T27)) -> Paid | U27: =PROPER(TRIM(raw_orders!U27)) -> Completed | V27: =C27-B27 -> -22 | W27: =IF(AND(P27="",Q27<>"",N27<>"",S27<>""),0,IF(OR(P27<0,P27>1),P27,P27)) -> 0.15 | X27: =N27*O27*(1-P27) -> 7335.84 | Y27: =X27-R27 -> 2367.43 | Z27: =Y27/X27 -> 0.32272105 | AA27: =TEXT(B27,"MMMM") -> November | AB27: =YEAR(B27) -> 2024 | AC27: =IF(OR(AF27 = "Invalid Discount",AG27="Invalid Discount",AH27="Invalid Shipping Record",AE27="Review Required"),"Invalid",IF(OR(G27="Unknown",M27="Unknown",ISBLANK(P27)),"Warning","Clean")) -> Invalid | AD27: =A27&B27&C27&D27&E27&F27&G27&H27&I27&J27&K27&L27&M27&N27&O27&P27&Q27&R27&S27&T27&U27&V27 -> ORD-2024-100264560645584CUST-1731Arjun BoseCorporateEastAssamGuwahatiTechnologyAccessoriesClassic Accessories 478First Class24315.20.157335.844968.412367.43PaidCompleted-22 | AE27: =IF(COUNTIF($A$2:$A$933,A27)=1,"OK",IF(COUNTIF($AD$2:$AD$933,AD27)>1,"Exact Duplicate", "Review Required")) -> OK | AF27: =IF(P27<0,"Invalid Discount","") | AG27: =IF(P27>1,"Invalid Discount","") | AH27: =IF(V27<0,"Invalid Shipping Record","") -> Invalid Shipping Record | AI27: =IF(ROUND(Q27,2)=ROUND(X27,2),"Match","Mismatch") -> Match | AJ27: =IF(ROUND(S27,2)=ROUND(Y27,2),"Match","Mismatch") -> Match | AK27: =PROPER(TRIM(raw_orders!G27)) -> East | AL27: =PROPER(TRIM(raw_orders!M27)) -> First Class | AN27: Total Records | AO27: =COUNTA(A2:A913) -> 912
A28: ORD-2024-10027 | B28: 45619 | C28: 45619 | D28: CUST-4401 | E28: =PROPER(TRIM(raw_orders!E28)) -> Diya Patel | F28: =PROPER(TRIM(raw_orders!F28)) -> Corporate | G28: =PROPER(TRIM(raw_orders!G28)) -> North | H28: =PROPER(TRIM(raw_orders!H28)) -> Uttar Pradesh | I28: =PROPER(TRIM(raw_orders!I28)) -> Noida | J28: =PROPER(TRIM(raw_orders!J28)) -> Technology | K28: =PROPER(TRIM(raw_orders!K28)) -> Phones | L28: Pro Phones 243 | M28: =PROPER(TRIM(raw_orders!M28)) -> Standard Class | N28: 4 | O28: 716.13 | P28: 0.1 | Q28: 2578.07 | R28: 1527.55 | S28: 1050.52 | T28: =PROPER(TRIM(raw_orders!T28)) -> Paid | U28: =PROPER(TRIM(raw_orders!U28)) -> Returned | V28: =C28-B28 -> 0 | W28: =IF(AND(P28="",Q28<>"",N28<>"",S28<>""),0,IF(OR(P28<0,P28>1),P28,P28)) -> 0.1 | X28: =N28*O28*(1-P28) -> 2578.068 | Y28: =X28-R28 -> 1050.518 | Z28: =Y28/X28 -> 0.40748266 | AA28: =TEXT(B28,"MMMM") -> November | AB28: =YEAR(B28) -> 2024 | AC28: =IF(OR(AF28 = "Invalid Discount",AG28="Invalid Discount",AH28="Invalid Shipping Record",AE28="Review Required"),"Invalid",IF(OR(G28="Unknown",M28="Unknown",ISBLANK(P28)),"Warning","Clean")) -> Clean | AD28: =A28&B28&C28&D28&E28&F28&G28&H28&I28&J28&K28&L28&M28&N28&O28&P28&Q28&R28&S28&T28&U28&V28 -> ORD-2024-100274561945619CUST-4401Diya PatelCorporateNorthUttar PradeshNoidaTechnologyPhonesPro Phones 243Standard Class4716.130.12578.071527.551050.52PaidReturned0 | AE28: =IF(COUNTIF($A$2:$A$933,A28)=1,"OK",IF(COUNTIF($AD$2:$AD$933,AD28)>1,"Exact Duplicate", "Review Required")) -> OK | AF28: =IF(P28<0,"Invalid Discount","") | AG28: =IF(P28>1,"Invalid Discount","") | AH28: =IF(V28<0,"Invalid Shipping Record","") | AI28: =IF(ROUND(Q28,2)=ROUND(X28,2),"Match","Mismatch") -> Match | AJ28: =IF(ROUND(S28,2)=ROUND(Y28,2),"Match","Mismatch") -> Match | AK28: =PROPER(TRIM(raw_orders!G28)) -> North | AL28: =PROPER(TRIM(raw_orders!M28)) -> Standard Class
A29: ORD-2025-10028 | B29: 45929 | C29: 45787 | D29: CUST-9875 | E29: =PROPER(TRIM(raw_orders!E29)) -> Arjun Bose | F29: =PROPER(TRIM(raw_orders!F29)) -> Small Business | G29: =PROPER(TRIM(raw_orders!G29)) -> South | H29: =PROPER(TRIM(raw_orders!H29)) -> Karnataka | I29: =PROPER(TRIM(raw_orders!I29)) -> Bengaluru | J29: =PROPER(TRIM(raw_orders!J29)) -> Office Supplies | K29: =PROPER(TRIM(raw_orders!K29)) -> Paper | L29: Basic Paper 613 | M29: =PROPER(TRIM(raw_orders!M29)) -> Second Class | N29: 5 | O29: 1806.51 | P29: 0.25 | Q29: 6774.41 | R29: 4710.36 | S29: 2064.05 | T29: =PROPER(TRIM(raw_orders!T29)) -> Failed | U29: =PROPER(TRIM(raw_orders!U29)) -> Returned | V29: =C29-B29 -> -142 | W29: =IF(AND(P29="",Q29<>"",N29<>"",S29<>""),0,IF(OR(P29<0,P29>1),P29,P29)) -> 0.25 | X29: =N29*O29*(1-P29) -> 6774.4125 | Y29: =X29-R29 -> 2064.0525 | Z29: =Y29/X29 -> 0.30468362 | AA29: =TEXT(B29,"MMMM") -> September | AB29: =YEAR(B29) -> 2025 | AC29: =IF(OR(AF29 = "Invalid Discount",AG29="Invalid Discount",AH29="Invalid Shipping Record",AE29="Review Required"),"Invalid",IF(OR(G29="Unknown",M29="Unknown",ISBLANK(P29)),"Warning","Clean")) -> Invalid | AD29: =A29&B29&C29&D29&E29&F29&G29&H29&I29&J29&K29&L29&M29&N29&O29&P29&Q29&R29&S29&T29&U29&V29 -> ORD-2025-100284592945787CUST-9875Arjun BoseSmall BusinessSouthKarnatakaBengaluruOffice SuppliesPaperBasic Paper 613Second Class51806.510.256774.414710.362064.05FailedReturned-142 | AE29: =IF(COUNTIF($A$2:$A$933,A29)=1,"OK",IF(COUNTIF($AD$2:$AD$933,AD29)>1,"Exact Duplicate", "Review Required")) -> OK | AF29: =IF(P29<0,"Invalid Discount","") | AG29: =IF(P29>1,"Invalid Discount","") | AH29: =IF(V29<0,"Invalid Shipping Record","") -> Invalid Shipping Record | AI29: =IF(ROUND(Q29,2)=ROUND(X29,2),"Match","Mismatch") -> Match | AJ29: =IF(ROUND(S29,2)=ROUND(Y29,2),"Match","Mismatch") -> Match | AK29: =PROPER(TRIM(raw_orders!G29)) -> South | AL29: =PROPER(TRIM(raw_orders!M29)) -> Second Class | AN29: Number of Sales mismatched Records | AO29: =COUNTIF(AI:AI,"Mismatch") -> 93
A30: ORD-2024-10029 | B30: 45606 | C30: 45583 | D30: CUST-1569 | E30: =PROPER(TRIM(raw_orders!E30)) -> Ananya Rao | F30: =PROPER(TRIM(raw_orders!F30)) -> Home Office | G30: =PROPER(TRIM(raw_orders!G30)) -> West | H30: =PROPER(TRIM(raw_orders!H30)) -> Gujarat | I30: =PROPER(TRIM(raw_orders!I30)) -> Ahmedabad | J30: =PROPER(TRIM(raw_orders!J30)) -> Technology | K30: =PROPER(TRIM(raw_orders!K30)) -> Phones | L30: Prime Phones 698 | M30: =PROPER(TRIM(raw_orders!M30)) -> Second Class | N30: 2 | O30: 1942.22 | P30: 0.25 | Q30: 2913.33 | R30: 2122.33 | S30: 791 | T30: =PROPER(TRIM(raw_orders!T30)) -> Refunded | U30: =PROPER(TRIM(raw_orders!U30)) -> Cancelled | V30: =C30-B30 -> -23 | W30: =IF(AND(P30="",Q30<>"",N30<>"",S30<>""),0,IF(OR(P30<0,P30>1),P30,P30)) -> 0.25 | X30: =N30*O30*(1-P30) -> 2913.33 | Y30: =X30-R30 -> 791 | Z30: =Y30/X30 -> 0.27151061 | AA30: =TEXT(B30,"MMMM") -> November | AB30: =YEAR(B30) -> 2024 | AC30: =IF(OR(AF30 = "Invalid Discount",AG30="Invalid Discount",AH30="Invalid Shipping Record",AE30="Review Required"),"Invalid",IF(OR(G30="Unknown",M30="Unknown",ISBLANK(P30)),"Warning","Clean")) -> Invalid | AD30: =A30&B30&C30&D30&E30&F30&G30&H30&I30&J30&K30&L30&M30&N30&O30&P30&Q30&R30&S30&T30&U30&V30 -> ORD-2024-100294560645583CUST-1569Ananya RaoHome OfficeWestGujaratAhmedabadTechnologyPhonesPrime Phones 698Second Class21942.220.252913.332122.33791RefundedCancelled-23 | AE30: =IF(COUNTIF($A$2:$A$933,A30)=1,"OK",IF(COUNTIF($AD$2:$AD$933,AD30)>1,"Exact Duplicate", "Review Required")) -> OK | AF30: =IF(P30<0,"Invalid Discount","") | AG30: =IF(P30>1,"Invalid Discount","") | AH30: =IF(V30<0,"Invalid Shipping Record","") -> Invalid Shipping Record | AI30: =IF(ROUND(Q30,2)=ROUND(X30,2),"Match","Mismatch") -> Match | AJ30: =IF(ROUND(S30,2)=ROUND(Y30,2),"Match","Mismatch") -> Match | AK30: =PROPER(TRIM(raw_orders!G30)) -> West | AL30: =PROPER(TRIM(raw_orders!M30)) -> Second Class
A31: ORD-2025-10030 | B31: 45882 | C31: 45882 | D31: CUST-5936 | E31: =PROPER(TRIM(raw_orders!E31)) -> Rohan Mehta | F31: =PROPER(TRIM(raw_orders!F31)) -> Home Office | G31: =PROPER(TRIM(raw_orders!G31)) -> South | H31: =PROPER(TRIM(raw_orders!H31)) -> Kerala | I31: =PROPER(TRIM(raw_orders!I31)) -> Kochi | J31: =PROPER(TRIM(raw_orders!J31)) -> Technology | K31: =PROPER(TRIM(raw_orders!K31)) -> Phones | L31: Pro Phones 442 | M31: =PROPER(TRIM(raw_orders!M31)) -> Standard Class | N31: 1 | O31: 256.01 | P31: 0.15 | Q31: 217.61 | R31: 119.77 | S31: 97.84 | T31: =PROPER(TRIM(raw_orders!T31)) -> Paid | U31: =PROPER(TRIM(raw_orders!U31)) -> Completed | V31: =C31-B31 -> 0 | W31: =IF(AND(P31="",Q31<>"",N31<>"",S31<>""),0,IF(OR(P31<0,P31>1),P31,P31)) -> 0.15 | X31: =N31*O31*(1-P31) -> 217.6085 | Y31: =X31-R31 -> 97.8385 | Z31: =Y31/X31 -> 0.4496079 | AA31: =TEXT(B31,"MMMM") -> August | AB31: =YEAR(B31) -> 2025 | AC31: =IF(OR(AF31 = "Invalid Discount",AG31="Invalid Discount",AH31="Invalid Shipping Record",AE31="Review Required"),"Invalid",IF(OR(G31="Unknown",M31="Unknown",ISBLANK(P31)),"Warning","Clean")) -> Clean | AD31: =A31&B31&C31&D31&E31&F31&G31&H31&I31&J31&K31&L31&M31&N31&O31&P31&Q31&R31&S31&T31&U31&V31 -> ORD-2025-100304588245882CUST-5936Rohan MehtaHome OfficeSouthKeralaKochiTechnologyPhonesPro Phones 442Standard Class1256.010.15217.61119.7797.84PaidCompleted0 | AE31: =IF(COUNTIF($A$2:$A$933,A31)=1,"OK",IF(COUNTIF($AD$2:$AD$933,AD31)>1,"Exact Duplicate", "Review Required")) -> OK | AF31: =IF(P31<0,"Invalid Discount","") | AG31: =IF(P31>1,"Invalid Discount","") | AH31: =IF(V31<0,"Invalid Shipping Record","") | AI31: =IF(ROUND(Q31,2)=ROUND(X31,2),"Match","Mismatch") -> Match | AJ31: =IF(ROUND(S31,2)=ROUND(Y31,2),"Match","Mismatch") -> Match | AK31: =PROPER(TRIM(raw_orders!G31)) -> South | AL31: =PROPER(TRIM(raw_orders!M31)) -> Standard Class | AN31: Number of Profit mismatched Records | AO31: =COUNTIF(AJ:AJ,"Mismatch") -> 94
A32: ORD-2024-10031 | B32: 45331 | C32: 45334 | D32: CUST-8759 | E32: =PROPER(TRIM(raw_orders!E32)) -> Ananya Rao | F32: =PROPER(TRIM(raw_orders!F32)) -> Corporate | G32: =PROPER(TRIM(raw_orders!G32)) -> West | H32: =PROPER(TRIM(raw_orders!H32)) -> Goa | I32: =PROPER(TRIM(raw_orders!I32)) -> Panaji | J32: =PROPER(TRIM(raw_orders!J32)) -> Office Supplies | K32: =PROPER(TRIM(raw_orders!K32)) -> Labels | L32: Pro Labels 355 | M32: =PROPER(TRIM(raw_orders!M32)) -> First Class | N32: 1 | O32: 3421.77 | P32: 0.1 | Q32: 3079.59 | R32: 2001.89 | S32: 1077.7 | T32: =PROPER(TRIM(raw_orders!T32)) -> Paid | U32: =PROPER(TRIM(raw_orders!U32)) -> Completed | V32: =C32-B32 -> 3 | W32: =IF(AND(P32="",Q32<>"",N32<>"",S32<>""),0,IF(OR(P32<0,P32>1),P32,P32)) -> 0.1 | X32: =N32*O32*(1-P32) -> 3079.593 | Y32: =X32-R32 -> 1077.703 | Z32: =Y32/X32 -> 0.34994981 | AA32: =TEXT(B32,"MMMM") -> February | AB32: =YEAR(B32) -> 2024 | AC32: =IF(OR(AF32 = "Invalid Discount",AG32="Invalid Discount",AH32="Invalid Shipping Record",AE32="Review Required"),"Invalid",IF(OR(G32="Unknown",M32="Unknown",ISBLANK(P32)),"Warning","Clean")) -> Clean | AD32: =A32&B32&C32&D32&E32&F32&G32&H32&I32&J32&K32&L32&M32&N32&O32&P32&Q32&R32&S32&T32&U32&V32 -> ORD-2024-100314533145334CUST-8759Ananya RaoCorporateWestGoaPanajiOffice SuppliesLabelsPro Labels 355First Class13421.770.13079.592001.891077.7PaidCompleted3 | AE32: =IF(COUNTIF($A$2:$A$933,A32)=1,"OK",IF(COUNTIF($AD$2:$AD$933,AD32)>1,"Exact Duplicate", "Review Required")) -> OK | AF32: =IF(P32<0,"Invalid Discount","") | AG32: =IF(P32>1,"Invalid Discount","") | AH32: =IF(V32<1,"Invalid Shipping Record","") | AI32: =IF(ROUND(Q32,2)=ROUND(X32,2),"Match","Mismatch") -> Match | AJ32: =IF(ROUND(S32,2)=ROUND(Y32,2),"Match","Mismatch") -> Match | AK32: =PROPER(TRIM(raw_orders!G32)) -> West | AL32: =PROPER(TRIM(raw_orders!M32)) -> First Class
A33: ORD-2025-10032 | B33: 45823 | C33: 45827 | D33: CUST-7867 | E33: =PROPER(TRIM(raw_orders!E33)) -> Karan Malhotra | F33: =PROPER(TRIM(raw_orders!F33)) -> Small Business | G33: =PROPER(TRIM(raw_orders!G33)) -> West | H33: =PROPER(TRIM(raw_orders!H33)) -> Madhya Pradesh | I33: =PROPER(TRIM(raw_orders!I33)) -> Indore | J33: =PROPER(TRIM(raw_orders!J33)) -> Office Supplies | K33: =PROPER(TRIM(raw_orders!K33)) -> Paper | L33: Pro Paper 959 | M33: =PROPER(TRIM(raw_orders!M33)) -> Second Class | N33: 9 | O33: 3092.55 | P33: 0 | Q33: 27832.95 | R33: 17769.75 | S33: 10063.2 | T33: =PROPER(TRIM(raw_orders!T33)) -> Failed | U33: =PROPER(TRIM(raw_orders!U33)) -> Returned | V33: =C33-B33 -> 4 | W33: =IF(AND(P33="",Q33<>"",N33<>"",S33<>""),0,IF(OR(P33<0,P33>1),P33,P33)) -> 0 | X33: =N33*O33*(1-P33) -> 27832.95 | Y33: =X33-R33 -> 10063.2 | Z33: =Y33/X33 -> 0.36155708 | AA33: =TEXT(B33,"MMMM") -> June | AB33: =YEAR(B33) -> 2025 | AC33: =IF(OR(AF33 = "Invalid Discount",AG33="Invalid Discount",AH33="Invalid Shipping Record",AE33="Review Required"),"Invalid",IF(OR(G33="Unknown",M33="Unknown",ISBLANK(P33)),"Warning","Clean")) -> Clean | AD33: =A33&B33&C33&D33&E33&F33&G33&H33&I33&J33&K33&L33&M33&N33&O33&P33&Q33&R33&S33&T33&U33&V33 -> ORD-2025-100324582345827CUST-7867Karan MalhotraSmall BusinessWestMadhya PradeshIndoreOffice SuppliesPaperPro Paper 959Second Class93092.55027832.9517769.7510063.2FailedReturned4 | AE33: =IF(COUNTIF($A$2:$A$933,A33)=1,"OK",IF(COUNTIF($AD$2:$AD$933,AD33)>1,"Exact Duplicate", "Review Required")) -> OK | AF33: =IF(P33<0,"Invalid Discount","") | AG33: =IF(P33>1,"Invalid Discount","") | AH33: =IF(V33<1,"Invalid Shipping Record","") | AI33: =IF(ROUND(Q33,2)=ROUND(X33,2),"Match","Mismatch") -> Match | AJ33: =IF(ROUND(S33,2)=ROUND(Y33,2),"Match","Mismatch") -> Match | AK33: =PROPER(TRIM(raw_orders!G33)) -> West | AL33: =PROPER(TRIM(raw_orders!M33)) -> Second Class | AN33: Number of records with both sales and profit mismatch | AO33: =COUNTIFS(AI:AI,"Mismatch",AJ:AJ,"Mismatch") -> 75
A34: ORD-2024-10033 | B34: 45618 | C34: 45622 | D34: CUST-6509 | E34: =PROPER(TRIM(raw_orders!E34)) -> Aarav Sharma | F34: =PROPER(TRIM(raw_orders!F34)) -> Corporate | G34: =PROPER(TRIM(raw_orders!G34)) -> South | H34: =PROPER(TRIM(raw_orders!H34)) -> Andhra Pradesh | I34: =PROPER(TRIM(raw_orders!I34)) -> Vijayawada | J34: =PROPER(TRIM(raw_orders!J34)) -> Technology | K34: =PROPER(TRIM(raw_orders!K34)) -> Phones | L34: Basic Phones 242 | M34: =PROPER(TRIM(raw_orders!M34)) -> Second Class | N34: 3 | O34: 4001.25 | Q34: 9002.81 | R34: 7529.92 | S34: 1472.89 | T34: =PROPER(TRIM(raw_orders!T34)) -> Paid | U34: =PROPER(TRIM(raw_orders!U34)) -> Completed | V34: =C34-B34 -> 4 | W34: =IF(AND(P34="",Q34<>"",N34<>"",S34<>""),0,IF(OR(P34<0,P34>1),P34,P34)) -> 0 | X34: =N34*O34*(1-P34) -> 12003.75 | Y34: =X34-R34 -> 4473.83 | Z34: =Y34/X34 -> 0.3727027 | AA34: =TEXT(B34,"MMMM") -> November | AB34: =YEAR(B34) -> 2024 | AC34: =IF(OR(AF34 = "Invalid Discount",AG34="Invalid Discount",AH34="Invalid Shipping Record",AE34="Review Required"),"Invalid",IF(OR(G34="Unknown",M34="Unknown",ISBLANK(P34)),"Warning","Clean")) -> Warning | AD34: =A34&B34&C34&D34&E34&F34&G34&H34&I34&J34&K34&L34&M34&N34&O34&P34&Q34&R34&S34&T34&U34&V34 -> ORD-2024-100334561845622CUST-6509Aarav SharmaCorporateSouthAndhra PradeshVijayawadaTechnologyPhonesBasic Phones 242Second Class34001.259002.817529.921472.89PaidCompleted4 | AE34: =IF(COUNTIF($A$2:$A$933,A34)=1,"OK",IF(COUNTIF($AD$2:$AD$933,AD34)>1,"Exact Duplicate", "Review Required")) -> OK | AF34: =IF(P34<0,"Invalid Discount","") | AG34: =IF(P34>1,"Invalid Discount","") | AH34: =IF(V34<1,"Invalid Shipping Record","") | AI34: =IF(ROUND(Q34,2)=ROUND(X34,2),"Match","Mismatch") -> Mismatch | AJ34: =IF(ROUND(S34,2)=ROUND(Y34,2),"Match","Mismatch") -> Mismatch | AK34: =PROPER(TRIM(raw_orders!G34)) -> South | AL34: =PROPER(TRIM(raw_orders!M34)) -> Second Class
A35: ORD-2024-10034 | B35: 45495 | C35: 45500 | D35: CUST-6660 | E35: =PROPER(TRIM(raw_orders!E35)) -> Priya Menon | F35: =PROPER(TRIM(raw_orders!F35)) -> Home Office | G35: =PROPER(TRIM(raw_orders!G35)) -> West | H35: =PROPER(TRIM(raw_orders!H35)) -> Goa | I35: =PROPER(TRIM(raw_orders!I35)) -> Panaji | J35: =PROPER(TRIM(raw_orders!J35)) -> Furniture | K35: =PROPER(TRIM(raw_orders!K35)) -> Tables | L35: Max Tables 836 | M35: =PROPER(TRIM(raw_orders!M35)) -> Same Day | N35: 7 | O35: 492.41 | P35: 0.25 | Q35: 2585.15 | R35: 2070.73 | S35: 514.42 | T35: =PROPER(TRIM(raw_orders!T35)) -> Paid | U35: =PROPER(TRIM(raw_orders!U35)) -> Completed | V35: =C35-B35 -> 5 | W35: =IF(AND(P35="",Q35<>"",N35<>"",S35<>""),0,IF(OR(P35<0,P35>1),P35,P35)) -> 0.25 | X35: =N35*O35*(1-P35) -> 2585.1525 | Y35: =X35-R35 -> 514.4225 | Z35: =Y35/X35 -> 0.19899116 | AA35: =TEXT(B35,"MMMM") -> July | AB35: =YEAR(B35) -> 2024 | AC35: =IF(OR(AF35 = "Invalid Discount",AG35="Invalid Discount",AH35="Invalid Shipping Record",AE35="Review Required"),"Invalid",IF(OR(G35="Unknown",M35="Unknown",ISBLANK(P35)),"Warning","Clean")) -> Clean | AD35: =A35&B35&C35&D35&E35&F35&G35&H35&I35&J35&K35&L35&M35&N35&O35&P35&Q35&R35&S35&T35&U35&V35 -> ORD-2024-100344549545500CUST-6660Priya MenonHome OfficeWestGoaPanajiFurnitureTablesMax Tables 836Same Day7492.410.252585.152070.73514.42PaidCompleted5 | AE35: =IF(COUNTIF($A$2:$A$933,A35)=1,"OK",IF(COUNTIF($AD$2:$AD$933,AD35)>1,"Exact Duplicate", "Review Required")) -> OK | AF35: =IF(P35<0,"Invalid Discount","") | AG35: =IF(P35>1,"Invalid Discount","") | AH35: =IF(V35<1,"Invalid Shipping Record","") | AI35: =IF(ROUND(Q35,2)=ROUND(X35,2),"Match","Mismatch") -> Match | AJ35: =IF(ROUND(S35,2)=ROUND(Y35,2),"Match","Mismatch") -> Match | AK35: =PROPER(TRIM(raw_orders!G35)) -> West | AL35: =PROPER(TRIM(raw_orders!M35)) -> Same Day
A36: ORD-2025-10035 | B36: 45688 | C36: 45693 | D36: CUST-2392 | E36: =PROPER(TRIM(raw_orders!E36)) -> Priya Menon | F36: =PROPER(TRIM(raw_orders!F36)) -> Home Office | G36: =PROPER(TRIM(raw_orders!G36)) -> East | H36: =PROPER(TRIM(raw_orders!H36)) -> West Bengal | I36: =PROPER(TRIM(raw_orders!I36)) -> Kolkata | J36: =PROPER(TRIM(raw_orders!J36)) -> Furniture | K36: =PROPER(TRIM(raw_orders!K36)) -> Chairs | L36: Elite Chairs 862 | M36: Unknown | N36: 2 | O36: 4159.69 | P36: 0.2 | Q36: 6655.5 | R36: 4340.21 | S36: 2607.32 | T36: =PROPER(TRIM(raw_orders!T36)) -> Paid | U36: =PROPER(TRIM(raw_orders!U36)) -> Completed | V36: =C36-B36 -> 5 | W36: =IF(AND(P36="",Q36<>"",N36<>"",S36<>""),0,IF(OR(P36<0,P36>1),P36,P36)) -> 0.2 | X36: =N36*O36*(1-P36) -> 6655.504 | Y36: =X36-R36 -> 2315.294 | Z36: =Y36/X36 -> 0.34787658 | AA36: =TEXT(B36,"MMMM") -> January | AB36: =YEAR(B36) -> 2025 | AC36: =IF(OR(AF36 = "Invalid Discount",AG36="Invalid Discount",AH36="Invalid Shipping Record",AE36="Review Required"),"Invalid",IF(OR(G36="Unknown",M36="Unknown",ISBLANK(P36)),"Warning","Clean")) -> Warning | AD36: =A36&B36&C36&D36&E36&F36&G36&H36&I36&J36&K36&L36&M36&N36&O36&P36&Q36&R36&S36&T36&U36&V36 -> ORD-2025-100354568845693CUST-2392Priya MenonHome OfficeEastWest BengalKolkataFurnitureChairsElite Chairs 862Unknown24159.690.26655.54340.212607.32PaidCompleted5 | AE36: =IF(COUNTIF($A$2:$A$933,A36)=1,"OK",IF(COUNTIF($AD$2:$AD$933,AD36)>1,"Exact Duplicate", "Review Required")) -> OK | AF36: =IF(P36<0,"Invalid Discount","") | AG36: =IF(P36>1,"Invalid Discount","") | AH36: =IF(V36<1,"Invalid Shipping Record","") | AI36: =IF(ROUND(Q36,2)=ROUND(X36,2),"Match","Mismatch") -> Match | AJ36: =IF(ROUND(S36,2)=ROUND(Y36,2),"Match","Mismatch") -> Mismatch | AK36: =PROPER(TRIM(raw_orders!G36)) -> East | AL36: =PROPER(TRIM(raw_orders!M36))
A37: ORD-2024-10036 | B37: 45441 | C37: 45441 | D37: CUST-1611 | E37: =PROPER(TRIM(raw_orders!E37)) -> Sneha Kapoor | F37: =PROPER(TRIM(raw_orders!F37)) -> Small Business | G37: =PROPER(TRIM(raw_orders!G37)) -> West | H37: =PROPER(TRIM(raw_orders!H37)) -> Gujarat | I37: =PROPER(TRIM(raw_orders!I37)) -> Ahmedabad | J37: =PROPER(TRIM(raw_orders!J37)) -> Furniture | K37: =PROPER(TRIM(raw_orders!K37)) -> Bookcases | L37: Prime Bookcases 414 | M37: =PROPER(TRIM(raw_orders!M37)) -> Second Class | N37: 8 | O37: 2507.12 | P37: 0.05 | Q37: 19054.11 | R37: 15313.83 | S37: 3740.28 | T37: =PROPER(TRIM(raw_orders!T37)) -> Pending | U37: =PROPER(TRIM(raw_orders!U37)) -> Returned | V37: =C37-B37 -> 0 | W37: =IF(AND(P37="",Q37<>"",N37<>"",S37<>""),0,IF(OR(P37<0,P37>1),P37,P37)) -> 0.05 | X37: =N37*O37*(1-P37) -> 19054.112 | Y37: =X37-R37 -> 3740.282 | Z37: =Y37/X37 -> 0.19629789 | AA37: =TEXT(B37,"MMMM") -> May | AB37: =YEAR(B37) -> 2024 | AC37: =IF(OR(AF37 = "Invalid Discount",AG37="Invalid Discount",AH37="Invalid Shipping Record",AE37="Review Required"),"Invalid",IF(OR(G37="Unknown",M37="Unknown",ISBLANK(P37)),"Warning","Clean")) -> Clean | AD37: =A37&B37&C37&D37&E37&F37&G37&H37&I37&J37&K37&L37&M37&N37&O37&P37&Q37&R37&S37&T37&U37&V37 -> ORD-2024-100364544145441CUST-1611Sneha KapoorSmall BusinessWestGujaratAhmedabadFurnitureBookcasesPrime Bookcases 414Second Class82507.120.0519054.1115313.833740.28PendingReturned0 | AE37: =IF(COUNTIF($A$2:$A$933,A37)=1,"OK",IF(COUNTIF($AD$2:$AD$933,AD37)>1,"Exact Duplicate", "Review Required")) -> OK | AF37: =IF(P37<0,"Invalid Discount","") | AG37: =IF(P37>1,"Invalid Discount","") | AH37: =IF(V37<0,"Invalid Shipping Record","") | AI37: =IF(ROUND(Q37,2)=ROUND(X37,2),"Match","Mismatch") -> Match | AJ37: =IF(ROUND(S37,2)=ROUND(Y37,2),"Match","Mismatch") -> Match | AK37: =PROPER(TRIM(raw_orders!G37)) -> West | AL37: =PROPER(TRIM(raw_orders!M37)) -> Second Class
A38: ORD-2024-10037 | B38: 45590 | C38: 45593 | D38: CUST-8296 | E38: =PROPER(TRIM(raw_orders!E38)) -> Rohan Mehta | F38: =PROPER(TRIM(raw_orders!F38)) -> Corporate | G38: =PROPER(TRIM(raw_orders!G38)) -> West | H38: =PROPER(TRIM(raw_orders!H38)) -> Maharashtra | I38: =PROPER(TRIM(raw_orders!I38)) -> Mumbai | J38: =PROPER(TRIM(raw_orders!J38)) -> Furniture | K38: =PROPER(TRIM(raw_orders!K38)) -> Bookcases | L38: Eco Bookcases 220 | M38: =PROPER(TRIM(raw_orders!M38)) -> Second Class | N38: 3 | O38: 3126.47 | P38: 0 | Q38: 9379.41 | R38: 6670.85 | S38: 2708.56 | T38: =PROPER(TRIM(raw_orders!T38)) -> Paid | U38: =PROPER(TRIM(raw_orders!U38)) -> Returned | V38: =C38-B38 -> 3 | W38: =IF(AND(P38="",Q38<>"",N38<>"",S38<>""),0,IF(OR(P38<0,P38>1),P38,P38)) -> 0 | X38: =N38*O38*(1-P38) -> 9379.41 | Y38: =X38-R38 -> 2708.56 | Z38: =Y38/X38 -> 0.28877723 | AA38: =TEXT(B38,"MMMM") -> October | AB38: =YEAR(B38) -> 2024 | AC38: =IF(OR(AF38 = "Invalid Discount",AG38="Invalid Discount",AH38="Invalid Shipping Record",AE38="Review Required"),"Invalid",IF(OR(G38="Unknown",M38="Unknown",ISBLANK(P38)),"Warning","Clean")) -> Clean | AD38: =A38&B38&C38&D38&E38&F38&G38&H38&I38&J38&K38&L38&M38&N38&O38&P38&Q38&R38&S38&T38&U38&V38 -> ORD-2024-100374559045593CUST-8296Rohan MehtaCorporateWestMaharashtraMumbaiFurnitureBookcasesEco Bookcases 220Second Class33126.4709379.416670.852708.56PaidReturned3 | AE38: =IF(COUNTIF($A$2:$A$933,A38)=1,"OK",IF(COUNTIF($AD$2:$AD$933,AD38)>1,"Exact Duplicate", "Review Required")) -> OK | AF38: =IF(P38<0,"Invalid Discount","") | AG38: =IF(P38>1,"Invalid Discount","") | AH38: =IF(V38<1,"Invalid Shipping Record","") | AI38: =IF(ROUND(Q38,2)=ROUND(X38,2),"Match","Mismatch") -> Match | AJ38: =IF(ROUND(S38,2)=ROUND(Y38,2),"Match","Mismatch") -> Match | AK38: =PROPER(TRIM(raw_orders!G38)) -> West | AL38: =PROPER(TRIM(raw_orders!M38)) -> Second Class
A39: ORD-2025-10038 | B39: 45867 | C39: 45867 | D39: CUST-4646 | E39: =PROPER(TRIM(raw_orders!E39)) -> Diya Patel | F39: =PROPER(TRIM(raw_orders!F39)) -> Consumer | G39: =PROPER(TRIM(raw_orders!G39)) -> West | H39: =PROPER(TRIM(raw_orders!H39)) -> Maharashtra | I39: =PROPER(TRIM(raw_orders!I39)) -> Mumbai | J39: =PROPER(TRIM(raw_orders!J39)) -> Technology | K39: =PROPER(TRIM(raw_orders!K39)) -> Copiers | L39: Pro Copiers 830 | M39: =PROPER(TRIM(raw_orders!M39)) -> Standard Class | N39: 4 | O39: 1327.54 | P39: 0.2 | Q39: 4248.13 | R39: 3321.09 | S39: 927.04 | T39: =PROPER(TRIM(raw_orders!T39)) -> Paid | U39: =PROPER(TRIM(raw_orders!U39)) -> Completed | V39: =C39-B39 -> 0 | W39: =IF(AND(P39="",Q39<>"",N39<>"",S39<>""),0,IF(OR(P39<0,P39>1),P39,P39)) -> 0.2 | X39: =N39*O39*(1-P39) -> 4248.128 | Y39: =X39-R39 -> 927.038 | Z39: =Y39/X39 -> 0.21822271 | AA39: =TEXT(B39,"MMMM") -> July | AB39: =YEAR(B39) -> 2025 | AC39: =IF(OR(AF39 = "Invalid Discount",AG39="Invalid Discount",AH39="Invalid Shipping Record",AE39="Review Required"),"Invalid",IF(OR(G39="Unknown",M39="Unknown",ISBLANK(P39)),"Warning","Clean")) -> Clean | AD39: =A39&B39&C39&D39&E39&F39&G39&H39&I39&J39&K39&L39&M39&N39&O39&P39&Q39&R39&S39&T39&U39&V39 -> ORD-2025-100384586745867CUST-4646Diya PatelConsumerWestMaharashtraMumbaiTechnologyCopiersPro Copiers 830Standard Class41327.540.24248.133321.09927.04PaidCompleted0 | AE39: =IF(COUNTIF($A$2:$A$933,A39)=1,"OK",IF(COUNTIF($AD$2:$AD$933,AD39)>1,"Exact Duplicate", "Review Required")) -> OK | AF39: =IF(P39<0,"Invalid Discount","") | AG39: =IF(P39>1,"Invalid Discount","") | AH39: =IF(V39<0,"Invalid Shipping Record","") | AI39: =IF(ROUND(Q39,2)=ROUND(X39,2),"Match","Mismatch") -> Match | AJ39: =IF(ROUND(S39,2)=ROUND(Y39,2),"Match","Mismatch") -> Match | AK39: =PROPER(TRIM(raw_orders!G39)) -> West | AL39: =PROPER(TRIM(raw_orders!M39)) -> Standard Class
A40: ORD-2024-10039 | B40: 45460 | C40: 45465 | D40: CUST-8235 | E40: =PROPER(TRIM(raw_orders!E40)) -> Aarav Sharma | F40: =PROPER(TRIM(raw_orders!F40)) -> Corporate | G40: =PROPER(TRIM(raw_orders!G40)) -> West | H40: =PROPER(TRIM(raw_orders!H40)) -> Gujarat | I40: =PROPER(TRIM(raw_orders!I40)) -> Ahmedabad | J40: =PROPER(TRIM(raw_orders!J40)) -> Technology | K40: =PROPER(TRIM(raw_orders!K40)) -> Phones | L40: Prime Phones 507 | M40: =PROPER(TRIM(raw_orders!M40)) -> First Class | N40: 7 | O40: 2210.68 | P40: 0.1 | Q40: 13927.28 | R40: 10504.87 | S40: 3422.41 | T40: =PROPER(TRIM(raw_orders!T40)) -> Paid | U40: =PROPER(TRIM(raw_orders!U40)) -> Completed | V40: =C40-B40 -> 5 | W40: =IF(AND(P40="",Q40<>"",N40<>"",S40<>""),0,IF(OR(P40<0,P40>1),P40,P40)) -> 0.1 | X40: =N40*O40*(1-P40) -> 13927.284 | Y40: =X40-R40 -> 3422.414 | Z40: =Y40/X40 -> 0.24573449 | AA40: =TEXT(B40,"MMMM") -> June | AB40: =YEAR(B40) -> 2024 | AC40: =IF(OR(AF40 = "Invalid Discount",AG40="Invalid Discount",AH40="Invalid Shipping Record",AE40="Review Required"),"Invalid",IF(OR(G40="Unknown",M40="Unknown",ISBLANK(P40)),"Warning","Clean")) -> Clean | AD40: =A40&B40&C40&D40&E40&F40&G40&H40&I40&J40&K40&L40&M40&N40&O40&P40&Q40&R40&S40&T40&U40&V40 -> ORD-2024-100394546045465CUST-8235Aarav SharmaCorporateWestGujaratAhmedabadTechnologyPhonesPrime Phones 507First Class72210.680.113927.2810504.873422.41PaidCompleted5 | AE40: =IF(COUNTIF($A$2:$A$933,A40)=1,"OK",IF(COUNTIF($AD$2:$AD$933,AD40)>1,"Exact Duplicate", "Review Required")) -> OK | AF40: =IF(P40<0,"Invalid Discount","") | AG40: =IF(P40>1,"Invalid Discount","") | AH40: =IF(V40<1,"Invalid Shipping Record","") | AI40: =IF(ROUND(Q40,2)=ROUND(X40,2),"Match","Mismatch") -> Match | AJ40: =IF(ROUND(S40,2)=ROUND(Y40,2),"Match","Mismatch") -> Match | AK40: =PROPER(TRIM(raw_orders!G40)) -> West | AL40: =PROPER(TRIM(raw_orders!M40)) -> First Class
A41: ORD-2024-10040 | B41: 45637 | C41: 45637 | D41: CUST-5830 | E41: =PROPER(TRIM(raw_orders!E41)) -> Mira Das | F41: =PROPER(TRIM(raw_orders!F41)) -> Small Business | G41: =PROPER(TRIM(raw_orders!G41)) -> West | H41: =PROPER(TRIM(raw_orders!H41)) -> Madhya Pradesh | I41: =PROPER(TRIM(raw_orders!I41)) -> Indore | J41: =PROPER(TRIM(raw_orders!J41)) -> Technology | K41: =PROPER(TRIM(raw_orders!K41)) -> Copiers | L41: Classic Copiers 590 | M41: =PROPER(TRIM(raw_orders!M41)) -> First Class | N41: 4 | O41: 1370.92 | P41: 0.1 | Q41: 4935.31 | R41: 3374.77 | S41: 1560.54 | T41: =PROPER(TRIM(raw_orders!T41)) -> Pending | U41: =PROPER(TRIM(raw_orders!U41)) -> Returned | V41: =C41-B41 -> 0 | W41: =IF(AND(P41="",Q41<>"",N41<>"",S41<>""),0,IF(OR(P41<0,P41>1),P41,P41)) -> 0.1 | X41: =N41*O41*(1-P41) -> 4935.312 | Y41: =X41-R41 -> 1560.542 | Z41: =Y41/X41 -> 0.31619926 | AA41: =TEXT(B41,"MMMM") -> December | AB41: =YEAR(B41) -> 2024 | AC41: =IF(OR(AF41 = "Invalid Discount",AG41="Invalid Discount",AH41="Invalid Shipping Record",AE41="Review Required"),"Invalid",IF(OR(G41="Unknown",M41="Unknown",ISBLANK(P41)),"Warning","Clean")) -> Clean | AD41: =A41&B41&C41&D41&E41&F41&G41&H41&I41&J41&K41&L41&M41&N41&O41&P41&Q41&R41&S41&T41&U41&V41 -> ORD-2024-100404563745637CUST-5830Mira DasSmall BusinessWestMadhya PradeshIndoreTechnologyCopiersClassic Copiers 590First Class41370.920.14935.313374.771560.54PendingReturned0 | AE41: =IF(COUNTIF($A$2:$A$933,A41)=1,"OK",IF(COUNTIF($AD$2:$AD$933,AD41)>1,"Exact Duplicate", "Review Required")) -> OK | AF41: =IF(P41<0,"Invalid Discount","") | AG41: =IF(P41>1,"Invalid Discount","") | AH41: =IF(V41<0,"Invalid Shipping Record","") | AI41: =IF(ROUND(Q41,2)=ROUND(X41,2),"Match","Mismatch") -> Match | AJ41: =IF(ROUND(S41,2)=ROUND(Y41,2),"Match","Mismatch") -> Match | AK41: =PROPER(TRIM(raw_orders!G41)) -> West | AL41: =PROPER(TRIM(raw_orders!M41)) -> First Class
A42: ORD-2024-10041 | B42: 45575 | C42: 45581 | D42: CUST-7178 | E42: =PROPER(TRIM(raw_orders!E42)) -> Isha Nair | F42: =PROPER(TRIM(raw_orders!F42)) -> Home Office | G42: =PROPER(TRIM(raw_orders!G42)) -> West | H42: =PROPER(TRIM(raw_orders!H42)) -> Rajasthan | I42: =PROPER(TRIM(raw_orders!I42)) -> Udaipur | J42: =PROPER(TRIM(raw_orders!J42)) -> Technology | K42: =PROPER(TRIM(raw_orders!K42)) -> Copiers | L42: Eco Copiers 865 | M42: =PROPER(TRIM(raw_orders!M42)) -> Standard Class | N42: 7 | O42: 2509.27 | P42: 0.2 | Q42: 14051.91 | R42: 11990.37 | S42: 2061.54 | T42: =PROPER(TRIM(raw_orders!T42)) -> Paid | U42: =PROPER(TRIM(raw_orders!U42)) -> Completed | V42: =C42-B42 -> 6 | W42: =IF(AND(P42="",Q42<>"",N42<>"",S42<>""),0,IF(OR(P42<0,P42>1),P42,P42)) -> 0.2 | X42: =N42*O42*(1-P42) -> 14051.912 | Y42: =X42-R42 -> 2061.542 | Z42: =Y42/X42 -> 0.146709 | AA42: =TEXT(B42,"MMMM") -> October | AB42: =YEAR(B42) -> 2024 | AC42: =IF(OR(AF42 = "Invalid Discount",AG42="Invalid Discount",AH42="Invalid Shipping Record",AE42="Review Required"),"Invalid",IF(OR(G42="Unknown",M42="Unknown",ISBLANK(P42)),"Warning","Clean")) -> Clean | AD42: =A42&B42&C42&D42&E42&F42&G42&H42&I42&J42&K42&L42&M42&N42&O42&P42&Q42&R42&S42&T42&U42&V42 -> ORD-2024-100414557545581CUST-7178Isha NairHome OfficeWestRajasthanUdaipurTechnologyCopiersEco Copiers 865Standard Class72509.270.214051.9111990.372061.54PaidCompleted6 | AE42: =IF(COUNTIF($A$2:$A$933,A42)=1,"OK",IF(COUNTIF($AD$2:$AD$933,AD42)>1,"Exact Duplicate", "Review Required")) -> OK | AF42: =IF(P42<0,"Invalid Discount","") | AG42: =IF(P42>1,"Invalid Discount","") | AH42: =IF(V42<1,"Invalid Shipping Record","") | AI42: =IF(ROUND(Q42,2)=ROUND(X42,2),"Match","Mismatch") -> Match | AJ42: =IF(ROUND(S42,2)=ROUND(Y42,2),"Match","Mismatch") -> Match | AK42: =PROPER(TRIM(raw_orders!G42)) -> West | AL42: =PROPER(TRIM(raw_orders!M42)) -> Standard Class
A43: ORD-2024-10042 | B43: 45363 | C43: 45368 | D43: CUST-3829 | E43: =PROPER(TRIM(raw_orders!E43)) -> Aarav Sharma | F43: =PROPER(TRIM(raw_orders!F43)) -> Small Business | G43: =PROPER(TRIM(raw_orders!G43)) -> East | H43: =PROPER(TRIM(raw_orders!H43)) -> Odisha | I43: =PROPER(TRIM(raw_orders!I43)) -> Bhubaneswar | J43: =PROPER(TRIM(raw_orders!J43)) -> Furniture | K43: =PROPER(TRIM(raw_orders!K43)) -> Bookcases | L43: Classic Bookcases 835 | M43: =PROPER(TRIM(raw_orders!M43)) -> Same Day | N43: 8 | O43: 855.81 | P43: 0 | Q43: 6846.48 | R43: 4239.89 | S43: 2606.59 | T43: =PROPER(TRIM(raw_orders!T43)) -> Pending | U43: =PROPER(TRIM(raw_orders!U43)) -> Cancelled | V43: =C43-B43 -> 5 | W43: =IF(AND(P43="",Q43<>"",N43<>"",S43<>""),0,IF(OR(P43<0,P43>1),P43,P43)) -> 0 | X43: =N43*O43*(1-P43) -> 6846.48 | Y43: =X43-R43 -> 2606.59 | Z43: =Y43/X43 -> 0.38071973 | AA43: =TEXT(B43,"MMMM") -> March | AB43: =YEAR(B43) -> 2024 | AC43: =IF(OR(AF43 = "Invalid Discount",AG43="Invalid Discount",AH43="Invalid Shipping Record",AE43="Review Required"),"Invalid",IF(OR(G43="Unknown",M43="Unknown",ISBLANK(P43)),"Warning","Clean")) -> Clean | AD43: =A43&B43&C43&D43&E43&F43&G43&H43&I43&J43&K43&L43&M43&N43&O43&P43&Q43&R43&S43&T43&U43&V43 -> ORD-2024-100424536345368CUST-3829Aarav SharmaSmall BusinessEastOdishaBhubaneswarFurnitureBookcasesClassic Bookcases 835Same Day8855.8106846.484239.892606.59PendingCancelled5 | AE43: =IF(COUNTIF($A$2:$A$933,A43)=1,"OK",IF(COUNTIF($AD$2:$AD$933,AD43)>1,"Exact Duplicate", "Review Required")) -> OK | AF43: =IF(P43<0,"Invalid Discount","") | AG43: =IF(P43>1,"Invalid Discount","") | AH43: =IF(V43<1,"Invalid Shipping Record","") | AI43: =IF(ROUND(Q43,2)=ROUND(X43,2),"Match","Mismatch") -> Match | AJ43: =IF(ROUND(S43,2)=ROUND(Y43,2),"Match","Mismatch") -> Match | AK43: =PROPER(TRIM(raw_orders!G43)) -> East | AL43: =PROPER(TRIM(raw_orders!M43)) -> Same Day
A44: ORD-2025-10043 | B44: 45940 | C44: 45945 | D44: CUST-6708 | E44: =PROPER(TRIM(raw_orders!E44)) -> Arjun Bose | F44: =PROPER(TRIM(raw_orders!F44)) -> Corporate | G44: =PROPER(TRIM(raw_orders!G44)) -> East | H44: =PROPER(TRIM(raw_orders!H44)) -> Jharkhand | I44: =PROPER(TRIM(raw_orders!I44)) -> Ranchi | J44: =PROPER(TRIM(raw_orders!J44)) -> Technology | K44: =PROPER(TRIM(raw_orders!K44)) -> Phones | L44: Eco Phones 702 | M44: =PROPER(TRIM(raw_orders!M44)) -> Standard Class | N44: 8 | O44: 979.87 | P44: 0.05 | Q44: 7447.01 | R44: 4496.22 | S44: 2950.79 | T44: =PROPER(TRIM(raw_orders!T44)) -> Paid | U44: =PROPER(TRIM(raw_orders!U44)) -> Completed | V44: =C44-B44 -> 5 | W44: =IF(AND(P44="",Q44<>"",N44<>"",S44<>""),0,IF(OR(P44<0,P44>1),P44,P44)) -> 0.05 | X44: =N44*O44*(1-P44) -> 7447.012 | Y44: =X44-R44 -> 2950.792 | Z44: =Y44/X44 -> 0.39623838 | AA44: =TEXT(B44,"MMMM") -> October | AB44: =YEAR(B44) -> 2025 | AC44: =IF(OR(AF44 = "Invalid Discount",AG44="Invalid Discount",AH44="Invalid Shipping Record",AE44="Review Required"),"Invalid",IF(OR(G44="Unknown",M44="Unknown",ISBLANK(P44)),"Warning","Clean")) -> Clean | AD44: =A44&B44&C44&D44&E44&F44&G44&H44&I44&J44&K44&L44&M44&N44&O44&P44&Q44&R44&S44&T44&U44&V44 -> ORD-2025-100434594045945CUST-6708Arjun BoseCorporateEastJharkhandRanchiTechnologyPhonesEco Phones 702Standard Class8979.870.057447.014496.222950.79PaidCompleted5 | AE44: =IF(COUNTIF($A$2:$A$933,A44)=1,"OK",IF(COUNTIF($AD$2:$AD$933,AD44)>1,"Exact Duplicate", "Review Required")) -> OK | AF44: =IF(P44<0,"Invalid Discount","") | AG44: =IF(P44>1,"Invalid Discount","") | AH44: =IF(V44<1,"Invalid Shipping Record","") | AI44: =IF(ROUND(Q44,2)=ROUND(X44,2),"Match","Mismatch") -> Match | AJ44: =IF(ROUND(S44,2)=ROUND(Y44,2),"Match","Mismatch") -> Match | AK44: =PROPER(TRIM(raw_orders!G44)) -> East | AL44: =PROPER(TRIM(raw_orders!M44)) -> Standard Class
A45: ORD-2024-10044 | B45: 45481 | C45: 45487 | D45: CUST-7119 | E45: =PROPER(TRIM(raw_orders!E45)) -> Priya Menon | F45: =PROPER(TRIM(raw_orders!F45)) -> Small Business | G45: =PROPER(TRIM(raw_orders!G45)) -> East | H45: =PROPER(TRIM(raw_orders!H45)) -> Odisha | I45: =PROPER(TRIM(raw_orders!I45)) -> Bhubaneswar | J45: =PROPER(TRIM(raw_orders!J45)) -> Furniture | K45: =PROPER(TRIM(raw_orders!K45)) -> Furnishings | L45: Smart Furnishings 956 | M45: =PROPER(TRIM(raw_orders!M45)) -> Same Day | N45: 3 | O45: 1010.23 | P45: 0 | Q45: 3030.69 | R45: 1721.08 | S45: 1309.61 | T45: =PROPER(TRIM(raw_orders!T45)) -> Paid | U45: =PROPER(TRIM(raw_orders!U45)) -> Completed | V45: =C45-B45 -> 6 | W45: =IF(AND(P45="",Q45<>"",N45<>"",S45<>""),0,IF(OR(P45<0,P45>1),P45,P45)) -> 0 | X45: =N45*O45*(1-P45) -> 3030.69 | Y45: =X45-R45 -> 1309.61 | Z45: =Y45/X45 -> 0.43211612 | AA45: =TEXT(B45,"MMMM") -> July | AB45: =YEAR(B45) -> 2024 | AC45: =IF(OR(AF45 = "Invalid Discount",AG45="Invalid Discount",AH45="Invalid Shipping Record",AE45="Review Required"),"Invalid",IF(OR(G45="Unknown",M45="Unknown",ISBLANK(P45)),"Warning","Clean")) -> Clean | AD45: =A45&B45&C45&D45&E45&F45&G45&H45&I45&J45&K45&L45&M45&N45&O45&P45&Q45&R45&S45&T45&U45&V45 -> ORD-2024-100444548145487CUST-7119Priya MenonSmall BusinessEastOdishaBhubaneswarFurnitureFurnishingsSmart Furnishings 956Same Day31010.2303030.691721.081309.61PaidCompleted6 | AE45: =IF(COUNTIF($A$2:$A$933,A45)=1,"OK",IF(COUNTIF($AD$2:$AD$933,AD45)>1,"Exact Duplicate", "Review Required")) -> OK | AF45: =IF(P45<0,"Invalid Discount","") | AG45: =IF(P45>1,"Invalid Discount","") | AH45: =IF(V45<1,"Invalid Shipping Record","") | AI45: =IF(ROUND(Q45,2)=ROUND(X45,2),"Match","Mismatch") -> Match | AJ45: =IF(ROUND(S45,2)=ROUND(Y45,2),"Match","Mismatch") -> Match | AK45: =PROPER(TRIM(raw_orders!G45)) -> East | AL45: =PROPER(TRIM(raw_orders!M45)) -> Same Day
A46: ORD-2024-10045 | B46: 45465 | C46: 45468 | D46: CUST-3373 | E46: =PROPER(TRIM(raw_orders!E46)) -> Rohan Mehta | F46: =PROPER(TRIM(raw_orders!F46)) -> Small Business | G46: =PROPER(TRIM(raw_orders!G46)) -> North | H46: =PROPER(TRIM(raw_orders!H46)) -> Haryana | I46: =PROPER(TRIM(raw_orders!I46)) -> Gurugram | J46: =PROPER(TRIM(raw_orders!J46)) -> Furniture | K46: =PROPER(TRIM(raw_orders!K46)) -> Chairs | L46: Max Chairs 393 | M46: =PROPER(TRIM(raw_orders!M46)) -> Standard Class | N46: 9 | O46: 3329.77 | P46: 0.1 | Q46: 26971.14 | R46: 17376.2 | S46: 9594.94 | T46: =PROPER(TRIM(raw_orders!T46)) -> Paid | U46: =PROPER(TRIM(raw_orders!U46)) -> Completed | V46: =C46-B46 -> 3 | W46: =IF(AND(P46="",Q46<>"",N46<>"",S46<>""),0,IF(OR(P46<0,P46>1),P46,P46)) -> 0.1 | X46: =N46*O46*(1-P46) -> 26971.137 | Y46: =X46-R46 -> 9594.937 | Z46: =Y46/X46 -> 0.35574833 | AA46: =TEXT(B46,"MMMM") -> June | AB46: =YEAR(B46) -> 2024 | AC46: =IF(OR(AF46 = "Invalid Discount",AG46="Invalid Discount",AH46="Invalid Shipping Record",AE46="Review Required"),"Invalid",IF(OR(G46="Unknown",M46="Unknown",ISBLANK(P46)),"Warning","Clean")) -> Clean | AD46: =A46&B46&C46&D46&E46&F46&G46&H46&I46&J46&K46&L46&M46&N46&O46&P46&Q46&R46&S46&T46&U46&V46 -> ORD-2024-100454546545468CUST-3373Rohan MehtaSmall BusinessNorthHaryanaGurugramFurnitureChairsMax Chairs 393Standard Class93329.770.126971.1417376.29594.94PaidCompleted3 | AE46: =IF(COUNTIF($A$2:$A$933,A46)=1,"OK",IF(COUNTIF($AD$2:$AD$933,AD46)>1,"Exact Duplicate", "Review Required")) -> OK | AF46: =IF(P46<0,"Invalid Discount","") | AG46: =IF(P46>1,"Invalid Discount","") | AH46: =IF(V46<1,"Invalid Shipping Record","") | AI46: =IF(ROUND(Q46,2)=ROUND(X46,2),"Match","Mismatch") -> Match | AJ46: =IF(ROUND(S46,2)=ROUND(Y46,2),"Match","Mismatch") -> Match | AK46: =PROPER(TRIM(raw_orders!G46)) -> North | AL46: =PROPER(TRIM(raw_orders!M46)) -> Standard Class
A47: ORD-2024-10046 | B47: 45309 | C47: 45315 | D47: CUST-8896 | E47: =PROPER(TRIM(raw_orders!E47)) -> Isha Nair | F47: =PROPER(TRIM(raw_orders!F47)) -> Home Office | G47: =PROPER(TRIM(raw_orders!G47)) -> East | H47: =PROPER(TRIM(raw_orders!H47)) -> Bihar | I47: =PROPER(TRIM(raw_orders!I47)) -> Patna | J47: =PROPER(TRIM(raw_orders!J47)) -> Office Supplies | K47: =PROPER(TRIM(raw_orders!K47)) -> Art | L47: Prime Art 221 | M47: =PROPER(TRIM(raw_orders!M47)) -> Second Class | N47: 8 | O47: 3927.82 | P47: 0.05 | Q47: 29851.43 | R47: 17487.48 | S47: 12363.95 | T47: =PROPER(TRIM(raw_orders!T47)) -> Pending | U47: =PROPER(TRIM(raw_orders!U47)) -> Returned | V47: =C47-B47 -> 6 | W47: =IF(AND(P47="",Q47<>"",N47<>"",S47<>""),0,IF(OR(P47<0,P47>1),P47,P47)) -> 0.05 | X47: =N47*O47*(1-P47) -> 29851.432 | Y47: =X47-R47 -> 12363.952 | Z47: =Y47/X47 -> 0.41418288 | AA47: =TEXT(B47,"MMMM") -> January | AB47: =YEAR(B47) -> 2024 | AC47: =IF(OR(AF47 = "Invalid Discount",AG47="Invalid Discount",AH47="Invalid Shipping Record",AE47="Review Required"),"Invalid",IF(OR(G47="Unknown",M47="Unknown",ISBLANK(P47)),"Warning","Clean")) -> Clean | AD47: =A47&B47&C47&D47&E47&F47&G47&H47&I47&J47&K47&L47&M47&N47&O47&P47&Q47&R47&S47&T47&U47&V47 -> ORD-2024-100464530945315CUST-8896Isha NairHome OfficeEastBiharPatnaOffice SuppliesArtPrime Art 221Second Class83927.820.0529851.4317487.4812363.95PendingReturned6 | AE47: =IF(COUNTIF($A$2:$A$933,A47)=1,"OK",IF(COUNTIF($AD$2:$AD$933,AD47)>1,"Exact Duplicate", "Review Required")) -> OK | AF47: =IF(P47<0,"Invalid Discount","") | AG47: =IF(P47>1,"Invalid Discount","") | AH47: =IF(V47<1,"Invalid Shipping Record","") | AI47: =IF(ROUND(Q47,2)=ROUND(X47,2),"Match","Mismatch") -> Match | AJ47: =IF(ROUND(S47,2)=ROUND(Y47,2),"Match","Mismatch") -> Match | AK47: =PROPER(TRIM(raw_orders!G47)) -> East | AL47: =PROPER(TRIM(raw_orders!M47)) -> Second Class
A48: ORD-2024-10047 | B48: 45492 | C48: 45492 | D48: CUST-8517 | E48: =PROPER(TRIM(raw_orders!E48)) -> Ananya Rao | F48: =PROPER(TRIM(raw_orders!F48)) -> Small Business | G48: =PROPER(TRIM(raw_orders!G48)) -> South | H48: =PROPER(TRIM(raw_orders!H48)) -> Kerala | I48: =PROPER(TRIM(raw_orders!I48)) -> Kochi | J48: =PROPER(TRIM(raw_orders!J48)) -> Furniture | K48: =PROPER(TRIM(raw_orders!K48)) -> Bookcases | L48: Elite Bookcases 671 | M48: =PROPER(TRIM(raw_orders!M48)) -> Standard Class | N48: 9 | O48: 2386.79 | P48: 0.25 | Q48: 16110.83 | R48: 10680.03 | S48: 5430.8 | T48: =PROPER(TRIM(raw_orders!T48)) -> Refunded | U48: =PROPER(TRIM(raw_orders!U48)) -> Returned | V48: =C48-B48 -> 0 | W48: =IF(AND(P48="",Q48<>"",N48<>"",S48<>""),0,IF(OR(P48<0,P48>1),P48,P48)) -> 0.25 | X48: =N48*O48*(1-P48) -> 16110.833 | Y48: =X48-R48 -> 5430.8025 | Z48: =Y48/X48 -> 0.33709012 | AA48: =TEXT(B48,"MMMM") -> July | AB48: =YEAR(B48) -> 2024 | AC48: =IF(OR(AF48 = "Invalid Discount",AG48="Invalid Discount",AH48="Invalid Shipping Record",AE48="Review Required"),"Invalid",IF(OR(G48="Unknown",M48="Unknown",ISBLANK(P48)),"Warning","Clean")) -> Clean | AD48: =A48&B48&C48&D48&E48&F48&G48&H48&I48&J48&K48&L48&M48&N48&O48&P48&Q48&R48&S48&T48&U48&V48 -> ORD-2024-100474549245492CUST-8517Ananya RaoSmall BusinessSouthKeralaKochiFurnitureBookcasesElite Bookcases 671Standard Class92386.790.2516110.8310680.035430.8RefundedReturned0 | AE48: =IF(COUNTIF($A$2:$A$933,A48)=1,"OK",IF(COUNTIF($AD$2:$AD$933,AD48)>1,"Exact Duplicate", "Review Required")) -> OK | AF48: =IF(P48<0,"Invalid Discount","") | AG48: =IF(P48>1,"Invalid Discount","") | AH48: =IF(V48<0,"Invalid Shipping Record","") | AI48: =IF(ROUND(Q48,2)=ROUND(X48,2),"Match","Mismatch") -> Match | AJ48: =IF(ROUND(S48,2)=ROUND(Y48,2),"Match","Mismatch") -> Match | AK48: =PROPER(TRIM(raw_orders!G48)) -> South | AL48: =PROPER(TRIM(raw_orders!M48)) -> Standard Class
A49: ORD-2024-10048 | B49: 45634 | C49: 45516 | D49: CUST-1987 | E49: =PROPER(TRIM(raw_orders!E49)) -> Rahul Verma | F49: =PROPER(TRIM(raw_orders!F49)) -> Corporate | G49: =PROPER(TRIM(raw_orders!G49)) -> South | H49: =PROPER(TRIM(raw_orders!H49)) -> Tamil Nadu | I49: =PROPER(TRIM(raw_orders!I49)) -> Chennai | J49: =PROPER(TRIM(raw_orders!J49)) -> Office Supplies | K49: =PROPER(TRIM(raw_orders!K49)) -> Storage | L49: Max Storage 432 | M49: =PROPER(TRIM(raw_orders!M49)) -> Standard Class | N49: 8 | O49: 2445.31 | P49: 0.1 | Q49: 17606.23 | R49: 12438.96 | S49: 5167.27 | T49: =PROPER(TRIM(raw_orders!T49)) -> Paid | U49: =PROPER(TRIM(raw_orders!U49)) -> Completed | V49: =C49-B49 -> -118 | W49: =IF(AND(P49="",Q49<>"",N49<>"",S49<>""),0,IF(OR(P49<0,P49>1),P49,P49)) -> 0.1 | X49: =N49*O49*(1-P49) -> 17606.232 | Y49: =X49-R49 -> 5167.272 | Z49: =Y49/X49 -> 0.29349108 | AA49: =TEXT(B49,"MMMM") -> December | AB49: =YEAR(B49) -> 2024 | AC49: =IF(OR(AF49 = "Invalid Discount",AG49="Invalid Discount",AH49="Invalid Shipping Record",AE49="Review Required"),"Invalid",IF(OR(G49="Unknown",M49="Unknown",ISBLANK(P49)),"Warning","Clean")) -> Invalid | AD49: =A49&B49&C49&D49&E49&F49&G49&H49&I49&J49&K49&L49&M49&N49&O49&P49&Q49&R49&S49&T49&U49&V49 -> ORD-2024-100484563445516CUST-1987Rahul VermaCorporateSouthTamil NaduChennaiOffice SuppliesStorageMax Storage 432Standard Class82445.310.117606.2312438.965167.27PaidCompleted-118 | AE49: =IF(COUNTIF($A$2:$A$933,A49)=1,"OK",IF(COUNTIF($AD$2:$AD$933,AD49)>1,"Exact Duplicate", "Review Required")) -> OK | AF49: =IF(P49<0,"Invalid Discount","") | AG49: =IF(P49>1,"Invalid Discount","") | AH49: =IF(V49<0,"Invalid Shipping Record","") -> Invalid Shipping Record | AI49: =IF(ROUND(Q49,2)=ROUND(X49,2),"Match","Mismatch") -> Match | AJ49: =IF(ROUND(S49,2)=ROUND(Y49,2),"Match","Mismatch") -> Match | AK49: =PROPER(TRIM(raw_orders!G49)) -> South | AL49: =PROPER(TRIM(raw_orders!M49)) -> Standard Class
A50: ORD-2025-10049 | B50: 45687 | C50: 45693 | D50: CUST-8183 | E50: =PROPER(TRIM(raw_orders!E50)) -> Neha Gupta | F50: =PROPER(TRIM(raw_orders!F50)) -> Corporate | G50: =PROPER(TRIM(raw_orders!G50)) -> West | H50: =PROPER(TRIM(raw_orders!H50)) -> Maharashtra | I50: =PROPER(TRIM(raw_orders!I50)) -> Mumbai | J50: =PROPER(TRIM(raw_orders!J50)) -> Furniture | K50: =PROPER(TRIM(raw_orders!K50)) -> Chairs | L50: Basic Chairs 837 | M50: =PROPER(TRIM(raw_orders!M50)) -> Second Class | N50: 7 | O50: 4063.66 | P50: 0 | Q50: 28445.62 | R50: 20938.59 | S50: 7507.03 | T50: =PROPER(TRIM(raw_orders!T50)) -> Paid | U50: =PROPER(TRIM(raw_orders!U50)) -> Completed | V50: =C50-B50 -> 6 | W50: =IF(AND(P50="",Q50<>"",N50<>"",S50<>""),0,IF(OR(P50<0,P50>1),P50,P50)) -> 0 | X50: =N50*O50*(1-P50) -> 28445.62 | Y50: =X50-R50 -> 7507.03 | Z50: =Y50/X50 -> 0.26390812 | AA50: =TEXT(B50,"MMMM") -> January | AB50: =YEAR(B50) -> 2025 | AC50: =IF(OR(AF50 = "Invalid Discount",AG50="Invalid Discount",AH50="Invalid Shipping Record",AE50="Review Required"),"Invalid",IF(OR(G50="Unknown",M50="Unknown",ISBLANK(P50)),"Warning","Clean")) -> Clean | AD50: =A50&B50&C50&D50&E50&F50&G50&H50&I50&J50&K50&L50&M50&N50&O50&P50&Q50&R50&S50&T50&U50&V50 -> ORD-2025-100494568745693CUST-8183Neha GuptaCorporateWestMaharashtraMumbaiFurnitureChairsBasic Chairs 837Second Class74063.66028445.6220938.597507.03PaidCompleted6 | AE50: =IF(COUNTIF($A$2:$A$933,A50)=1,"OK",IF(COUNTIF($AD$2:$AD$933,AD50)>1,"Exact Duplicate", "Review Required")) -> OK | AF50: =IF(P50<0,"Invalid Discount","") | AG50: =IF(P50>1,"Invalid Discount","") | AH50: =IF(V50<1,"Invalid Shipping Record","") | AI50: =IF(ROUND(Q50,2)=ROUND(X50,2),"Match","Mismatch") -> Match | AJ50: =IF(ROUND(S50,2)=ROUND(Y50,2),"Match","Mismatch") -> Match | AK50: =PROPER(TRIM(raw_orders!G50)) -> West | AL50: =PROPER(TRIM(raw_orders!M50)) -> Second Class
A51: ORD-2024-10050 | B51: 45388 | C51: 45395 | D51: CUST-2380 | E51: =PROPER(TRIM(raw_orders!E51)) -> Aarav Sharma | F51: =PROPER(TRIM(raw_orders!F51)) -> Home Office | G51: =PROPER(TRIM(raw_orders!G51)) -> North | H51: =PROPER(TRIM(raw_orders!H51)) -> Uttar Pradesh | I51: =PROPER(TRIM(raw_orders!I51)) -> Noida | J51: =PROPER(TRIM(raw_orders!J51)) -> Technology | K51: =PROPER(TRIM(raw_orders!K51)) -> Copiers | L51: Classic Copiers 295 | M51: =PROPER(TRIM(raw_orders!M51)) -> Second Class | N51: 9 | O51: 792.11 | P51: 0.05 | Q51: 6772.54 | R51: 5755.46 | S51: 1017.08 | T51: =PROPER(TRIM(raw_orders!T51)) -> Paid | U51: =PROPER(TRIM(raw_orders!U51)) -> Completed | V51: =C51-B51 -> 7 | W51: =IF(AND(P51="",Q51<>"",N51<>"",S51<>""),0,IF(OR(P51<0,P51>1),P51,P51)) -> 0.05 | X51: =N51*O51*(1-P51) -> 6772.5405 | Y51: =X51-R51 -> 1017.0805 | Z51: =Y51/X51 -> 0.1501771 | AA51: =TEXT(B51,"MMMM") -> April | AB51: =YEAR(B51) -> 2024 | AC51: =IF(OR(AF51 = "Invalid Discount",AG51="Invalid Discount",AH51="Invalid Shipping Record",AE51="Review Required"),"Invalid",IF(OR(G51="Unknown",M51="Unknown",ISBLANK(P51)),"Warning","Clean")) -> Clean | AD51: =A51&B51&C51&D51&E51&F51&G51&H51&I51&J51&K51&L51&M51&N51&O51&P51&Q51&R51&S51&T51&U51&V51 -> ORD-2024-100504538845395CUST-2380Aarav SharmaHome OfficeNorthUttar PradeshNoidaTechnologyCopiersClassic Copiers 295Second Class9792.110.056772.545755.461017.08PaidCompleted7 | AE51: =IF(COUNTIF($A$2:$A$933,A51)=1,"OK",IF(COUNTIF($AD$2:$AD$933,AD51)>1,"Exact Duplicate", "Review Required")) -> OK | AF51: =IF(P51<0,"Invalid Discount","") | AG51: =IF(P51>1,"Invalid Discount","") | AH51: =IF(V51<1,"Invalid Shipping Record","") | AI51: =IF(ROUND(Q51,2)=ROUND(X51,2),"Match","Mismatch") -> Match | AJ51: =IF(ROUND(S51,2)=ROUND(Y51,2),"Match","Mismatch") -> Match | AK51: =PROPER(TRIM(raw_orders!G51)) -> North | AL51: =PROPER(TRIM(raw_orders!M51)) -> Second Class
A52: ORD-2025-10051 | B52: 45788 | C52: 45796 | D52: CUST-8787 | E52: =PROPER(TRIM(raw_orders!E52)) -> Sneha Kapoor | F52: =PROPER(TRIM(raw_orders!F52)) -> Consumer | G52: =PROPER(TRIM(raw_orders!G52)) -> East | H52: =PROPER(TRIM(raw_orders!H52)) -> West Bengal | I52: =PROPER(TRIM(raw_orders!I52)) -> Kolkata | J52: =PROPER(TRIM(raw_orders!J52)) -> Technology | K52: =PROPER(TRIM(raw_orders!K52)) -> Copiers | L52: Pro Copiers 963 | M52: =PROPER(TRIM(raw_orders!M52)) -> Standard Class | N52: 1 | O52: 2382.8 | P52: 0.15 | Q52: 2025.38 | R52: 1140.65 | S52: 884.73 | T52: =PROPER(TRIM(raw_orders!T52)) -> Paid | U52: =PROPER(TRIM(raw_orders!U52)) -> Completed | V52: =C52-B52 -> 8 | W52: =IF(AND(P52="",Q52<>"",N52<>"",S52<>""),0,IF(OR(P52<0,P52>1),P52,P52)) -> 0.15 | X52: =N52*O52*(1-P52) -> 2025.38 | Y52: =X52-R52 -> 884.73 | Z52: =Y52/X52 -> 0.43682173 | AA52: =TEXT(B52,"MMMM") -> May | AB52: =YEAR(B52) -> 2025 | AC52: =IF(OR(AF52 = "Invalid Discount",AG52="Invalid Discount",AH52="Invalid Shipping Record",AE52="Review Required"),"Invalid",IF(OR(G52="Unknown",M52="Unknown",ISBLANK(P52)),"Warning","Clean")) -> Clean | AD52: =A52&B52&C52&D52&E52&F52&G52&H52&I52&J52&K52&L52&M52&N52&O52&P52&Q52&R52&S52&T52&U52&V52 -> ORD-2025-100514578845796CUST-8787Sneha KapoorConsumerEastWest BengalKolkataTechnologyCopiersPro Copiers 963Standard Class12382.80.152025.381140.65884.73PaidCompleted8 | AE52: =IF(COUNTIF($A$2:$A$933,A52)=1,"OK",IF(COUNTIF($AD$2:$AD$933,AD52)>1,"Exact Duplicate", "Review Required")) -> OK | AF52: =IF(P52<0,"Invalid Discount","") | AG52: =IF(P52>1,"Invalid Discount","") | AH52: =IF(V52<1,"Invalid Shipping Record","") | AI52: =IF(ROUND(Q52,2)=ROUND(X52,2),"Match","Mismatch") -> Match | AJ52: =IF(ROUND(S52,2)=ROUND(Y52,2),"Match","Mismatch") -> Match | AK52: =PROPER(TRIM(raw_orders!G52)) -> East | AL52: =PROPER(TRIM(raw_orders!M52)) -> Standard Class
A53: ORD-2024-10052 | B53: 45406 | C53: 45411 | D53: CUST-3557 | E53: =PROPER(TRIM(raw_orders!E53)) -> Ananya Rao | F53: =PROPER(TRIM(raw_orders!F53)) -> Corporate | G53: =PROPER(TRIM(raw_orders!G53)) -> South | H53: =PROPER(TRIM(raw_orders!H53)) -> Telangana | I53: =PROPER(TRIM(raw_orders!I53)) -> Hyderabad | J53: =PROPER(TRIM(raw_orders!J53)) -> Office Supplies | K53: =PROPER(TRIM(raw_orders!K53)) -> Art | L53: Pro Art 907 | M53: =PROPER(TRIM(raw_orders!M53)) -> Standard Class | N53: 6 | O53: 1528.08 | P53: 0 | Q53: 9168.48 | R53: 7439.77 | S53: 1728.71 | T53: =PROPER(TRIM(raw_orders!T53)) -> Paid | U53: =PROPER(TRIM(raw_orders!U53)) -> Completed | V53: =C53-B53 -> 5 | W53: =IF(AND(P53="",Q53<>"",N53<>"",S53<>""),0,IF(OR(P53<0,P53>1),P53,P53)) -> 0 | X53: =N53*O53*(1-P53) -> 9168.48 | Y53: =X53-R53 -> 1728.71 | Z53: =Y53/X53 -> 0.18854925 | AA53: =TEXT(B53,"MMMM") -> April | AB53: =YEAR(B53) -> 2024 | AC53: =IF(OR(AF53 = "Invalid Discount",AG53="Invalid Discount",AH53="Invalid Shipping Record",AE53="Review Required"),"Invalid",IF(OR(G53="Unknown",M53="Unknown",ISBLANK(P53)),"Warning","Clean")) -> Clean | AD53: =A53&B53&C53&D53&E53&F53&G53&H53&I53&J53&K53&L53&M53&N53&O53&P53&Q53&R53&S53&T53&U53&V53 -> ORD-2024-100524540645411CUST-3557Ananya RaoCorporateSouthTelanganaHyderabadOffice SuppliesArtPro Art 907Standard Class61528.0809168.487439.771728.71PaidCompleted5 | AE53: =IF(COUNTIF($A$2:$A$933,A53)=1,"OK",IF(COUNTIF($AD$2:$AD$933,AD53)>1,"Exact Duplicate", "Review Required")) -> OK | AF53: =IF(P53<0,"Invalid Discount","") | AG53: =IF(P53>1,"Invalid Discount","") | AH53: =IF(V53<1,"Invalid Shipping Record","") | AI53: =IF(ROUND(Q53,2)=ROUND(X53,2),"Match","Mismatch") -> Match | AJ53: =IF(ROUND(S53,2)=ROUND(Y53,2),"Match","Mismatch") -> Match | AK53: =PROPER(TRIM(raw_orders!G53)) -> South | AL53: =PROPER(TRIM(raw_orders!M53)) -> Standard Class
A54: ORD-2024-10053 | B54: 45591 | C54: 45593 | D54: CUST-2778 | E54: =PROPER(TRIM(raw_orders!E54)) -> Kabir Singh | F54: =PROPER(TRIM(raw_orders!F54)) -> Small Business | G54: =PROPER(TRIM(raw_orders!G54)) -> North | H54: =PROPER(TRIM(raw_orders!H54)) -> Rajasthan | I54: =PROPER(TRIM(raw_orders!I54)) -> Jaipur | J54: =PROPER(TRIM(raw_orders!J54)) -> Furniture | K54: =PROPER(TRIM(raw_orders!K54)) -> Chairs | L54: Pro Chairs 526 | M54: =PROPER(TRIM(raw_orders!M54)) -> First Class | N54: 9 | O54: 1399.63 | P54: 0 | Q54: 12596.67 | R54: 10603.29 | S54: 1993.38 | T54: =PROPER(TRIM(raw_orders!T54)) -> Failed | U54: =PROPER(TRIM(raw_orders!U54)) -> Cancelled | V54: =C54-B54 -> 2 | W54: =IF(AND(P54="",Q54<>"",N54<>"",S54<>""),0,IF(OR(P54<0,P54>1),P54,P54)) -> 0 | X54: =N54*O54*(1-P54) -> 12596.67 | Y54: =X54-R54 -> 1993.38 | Z54: =Y54/X54 -> 0.15824658 | AA54: =TEXT(B54,"MMMM") -> October | AB54: =YEAR(B54) -> 2024 | AC54: =IF(OR(AF54 = "Invalid Discount",AG54="Invalid Discount",AH54="Invalid Shipping Record",AE54="Review Required"),"Invalid",IF(OR(G54="Unknown",M54="Unknown",ISBLANK(P54)),"Warning","Clean")) -> Clean | AD54: =A54&B54&C54&D54&E54&F54&G54&H54&I54&J54&K54&L54&M54&N54&O54&P54&Q54&R54&S54&T54&U54&V54 -> ORD-2024-100534559145593CUST-2778Kabir SinghSmall BusinessNorthRajasthanJaipurFurnitureChairsPro Chairs 526First Class91399.63012596.6710603.291993.38FailedCancelled2 | AE54: =IF(COUNTIF($A$2:$A$933,A54)=1,"OK",IF(COUNTIF($AD$2:$AD$933,AD54)>1,"Exact Duplicate", "Review Required")) -> OK | AF54: =IF(P54<0,"Invalid Discount","") | AG54: =IF(P54>1,"Invalid Discount","") | AH54: =IF(V54<1,"Invalid Shipping Record","") | AI54: =IF(ROUND(Q54,2)=ROUND(X54,2),"Match","Mismatch") -> Match | AJ54: =IF(ROUND(S54,2)=ROUND(Y54,2),"Match","Mismatch") -> Match | AK54: =PROPER(TRIM(raw_orders!G54)) -> North | AL54: =PROPER(TRIM(raw_orders!M54)) -> First Class
A55: ORD-2025-10054 | B55: 45747 | C55: 45747 | D55: CUST-7195 | E55: =PROPER(TRIM(raw_orders!E55)) -> Kabir Singh | F55: =PROPER(TRIM(raw_orders!F55)) -> Home Office | G55: =PROPER(TRIM(raw_orders!G55)) -> West | H55: =PROPER(TRIM(raw_orders!H55)) -> Gujarat | I55: =PROPER(TRIM(raw_orders!I55)) -> Ahmedabad | J55: =PROPER(TRIM(raw_orders!J55)) -> Office Supplies | K55: =PROPER(TRIM(raw_orders!K55)) -> Storage | L55: Elite Storage 924 | M55: =PROPER(TRIM(raw_orders!M55)) -> First Class | N55: 5 | O55: 1207.47 | P55: 0.15 | Q55: 5131.75 | R55: 2838.68 | S55: 2293.07 | T55: =PROPER(TRIM(raw_orders!T55)) -> Paid | U55: =PROPER(TRIM(raw_orders!U55)) -> Completed | V55: =C55-B55 -> 0 | W55: =IF(AND(P55="",Q55<>"",N55<>"",S55<>""),0,IF(OR(P55<0,P55>1),P55,P55)) -> 0.15 | X55: =N55*O55*(1-P55) -> 5131.7475 | Y55: =X55-R55 -> 2293.0675 | Z55: =Y55/X55 -> 0.4468395 | AA55: =TEXT(B55,"MMMM") -> March | AB55: =YEAR(B55) -> 2025 | AC55: =IF(OR(AF55 = "Invalid Discount",AG55="Invalid Discount",AH55="Invalid Shipping Record",AE55="Review Required"),"Invalid",IF(OR(G55="Unknown",M55="Unknown",ISBLANK(P55)),"Warning","Clean")) -> Clean | AD55: =A55&B55&C55&D55&E55&F55&G55&H55&I55&J55&K55&L55&M55&N55&O55&P55&Q55&R55&S55&T55&U55&V55 -> ORD-2025-100544574745747CUST-7195Kabir SinghHome OfficeWestGujaratAhmedabadOffice SuppliesStorageElite Storage 924First Class51207.470.155131.752838.682293.07PaidCompleted0 | AE55: =IF(COUNTIF($A$2:$A$933,A55)=1,"OK",IF(COUNTIF($AD$2:$AD$933,AD55)>1,"Exact Duplicate", "Review Required")) -> OK | AF55: =IF(P55<0,"Invalid Discount","") | AG55: =IF(P55>1,"Invalid Discount","") | AH55: =IF(V55<0,"Invalid Shipping Record","") | AI55: =IF(ROUND(Q55,2)=ROUND(X55,2),"Match","Mismatch") -> Match | AJ55: =IF(ROUND(S55,2)=ROUND(Y55,2),"Match","Mismatch") -> Match | AK55: =PROPER(TRIM(raw_orders!G55)) -> West | AL55: =PROPER(TRIM(raw_orders!M55)) -> First Class
A56: ORD-2025-10055 | B56: 45807 | C56: 45810 | D56: CUST-9039 | E56: =PROPER(TRIM(raw_orders!E56)) -> Arjun Bose | F56: =PROPER(TRIM(raw_orders!F56)) -> Corporate | G56: =PROPER(TRIM(raw_orders!G56)) -> South | H56: =PROPER(TRIM(raw_orders!H56)) -> Tamil Nadu | I56: =PROPER(TRIM(raw_orders!I56)) -> Chennai | J56: =PROPER(TRIM(raw_orders!J56)) -> Office Supplies | K56: =PROPER(TRIM(raw_orders!K56)) -> Labels | L56: Pro Labels 957 | M56: =PROPER(TRIM(raw_orders!M56)) -> Same Day | N56: 8 | O56: 474.37 | P56: 0.1 | Q56: 3415.46 | R56: 1993.23 | S56: 1422.23 | T56: =PROPER(TRIM(raw_orders!T56)) -> Failed | U56: =PROPER(TRIM(raw_orders!U56)) -> Cancelled | V56: =C56-B56 -> 3 | W56: =IF(AND(P56="",Q56<>"",N56<>"",S56<>""),0,IF(OR(P56<0,P56>1),P56,P56)) -> 0.1 | X56: =N56*O56*(1-P56) -> 3415.464 | Y56: =X56-R56 -> 1422.234 | Z56: =Y56/X56 -> 0.41641019 | AA56: =TEXT(B56,"MMMM") -> May | AB56: =YEAR(B56) -> 2025 | AC56: =IF(OR(AF56 = "Invalid Discount",AG56="Invalid Discount",AH56="Invalid Shipping Record",AE56="Review Required"),"Invalid",IF(OR(G56="Unknown",M56="Unknown",ISBLANK(P56)),"Warning","Clean")) -> Clean | AD56: =A56&B56&C56&D56&E56&F56&G56&H56&I56&J56&K56&L56&M56&N56&O56&P56&Q56&R56&S56&T56&U56&V56 -> ORD-2025-100554580745810CUST-9039Arjun BoseCorporateSouthTamil NaduChennaiOffice SuppliesLabelsPro Labels 957Same Day8474.370.13415.461993.231422.23FailedCancelled3 | AE56: =IF(COUNTIF($A$2:$A$933,A56)=1,"OK",IF(COUNTIF($AD$2:$AD$933,AD56)>1,"Exact Duplicate", "Review Required")) -> OK | AF56: =IF(P56<0,"Invalid Discount","") | AG56: =IF(P56>1,"Invalid Discount","") | AH56: =IF(V56<1,"Invalid Shipping Record","") | AI56: =IF(ROUND(Q56,2)=ROUND(X56,2),"Match","Mismatch") -> Match | AJ56: =IF(ROUND(S56,2)=ROUND(Y56,2),"Match","Mismatch") -> Match | AK56: =PROPER(TRIM(raw_orders!G56)) -> South | AL56: =PROPER(TRIM(raw_orders!M56)) -> Same Day
A57: ORD-2025-10056 | B57: 45664 | C57: 45723 | D57: CUST-9821 | E57: =PROPER(TRIM(raw_orders!E57)) -> Mira Das | F57: =PROPER(TRIM(raw_orders!F57)) -> Small Business | G57: =PROPER(TRIM(raw_orders!G57)) -> South | H57: =PROPER(TRIM(raw_orders!H57)) -> Andhra Pradesh | I57: =PROPER(TRIM(raw_orders!I57)) -> Vijayawada | J57: =PROPER(TRIM(raw_orders!J57)) -> Technology | K57: =PROPER(TRIM(raw_orders!K57)) -> Machines | L57: Classic Machines 310 | M57: =PROPER(TRIM(raw_orders!M57)) -> Same Day | N57: 3 | O57: 1516.24 | P57: 0.25 | Q57: 3411.54 | R57: 2803.13 | S57: 608.41 | T57: =PROPER(TRIM(raw_orders!T57)) -> Paid | U57: =PROPER(TRIM(raw_orders!U57)) -> Completed | V57: =C57-B57 -> 59 | W57: =IF(AND(P57="",Q57<>"",N57<>"",S57<>""),0,IF(OR(P57<0,P57>1),P57,P57)) -> 0.25 | X57: =N57*O57*(1-P57) -> 3411.54 | Y57: =X57-R57 -> 608.41 | Z57: =Y57/X57 -> 0.17833881 | AA57: =TEXT(B57,"MMMM") -> January | AB57: =YEAR(B57) -> 2025 | AC57: =IF(OR(AF57 = "Invalid Discount",AG57="Invalid Discount",AH57="Invalid Shipping Record",AE57="Review Required"),"Invalid",IF(OR(G57="Unknown",M57="Unknown",ISBLANK(P57)),"Warning","Clean")) -> Clean | AD57: =A57&B57&C57&D57&E57&F57&G57&H57&I57&J57&K57&L57&M57&N57&O57&P57&Q57&R57&S57&T57&U57&V57 -> ORD-2025-100564566445723CUST-9821Mira DasSmall BusinessSouthAndhra PradeshVijayawadaTechnologyMachinesClassic Machines 310Same Day31516.240.253411.542803.13608.41PaidCompleted59 | AE57: =IF(COUNTIF($A$2:$A$933,A57)=1,"OK",IF(COUNTIF($AD$2:$AD$933,AD57)>1,"Exact Duplicate", "Review Required")) -> OK | AF57: =IF(P57<0,"Invalid Discount","") | AG57: =IF(P57>1,"Invalid Discount","") | AH57: =IF(V57<1,"Invalid Shipping Record","") | AI57: =IF(ROUND(Q57,2)=ROUND(X57,2),"Match","Mismatch") -> Match | AJ57: =IF(ROUND(S57,2)=ROUND(Y57,2),"Match","Mismatch") -> Match | AK57: =PROPER(TRIM(raw_orders!G57)) -> South | AL57: =PROPER(TRIM(raw_orders!M57)) -> Same Day
A58: ORD-2025-10057 | B58: 45662 | C58: 45809 | D58: CUST-8701 | E58: =PROPER(TRIM(raw_orders!E58)) -> Karan Malhotra | F58: =PROPER(TRIM(raw_orders!F58)) -> Consumer | G58: =PROPER(TRIM(raw_orders!G58)) -> South | H58: =PROPER(TRIM(raw_orders!H58)) -> Karnataka | I58: =PROPER(TRIM(raw_orders!I58)) -> Bengaluru | J58: =PROPER(TRIM(raw_orders!J58)) -> Office Supplies | K58: =PROPER(TRIM(raw_orders!K58)) -> Binders | L58: Smart Binders 393 | M58: =PROPER(TRIM(raw_orders!M58)) -> Second Class | N58: 3 | O58: 3155.61 | P58: 0 | Q58: 9466.83 | R58: 6557.83 | S58: 2909 | T58: =PROPER(TRIM(raw_orders!T58)) -> Refunded | U58: =PROPER(TRIM(raw_orders!U58)) -> Cancelled | V58: =C58-B58 -> 147 | W58: =IF(AND(P58="",Q58<>"",N58<>"",S58<>""),0,IF(OR(P58<0,P58>1),P58,P58)) -> 0 | X58: =N58*O58*(1-P58) -> 9466.83 | Y58: =X58-R58 -> 2909 | Z58: =Y58/X58 -> 0.30728343 | AA58: =TEXT(B58,"MMMM") -> January | AB58: =YEAR(B58) -> 2025 | AC58: =IF(OR(AF58 = "Invalid Discount",AG58="Invalid Discount",AH58="Invalid Shipping Record",AE58="Review Required"),"Invalid",IF(OR(G58="Unknown",M58="Unknown",ISBLANK(P58)),"Warning","Clean")) -> Clean | AD58: =A58&B58&C58&D58&E58&F58&G58&H58&I58&J58&K58&L58&M58&N58&O58&P58&Q58&R58&S58&T58&U58&V58 -> ORD-2025-100574566245809CUST-8701Karan MalhotraConsumerSouthKarnatakaBengaluruOffice SuppliesBindersSmart Binders 393Second Class33155.6109466.836557.832909RefundedCancelled147 | AE58: =IF(COUNTIF($A$2:$A$933,A58)=1,"OK",IF(COUNTIF($AD$2:$AD$933,AD58)>1,"Exact Duplicate", "Review Required")) -> OK | AF58: =IF(P58<0,"Invalid Discount","") | AG58: =IF(P58>1,"Invalid Discount","") | AH58: =IF(V58<1,"Invalid Shipping Record","") | AI58: =IF(ROUND(Q58,2)=ROUND(X58,2),"Match","Mismatch") -> Match | AJ58: =IF(ROUND(S58,2)=ROUND(Y58,2),"Match","Mismatch") -> Match | AK58: =PROPER(TRIM(raw_orders!G58)) -> South | AL58: =PROPER(TRIM(raw_orders!M58)) -> Second Class
A59: ORD-2024-10058 | B59: 45329 | C59: 45337 | D59: CUST-9941 | E59: =PROPER(TRIM(raw_orders!E59)) -> Priya Menon | F59: =PROPER(TRIM(raw_orders!F59)) -> Consumer | G59: =PROPER(TRIM(raw_orders!G59)) -> West | H59: =PROPER(TRIM(raw_orders!H59)) -> Goa | I59: =PROPER(TRIM(raw_orders!I59)) -> Panaji | J59: =PROPER(TRIM(raw_orders!J59)) -> Furniture | K59: =PROPER(TRIM(raw_orders!K59)) -> Chairs | L59: Max Chairs 813 | M59: =PROPER(TRIM(raw_orders!M59)) -> Same Day | N59: 5 | O59: 255.87 | P59: 0 | Q59: 1279.35 | R59: 1091.54 | S59: 187.81 | T59: =PROPER(TRIM(raw_orders!T59)) -> Paid | U59: =PROPER(TRIM(raw_orders!U59)) -> Completed | V59: =C59-B59 -> 8 | W59: =IF(AND(P59="",Q59<>"",N59<>"",S59<>""),0,IF(OR(P59<0,P59>1),P59,P59)) -> 0 | X59: =N59*O59*(1-P59) -> 1279.35 | Y59: =X59-R59 -> 187.81 | Z59: =Y59/X59 -> 0.14680111 | AA59: =TEXT(B59,"MMMM") -> February | AB59: =YEAR(B59) -> 2024 | AC59: =IF(OR(AF59 = "Invalid Discount",AG59="Invalid Discount",AH59="Invalid Shipping Record",AE59="Review Required"),"Invalid",IF(OR(G59="Unknown",M59="Unknown",ISBLANK(P59)),"Warning","Clean")) -> Clean | AD59: =A59&B59&C59&D59&E59&F59&G59&H59&I59&J59&K59&L59&M59&N59&O59&P59&Q59&R59&S59&T59&U59&V59 -> ORD-2024-100584532945337CUST-9941Priya MenonConsumerWestGoaPanajiFurnitureChairsMax Chairs 813Same Day5255.8701279.351091.54187.81PaidCompleted8 | AE59: =IF(COUNTIF($A$2:$A$933,A59)=1,"OK",IF(COUNTIF($AD$2:$AD$933,AD59)>1,"Exact Duplicate", "Review Required")) -> OK | AF59: =IF(P59<0,"Invalid Discount","") | AG59: =IF(P59>1,"Invalid Discount","") | AH59: =IF(V59<1,"Invalid Shipping Record","") | AI59: =IF(ROUND(Q59,2)=ROUND(X59,2),"Match","Mismatch") -> Match | AJ59: =IF(ROUND(S59,2)=ROUND(Y59,2),"Match","Mismatch") -> Match | AK59: =PROPER(TRIM(raw_orders!G59)) -> West | AL59: =PROPER(TRIM(raw_orders!M59)) -> Same Day
A60: ORD-2024-10059 | B60: 45536 | C60: 45542 | D60: CUST-3983 | E60: =PROPER(TRIM(raw_orders!E60)) -> Isha Nair | F60: =PROPER(TRIM(raw_orders!F60)) -> Home Office | G60: =PROPER(TRIM(raw_orders!G60)) -> North | H60: =PROPER(TRIM(raw_orders!H60)) -> Rajasthan | I60: =PROPER(TRIM(raw_orders!I60)) -> Jaipur | J60: =PROPER(TRIM(raw_orders!J60)) -> Office Supplies | K60: =PROPER(TRIM(raw_orders!K60)) -> Storage | L60: Basic Storage 872 | M60: Unknown | N60: 9 | O60: 1389.48 | P60: 0.1 | Q60: 11254.79 | R60: 6578.06 | S60: 4676.73 | T60: =PROPER(TRIM(raw_orders!T60)) -> Pending | U60: =PROPER(TRIM(raw_orders!U60)) -> Returned | V60: =C60-B60 -> 6 | W60: =IF(AND(P60="",Q60<>"",N60<>"",S60<>""),0,IF(OR(P60<0,P60>1),P60,P60)) -> 0.1 | X60: =N60*O60*(1-P60) -> 11254.788 | Y60: =X60-R60 -> 4676.728 | Z60: =Y60/X60 -> 0.41553231 | AA60: =TEXT(B60,"MMMM") -> September | AB60: =YEAR(B60) -> 2024 | AC60: =IF(OR(AF60 = "Invalid Discount",AG60="Invalid Discount",AH60="Invalid Shipping Record",AE60="Review Required"),"Invalid",IF(OR(G60="Unknown",M60="Unknown",ISBLANK(P60)),"Warning","Clean")) -> Warning | AD60: =A60&B60&C60&D60&E60&F60&G60&H60&I60&J60&K60&L60&M60&N60&O60&P60&Q60&R60&S60&T60&U60&V60 -> ORD-2024-100594553645542CUST-3983Isha NairHome OfficeNorthRajasthanJaipurOffice SuppliesStorageBasic Storage 872Unknown91389.480.111254.796578.064676.73PendingReturned6 | AE60: =IF(COUNTIF($A$2:$A$933,A60)=1,"OK",IF(COUNTIF($AD$2:$AD$933,AD60)>1,"Exact Duplicate", "Review Required")) -> OK | AF60: =IF(P60<0,"Invalid Discount","") | AG60: =IF(P60>1,"Invalid Discount","") | AH60: =IF(V60<1,"Invalid Shipping Record","") | AI60: =IF(ROUND(Q60,2)=ROUND(X60,2),"Match","Mismatch") -> Match | AJ60: =IF(ROUND(S60,2)=ROUND(Y60,2),"Match","Mismatch") -> Match | AK60: =PROPER(TRIM(raw_orders!G60)) -> North | AL60: =PROPER(TRIM(raw_orders!M60))
A61: ORD-2024-10060 | B61: 45493 | C61: 45498 | D61: CUST-2418 | E61: =PROPER(TRIM(raw_orders!E61)) -> Priya Menon | F61: =PROPER(TRIM(raw_orders!F61)) -> Corporate | G61: =PROPER(TRIM(raw_orders!G61)) -> East | H61: =PROPER(TRIM(raw_orders!H61)) -> Assam | I61: =PROPER(TRIM(raw_orders!I61)) -> Guwahati | J61: =PROPER(TRIM(raw_orders!J61)) -> Office Supplies | K61: =PROPER(TRIM(raw_orders!K61)) -> Labels | L61: Smart Labels 655 | M61: =PROPER(TRIM(raw_orders!M61)) -> Same Day | N61: 5 | O61: 4133.85 | P61: 0.2 | Q61: 16535.4 | R61: 12990.21 | S61: 3545.19 | T61: =PROPER(TRIM(raw_orders!T61)) -> Paid | U61: =PROPER(TRIM(raw_orders!U61)) -> Cancelled | V61: =C61-B61 -> 5 | W61: =IF(AND(P61="",Q61<>"",N61<>"",S61<>""),0,IF(OR(P61<0,P61>1),P61,P61)) -> 0.2 | X61: =N61*O61*(1-P61) -> 16535.4 | Y61: =X61-R61 -> 3545.19 | Z61: =Y61/X61 -> 0.21440001 | AA61: =TEXT(B61,"MMMM") -> July | AB61: =YEAR(B61) -> 2024 | AC61: =IF(OR(AF61 = "Invalid Discount",AG61="Invalid Discount",AH61="Invalid Shipping Record",AE61="Review Required"),"Invalid",IF(OR(G61="Unknown",M61="Unknown",ISBLANK(P61)),"Warning","Clean")) -> Clean | AD61: =A61&B61&C61&D61&E61&F61&G61&H61&I61&J61&K61&L61&M61&N61&O61&P61&Q61&R61&S61&T61&U61&V61 -> ORD-2024-100604549345498CUST-2418Priya MenonCorporateEastAssamGuwahatiOffice SuppliesLabelsSmart Labels 655Same Day54133.850.216535.412990.213545.19PaidCancelled5 | AE61: =IF(COUNTIF($A$2:$A$933,A61)=1,"OK",IF(COUNTIF($AD$2:$AD$933,AD61)>1,"Exact Duplicate", "Review Required")) -> OK | AF61: =IF(P61<0,"Invalid Discount","") | AG61: =IF(P61>1,"Invalid Discount","") | AH61: =IF(V61<1,"Invalid Shipping Record","") | AI61: =IF(ROUND(Q61,2)=ROUND(X61,2),"Match","Mismatch") -> Match | AJ61: =IF(ROUND(S61,2)=ROUND(Y61,2),"Match","Mismatch") -> Match | AK61: =PROPER(TRIM(raw_orders!G61)) -> East | AL61: =PROPER(TRIM(raw_orders!M61)) -> Same Day
A62: ORD-2024-10061 | B62: 45486 | C62: 45492 | D62: CUST-2892 | E62: =PROPER(TRIM(raw_orders!E62)) -> Ananya Rao | F62: =PROPER(TRIM(raw_orders!F62)) -> Corporate | G62: =PROPER(TRIM(raw_orders!G62)) -> East | H62: =PROPER(TRIM(raw_orders!H62)) -> Assam | I62: =PROPER(TRIM(raw_orders!I62)) -> Guwahati | J62: =PROPER(TRIM(raw_orders!J62)) -> Office Supplies | K62: =PROPER(TRIM(raw_orders!K62)) -> Labels | L62: Eco Labels 210 | M62: =PROPER(TRIM(raw_orders!M62)) -> Same Day | N62: 3 | O62: 275.76 | P62: 0.2 | Q62: 661.82 | R62: 481.47 | S62: 180.35 | T62: =PROPER(TRIM(raw_orders!T62)) -> Refunded | U62: =PROPER(TRIM(raw_orders!U62)) -> Cancelled | V62: =C62-B62 -> 6 | W62: =IF(AND(P62="",Q62<>"",N62<>"",S62<>""),0,IF(OR(P62<0,P62>1),P62,P62)) -> 0.2 | X62: =N62*O62*(1-P62) -> 661.824 | Y62: =X62-R62 -> 180.354 | Z62: =Y62/X62 -> 0.27251052 | AA62: =TEXT(B62,"MMMM") -> July | AB62: =YEAR(B62) -> 2024 | AC62: =IF(OR(AF62 = "Invalid Discount",AG62="Invalid Discount",AH62="Invalid Shipping Record",AE62="Review Required"),"Invalid",IF(OR(G62="Unknown",M62="Unknown",ISBLANK(P62)),"Warning","Clean")) -> Clean | AD62: =A62&B62&C62&D62&E62&F62&G62&H62&I62&J62&K62&L62&M62&N62&O62&P62&Q62&R62&S62&T62&U62&V62 -> ORD-2024-100614548645492CUST-2892Ananya RaoCorporateEastAssamGuwahatiOffice SuppliesLabelsEco Labels 210Same Day3275.760.2661.82481.47180.35RefundedCancelled6 | AE62: =IF(COUNTIF($A$2:$A$933,A62)=1,"OK",IF(COUNTIF($AD$2:$AD$933,AD62)>1,"Exact Duplicate", "Review Required")) -> OK | AF62: =IF(P62<0,"Invalid Discount","") | AG62: =IF(P62>1,"Invalid Discount","") | AH62: =IF(V62<1,"Invalid Shipping Record","") | AI62: =IF(ROUND(Q62,2)=ROUND(X62,2),"Match","Mismatch") -> Match | AJ62: =IF(ROUND(S62,2)=ROUND(Y62,2),"Match","Mismatch") -> Match | AK62: =PROPER(TRIM(raw_orders!G62)) -> East | AL62: =PROPER(TRIM(raw_orders!M62)) -> Same Day
A63: ORD-2024-10062 | B63: 45398 | C63: 45398 | D63: CUST-7008 | E63: =PROPER(TRIM(raw_orders!E63)) -> Vikram Iyer | F63: =PROPER(TRIM(raw_orders!F63)) -> Home Office | G63: =PROPER(TRIM(raw_orders!G63)) -> East | H63: =PROPER(TRIM(raw_orders!H63)) -> Bihar | I63: =PROPER(TRIM(raw_orders!I63)) -> Patna | J63: =PROPER(TRIM(raw_orders!J63)) -> Furniture | K63: =PROPER(TRIM(raw_orders!K63)) -> Bookcases | L63: Classic Bookcases 296 | M63: =PROPER(TRIM(raw_orders!M63)) -> Standard Class | N63: 1 | O63: 949.59 | P63: 0 | Q63: 949.59 | R63: 751.25 | S63: 198.34 | T63: =PROPER(TRIM(raw_orders!T63)) -> Paid | U63: =PROPER(TRIM(raw_orders!U63)) -> Completed | V63: =C63-B63 -> 0 | W63: =IF(AND(P63="",Q63<>"",N63<>"",S63<>""),0,IF(OR(P63<0,P63>1),P63,P63)) -> 0 | X63: =N63*O63*(1-P63) -> 949.59 | Y63: =X63-R63 -> 198.34 | Z63: =Y63/X63 -> 0.20886909 | AA63: =TEXT(B63,"MMMM") -> April | AB63: =YEAR(B63) -> 2024 | AC63: =IF(OR(AF63 = "Invalid Discount",AG63="Invalid Discount",AH63="Invalid Shipping Record",AE63="Review Required"),"Invalid",IF(OR(G63="Unknown",M63="Unknown",ISBLANK(P63)),"Warning","Clean")) -> Clean | AD63: =A63&B63&C63&D63&E63&F63&G63&H63&I63&J63&K63&L63&M63&N63&O63&P63&Q63&R63&S63&T63&U63&V63 -> ORD-2024-100624539845398CUST-7008Vikram IyerHome OfficeEastBiharPatnaFurnitureBookcasesClassic Bookcases 296Standard Class1949.590949.59751.25198.34PaidCompleted0 | AE63: =IF(COUNTIF($A$2:$A$933,A63)=1,"OK",IF(COUNTIF($AD$2:$AD$933,AD63)>1,"Exact Duplicate", "Review Required")) -> OK | AF63: =IF(P63<0,"Invalid Discount","") | AG63: =IF(P63>1,"Invalid Discount","") | AH63: =IF(V63<0,"Invalid Shipping Record","") | AI63: =IF(ROUND(Q63,2)=ROUND(X63,2),"Match","Mismatch") -> Match | AJ63: =IF(ROUND(S63,2)=ROUND(Y63,2),"Match","Mismatch") -> Match | AK63: =PROPER(TRIM(raw_orders!G63)) -> East | AL63: =PROPER(TRIM(raw_orders!M63)) -> Standard Class
A64: ORD-2024-10063 | B64: 45595 | C64: 45333 | D64: CUST-4900 | E64: =PROPER(TRIM(raw_orders!E64)) -> Sneha Kapoor | F64: =PROPER(TRIM(raw_orders!F64)) -> Home Office | G64: =PROPER(TRIM(raw_orders!G64)) -> North | H64: =PROPER(TRIM(raw_orders!H64)) -> Rajasthan | I64: =PROPER(TRIM(raw_orders!I64)) -> Jaipur | J64: =PROPER(TRIM(raw_orders!J64)) -> Technology | K64: =PROPER(TRIM(raw_orders!K64)) -> Phones | L64: Basic Phones 230 | M64: =PROPER(TRIM(raw_orders!M64)) -> Standard Class | N64: 9 | O64: 3042.29 | P64: 0.2 | Q64: 21904.49 | R64: 13570.55 | S64: 8333.94 | T64: =PROPER(TRIM(raw_orders!T64)) -> Paid | U64: =PROPER(TRIM(raw_orders!U64)) -> Completed | V64: =C64-B64 -> -262 | W64: =IF(AND(P64="",Q64<>"",N64<>"",S64<>""),0,IF(OR(P64<0,P64>1),P64,P64)) -> 0.2 | X64: =N64*O64*(1-P64) -> 21904.488 | Y64: =X64-R64 -> 8333.938 | Z64: =Y64/X64 -> 0.38046714 | AA64: =TEXT(B64,"MMMM") -> October | AB64: =YEAR(B64) -> 2024 | AC64: =IF(OR(AF64 = "Invalid Discount",AG64="Invalid Discount",AH64="Invalid Shipping Record",AE64="Review Required"),"Invalid",IF(OR(G64="Unknown",M64="Unknown",ISBLANK(P64)),"Warning","Clean")) -> Invalid | AD64: =A64&B64&C64&D64&E64&F64&G64&H64&I64&J64&K64&L64&M64&N64&O64&P64&Q64&R64&S64&T64&U64&V64 -> ORD-2024-100634559545333CUST-4900Sneha KapoorHome OfficeNorthRajasthanJaipurTechnologyPhonesBasic Phones 230Standard Class93042.290.221904.4913570.558333.94PaidCompleted-262 | AE64: =IF(COUNTIF($A$2:$A$933,A64)=1,"OK",IF(COUNTIF($AD$2:$AD$933,AD64)>1,"Exact Duplicate", "Review Required")) -> OK | AF64: =IF(P64<0,"Invalid Discount","") | AG64: =IF(P64>1,"Invalid Discount","") | AH64: =IF(V64<0,"Invalid Shipping Record","") -> Invalid Shipping Record | AI64: =IF(ROUND(Q64,2)=ROUND(X64,2),"Match","Mismatch") -> Match | AJ64: =IF(ROUND(S64,2)=ROUND(Y64,2),"Match","Mismatch") -> Match | AK64: =PROPER(TRIM(raw_orders!G64)) -> North | AL64: =PROPER(TRIM(raw_orders!M64)) -> Standard Class
A65: ORD-2024-10064 | B65: 45316 | C65: 45293 | D65: CUST-5382 | E65: =PROPER(TRIM(raw_orders!E65)) -> Sneha Kapoor | F65: =PROPER(TRIM(raw_orders!F65)) -> Home Office | G65: =PROPER(TRIM(raw_orders!G65)) -> North | H65: =PROPER(TRIM(raw_orders!H65)) -> Haryana | I65: =PROPER(TRIM(raw_orders!I65)) -> Gurugram | J65: =PROPER(TRIM(raw_orders!J65)) -> Office Supplies | K65: =PROPER(TRIM(raw_orders!K65)) -> Binders | L65: Pro Binders 690 | M65: =PROPER(TRIM(raw_orders!M65)) -> Same Day | N65: 2 | O65: 2832.77 | P65: 0.15 | Q65: 4815.71 | R65: 3027.75 | S65: 1917.47 | T65: =PROPER(TRIM(raw_orders!T65)) -> Paid | U65: =PROPER(TRIM(raw_orders!U65)) -> Completed | V65: =C65-B65 -> -23 | W65: =IF(AND(P65="",Q65<>"",N65<>"",S65<>""),0,IF(OR(P65<0,P65>1),P65,P65)) -> 0.15 | X65: =N65*O65*(1-P65) -> 4815.709 | Y65: =X65-R65 -> 1787.959 | Z65: =Y65/X65 -> 0.37127638 | AA65: =TEXT(B65,"MMMM") -> January | AB65: =YEAR(B65) -> 2024 | AC65: =IF(OR(AF65 = "Invalid Discount",AG65="Invalid Discount",AH65="Invalid Shipping Record",AE65="Review Required"),"Invalid",IF(OR(G65="Unknown",M65="Unknown",ISBLANK(P65)),"Warning","Clean")) -> Invalid | AD65: =A65&B65&C65&D65&E65&F65&G65&H65&I65&J65&K65&L65&M65&N65&O65&P65&Q65&R65&S65&T65&U65&V65 -> ORD-2024-100644531645293CUST-5382Sneha KapoorHome OfficeNorthHaryanaGurugramOffice SuppliesBindersPro Binders 690Same Day22832.770.154815.713027.751917.47PaidCompleted-23 | AE65: =IF(COUNTIF($A$2:$A$933,A65)=1,"OK",IF(COUNTIF($AD$2:$AD$933,AD65)>1,"Exact Duplicate", "Review Required")) -> OK | AF65: =IF(P65<0,"Invalid Discount","") | AG65: =IF(P65>1,"Invalid Discount","") | AH65: =IF(V65<0,"Invalid Shipping Record","") -> Invalid Shipping Record | AI65: =IF(ROUND(Q65,2)=ROUND(X65,2),"Match","Mismatch") -> Match | AJ65: =IF(ROUND(S65,2)=ROUND(Y65,2),"Match","Mismatch") -> Mismatch | AK65: =PROPER(TRIM(raw_orders!G65)) -> North | AL65: =PROPER(TRIM(raw_orders!M65)) -> Same Day
A66: ORD-2024-10065 | B66: 45649 | C66: 45655 | D66: CUST-2749 | E66: =PROPER(TRIM(raw_orders!E66)) -> Aarav Sharma | F66: =PROPER(TRIM(raw_orders!F66)) -> Corporate | G66: =PROPER(TRIM(raw_orders!G66)) -> East | H66: =PROPER(TRIM(raw_orders!H66)) -> Jharkhand | I66: =PROPER(TRIM(raw_orders!I66)) -> Ranchi | J66: =PROPER(TRIM(raw_orders!J66)) -> Office Supplies | K66: =PROPER(TRIM(raw_orders!K66)) -> Paper | L66: Classic Paper 458 | M66: =PROPER(TRIM(raw_orders!M66)) -> First Class | N66: 7 | O66: 447.84 | P66: 0 | Q66: 3134.88 | R66: 2367.63 | S66: 767.25 | T66: =PROPER(TRIM(raw_orders!T66)) -> Refunded | U66: =PROPER(TRIM(raw_orders!U66)) -> Returned | V66: =C66-B66 -> 6 | W66: =IF(AND(P66="",Q66<>"",N66<>"",S66<>""),0,IF(OR(P66<0,P66>1),P66,P66)) -> 0 | X66: =N66*O66*(1-P66) -> 3134.88 | Y66: =X66-R66 -> 767.25 | Z66: =Y66/X66 -> 0.24474621 | AA66: =TEXT(B66,"MMMM") -> December | AB66: =YEAR(B66) -> 2024 | AC66: =IF(OR(AF66 = "Invalid Discount",AG66="Invalid Discount",AH66="Invalid Shipping Record",AE66="Review Required"),"Invalid",IF(OR(G66="Unknown",M66="Unknown",ISBLANK(P66)),"Warning","Clean")) -> Clean | AD66: =A66&B66&C66&D66&E66&F66&G66&H66&I66&J66&K66&L66&M66&N66&O66&P66&Q66&R66&S66&T66&U66&V66 -> ORD-2024-100654564945655CUST-2749Aarav SharmaCorporateEastJharkhandRanchiOffice SuppliesPaperClassic Paper 458First Class7447.8403134.882367.63767.25RefundedReturned6 | AE66: =IF(COUNTIF($A$2:$A$933,A66)=1,"OK",IF(COUNTIF($AD$2:$AD$933,AD66)>1,"Exact Duplicate", "Review Required")) -> OK | AF66: =IF(P66<0,"Invalid Discount","") | AG66: =IF(P66>1,"Invalid Discount","") | AH66: =IF(V66<1,"Invalid Shipping Record","") | AI66: =IF(ROUND(Q66,2)=ROUND(X66,2),"Match","Mismatch") -> Match | AJ66: =IF(ROUND(S66,2)=ROUND(Y66,2),"Match","Mismatch") -> Match | AK66: =PROPER(TRIM(raw_orders!G66)) -> East | AL66: =PROPER(TRIM(raw_orders!M66)) -> First Class
A67: ORD-2024-10066 | B67: 45404 | C67: 45409 | D67: CUST-2463 | E67: =PROPER(TRIM(raw_orders!E67)) -> Mira Das | F67: =PROPER(TRIM(raw_orders!F67)) -> Home Office | G67: =PROPER(TRIM(raw_orders!G67)) -> West | H67: =PROPER(TRIM(raw_orders!H67)) -> Maharashtra | I67: =PROPER(TRIM(raw_orders!I67)) -> Mumbai | J67: =PROPER(TRIM(raw_orders!J67)) -> Office Supplies | K67: =PROPER(TRIM(raw_orders!K67)) -> Paper | L67: Pro Paper 552 | M67: =PROPER(TRIM(raw_orders!M67)) -> Second Class | N67: 1 | O67: 4280.19 | P67: 0.05 | Q67: 4066.18 | R67: 2628.92 | S67: 1437.26 | T67: =PROPER(TRIM(raw_orders!T67)) -> Paid | U67: =PROPER(TRIM(raw_orders!U67)) -> Completed | V67: =C67-B67 -> 5 | W67: =IF(AND(P67="",Q67<>"",N67<>"",S67<>""),0,IF(OR(P67<0,P67>1),P67,P67)) -> 0.05 | X67: =N67*O67*(1-P67) -> 4066.1805 | Y67: =X67-R67 -> 1437.2605 | Z67: =Y67/X67 -> 0.35346697 | AA67: =TEXT(B67,"MMMM") -> April | AB67: =YEAR(B67) -> 2024 | AC67: =IF(OR(AF67 = "Invalid Discount",AG67="Invalid Discount",AH67="Invalid Shipping Record",AE67="Review Required"),"Invalid",IF(OR(G67="Unknown",M67="Unknown",ISBLANK(P67)),"Warning","Clean")) -> Clean | AD67: =A67&B67&C67&D67&E67&F67&G67&H67&I67&J67&K67&L67&M67&N67&O67&P67&Q67&R67&S67&T67&U67&V67 -> ORD-2024-100664540445409CUST-2463Mira DasHome OfficeWestMaharashtraMumbaiOffice SuppliesPaperPro Paper 552Second Class14280.190.054066.182628.921437.26PaidCompleted5 | AE67: =IF(COUNTIF($A$2:$A$933,A67)=1,"OK",IF(COUNTIF($AD$2:$AD$933,AD67)>1,"Exact Duplicate", "Review Required")) -> OK | AF67: =IF(P67<0,"Invalid Discount","") | AG67: =IF(P67>1,"Invalid Discount","") | AH67: =IF(V67<1,"Invalid Shipping Record","") | AI67: =IF(ROUND(Q67,2)=ROUND(X67,2),"Match","Mismatch") -> Match | AJ67: =IF(ROUND(S67,2)=ROUND(Y67,2),"Match","Mismatch") -> Match | AK67: =PROPER(TRIM(raw_orders!G67)) -> West | AL67: =PROPER(TRIM(raw_orders!M67)) -> Second Class
A68: ORD-2025-10067 | B68: 45897 | C68: 45901 | D68: CUST-1504 | E68: =PROPER(TRIM(raw_orders!E68)) -> Karan Malhotra | F68: =PROPER(TRIM(raw_orders!F68)) -> Small Business | G68: =PROPER(TRIM(raw_orders!G68)) -> South | H68: =PROPER(TRIM(raw_orders!H68)) -> Tamil Nadu | I68: =PROPER(TRIM(raw_orders!I68)) -> Chennai | J68: =PROPER(TRIM(raw_orders!J68)) -> Technology | K68: =PROPER(TRIM(raw_orders!K68)) -> Accessories | L68: Elite Accessories 187 | M68: =PROPER(TRIM(raw_orders!M68)) -> Same Day | N68: 7 | O68: 1057.46 | P68: 0.05 | Q68: 7032.11 | R68: 4610.34 | S68: 2421.77 | T68: =PROPER(TRIM(raw_orders!T68)) -> Paid | U68: =PROPER(TRIM(raw_orders!U68)) -> Completed | V68: =C68-B68 -> 4 | W68: =IF(AND(P68="",Q68<>"",N68<>"",S68<>""),0,IF(OR(P68<0,P68>1),P68,P68)) -> 0.05 | X68: =N68*O68*(1-P68) -> 7032.109 | Y68: =X68-R68 -> 2421.769 | Z68: =Y68/X68 -> 0.3443873 | AA68: =TEXT(B68,"MMMM") -> August | AB68: =YEAR(B68) -> 2025 | AC68: =IF(OR(AF68 = "Invalid Discount",AG68="Invalid Discount",AH68="Invalid Shipping Record",AE68="Review Required"),"Invalid",IF(OR(G68="Unknown",M68="Unknown",ISBLANK(P68)),"Warning","Clean")) -> Clean | AD68: =A68&B68&C68&D68&E68&F68&G68&H68&I68&J68&K68&L68&M68&N68&O68&P68&Q68&R68&S68&T68&U68&V68 -> ORD-2025-100674589745901CUST-1504Karan MalhotraSmall BusinessSouthTamil NaduChennaiTechnologyAccessoriesElite Accessories 187Same Day71057.460.057032.114610.342421.77PaidCompleted4 | AE68: =IF(COUNTIF($A$2:$A$933,A68)=1,"OK",IF(COUNTIF($AD$2:$AD$933,AD68)>1,"Exact Duplicate", "Review Required")) -> OK | AF68: =IF(P68<0,"Invalid Discount","") | AG68: =IF(P68>1,"Invalid Discount","") | AH68: =IF(V68<1,"Invalid Shipping Record","") | AI68: =IF(ROUND(Q68,2)=ROUND(X68,2),"Match","Mismatch") -> Match | AJ68: =IF(ROUND(S68,2)=ROUND(Y68,2),"Match","Mismatch") -> Match | AK68: =PROPER(TRIM(raw_orders!G68)) -> South | AL68: =PROPER(TRIM(raw_orders!M68)) -> Same Day
A69: ORD-2025-10068 | B69: 45691 | C69: 45840 | D69: CUST-8282 | E69: =PROPER(TRIM(raw_orders!E69)) -> Kabir Singh | F69: =PROPER(TRIM(raw_orders!F69)) -> Consumer | G69: =PROPER(TRIM(raw_orders!G69)) -> North | H69: =PROPER(TRIM(raw_orders!H69)) -> Haryana | I69: =PROPER(TRIM(raw_orders!I69)) -> Gurugram | J69: =PROPER(TRIM(raw_orders!J69)) -> Office Supplies | K69: =PROPER(TRIM(raw_orders!K69)) -> Paper | L69: Eco Paper 922 | M69: =PROPER(TRIM(raw_orders!M69)) -> First Class | N69: 7 | O69: 3609.34 | P69: 0.05 | Q69: 24002.11 | R69: 18707.57 | S69: 5294.54 | T69: =PROPER(TRIM(raw_orders!T69)) -> Paid | U69: =PROPER(TRIM(raw_orders!U69)) -> Completed | V69: =C69-B69 -> 149 | W69: =IF(AND(P69="",Q69<>"",N69<>"",S69<>""),0,IF(OR(P69<0,P69>1),P69,P69)) -> 0.05 | X69: =N69*O69*(1-P69) -> 24002.111 | Y69: =X69-R69 -> 5294.541 | Z69: =Y69/X69 -> 0.22058647 | AA69: =TEXT(B69,"MMMM") -> February | AB69: =YEAR(B69) -> 2025 | AC69: =IF(OR(AF69 = "Invalid Discount",AG69="Invalid Discount",AH69="Invalid Shipping Record",AE69="Review Required"),"Invalid",IF(OR(G69="Unknown",M69="Unknown",ISBLANK(P69)),"Warning","Clean")) -> Clean | AD69: =A69&B69&C69&D69&E69&F69&G69&H69&I69&J69&K69&L69&M69&N69&O69&P69&Q69&R69&S69&T69&U69&V69 -> ORD-2025-100684569145840CUST-8282Kabir SinghConsumerNorthHaryanaGurugramOffice SuppliesPaperEco Paper 922First Class73609.340.0524002.1118707.575294.54PaidCompleted149 | AE69: =IF(COUNTIF($A$2:$A$933,A69)=1,"OK",IF(COUNTIF($AD$2:$AD$933,AD69)>1,"Exact Duplicate", "Review Required")) -> OK | AF69: =IF(P69<0,"Invalid Discount","") | AG69: =IF(P69>1,"Invalid Discount","") | AH69: =IF(V69<1,"Invalid Shipping Record","") | AI69: =IF(ROUND(Q69,2)=ROUND(X69,2),"Match","Mismatch") -> Match | AJ69: =IF(ROUND(S69,2)=ROUND(Y69,2),"Match","Mismatch") -> Match | AK69: =PROPER(TRIM(raw_orders!G69)) -> North | AL69: =PROPER(TRIM(raw_orders!M69)) -> First Class
A70: ORD-2024-10069 | B70: 45606 | C70: 45609 | D70: CUST-6054 | E70: =PROPER(TRIM(raw_orders!E70)) -> Isha Nair | F70: =PROPER(TRIM(raw_orders!F70)) -> Corporate | G70: =PROPER(TRIM(raw_orders!G70)) -> East | H70: =PROPER(TRIM(raw_orders!H70)) -> Jharkhand | I70: =PROPER(TRIM(raw_orders!I70)) -> Ranchi | J70: =PROPER(TRIM(raw_orders!J70)) -> Office Supplies | K70: =PROPER(TRIM(raw_orders!K70)) -> Storage | L70: Pro Storage 975 | M70: =PROPER(TRIM(raw_orders!M70)) -> Second Class | N70: 9 | O70: 2211.12 | P70: 0 | Q70: 19900.08 | R70: 10962.66 | S70: 8937.42 | T70: =PROPER(TRIM(raw_orders!T70)) -> Failed | U70: =PROPER(TRIM(raw_orders!U70)) -> Returned | V70: =C70-B70 -> 3 | W70: =IF(AND(P70="",Q70<>"",N70<>"",S70<>""),0,IF(OR(P70<0,P70>1),P70,P70)) -> 0 | X70: =N70*O70*(1-P70) -> 19900.08 | Y70: =X70-R70 -> 8937.42 | Z70: =Y70/X70 -> 0.44911478 | AA70: =TEXT(B70,"MMMM") -> November | AB70: =YEAR(B70) -> 2024 | AC70: =IF(OR(AF70 = "Invalid Discount",AG70="Invalid Discount",AH70="Invalid Shipping Record",AE70="Review Required"),"Invalid",IF(OR(G70="Unknown",M70="Unknown",ISBLANK(P70)),"Warning","Clean")) -> Clean | AD70: =A70&B70&C70&D70&E70&F70&G70&H70&I70&J70&K70&L70&M70&N70&O70&P70&Q70&R70&S70&T70&U70&V70 -> ORD-2024-100694560645609CUST-6054Isha NairCorporateEastJharkhandRanchiOffice SuppliesStoragePro Storage 975Second Class92211.12019900.0810962.668937.42FailedReturned3 | AE70: =IF(COUNTIF($A$2:$A$933,A70)=1,"OK",IF(COUNTIF($AD$2:$AD$933,AD70)>1,"Exact Duplicate", "Review Required")) -> OK | AF70: =IF(P70<0,"Invalid Discount","") | AG70: =IF(P70>1,"Invalid Discount","") | AH70: =IF(V70<1,"Invalid Shipping Record","") | AI70: =IF(ROUND(Q70,2)=ROUND(X70,2),"Match","Mismatch") -> Match | AJ70: =IF(ROUND(S70,2)=ROUND(Y70,2),"Match","Mismatch") -> Match | AK70: =PROPER(TRIM(raw_orders!G70)) -> East | AL70: =PROPER(TRIM(raw_orders!M70)) -> Second Class
A71: ORD-2024-10070 | B71: 45391 | C71: 45396 | D71: CUST-5979 | E71: =PROPER(TRIM(raw_orders!E71)) -> Neha Gupta | F71: =PROPER(TRIM(raw_orders!F71)) -> Small Business | G71: =PROPER(TRIM(raw_orders!G71)) -> West | H71: =PROPER(TRIM(raw_orders!H71)) -> Gujarat | I71: =PROPER(TRIM(raw_orders!I71)) -> Ahmedabad | J71: =PROPER(TRIM(raw_orders!J71)) -> Technology | K71: =PROPER(TRIM(raw_orders!K71)) -> Machines | L71: Prime Machines 782 | M71: =PROPER(TRIM(raw_orders!M71)) -> Same Day | N71: 7 | O71: 3417.09 | P71: 0.1 | Q71: 21527.67 | R71: 18287.58 | S71: 3240.09 | T71: =PROPER(TRIM(raw_orders!T71)) -> Refunded | U71: =PROPER(TRIM(raw_orders!U71)) -> Returned | V71: =C71-B71 -> 5 | W71: =IF(AND(P71="",Q71<>"",N71<>"",S71<>""),0,IF(OR(P71<0,P71>1),P71,P71)) -> 0.1 | X71: =N71*O71*(1-P71) -> 21527.667 | Y71: =X71-R71 -> 3240.087 | Z71: =Y71/X71 -> 0.15050804 | AA71: =TEXT(B71,"MMMM") -> April | AB71: =YEAR(B71) -> 2024 | AC71: =IF(OR(AF71 = "Invalid Discount",AG71="Invalid Discount",AH71="Invalid Shipping Record",AE71="Review Required"),"Invalid",IF(OR(G71="Unknown",M71="Unknown",ISBLANK(P71)),"Warning","Clean")) -> Clean | AD71: =A71&B71&C71&D71&E71&F71&G71&H71&I71&J71&K71&L71&M71&N71&O71&P71&Q71&R71&S71&T71&U71&V71 -> ORD-2024-100704539145396CUST-5979Neha GuptaSmall BusinessWestGujaratAhmedabadTechnologyMachinesPrime Machines 782Same Day73417.090.121527.6718287.583240.09RefundedReturned5 | AE71: =IF(COUNTIF($A$2:$A$933,A71)=1,"OK",IF(COUNTIF($AD$2:$AD$933,AD71)>1,"Exact Duplicate", "Review Required")) -> OK | AF71: =IF(P71<0,"Invalid Discount","") | AG71: =IF(P71>1,"Invalid Discount","") | AH71: =IF(V71<1,"Invalid Shipping Record","") | AI71: =IF(ROUND(Q71,2)=ROUND(X71,2),"Match","Mismatch") -> Match | AJ71: =IF(ROUND(S71,2)=ROUND(Y71,2),"Match","Mismatch") -> Match | AK71: =PROPER(TRIM(raw_orders!G71)) -> West | AL71: =PROPER(TRIM(raw_orders!M71)) -> Same Day
A72: ORD-2025-10071 | B72: 45891 | C72: 45896 | D72: CUST-5582 | E72: =PROPER(TRIM(raw_orders!E72)) -> Karan Malhotra | F72: =PROPER(TRIM(raw_orders!F72)) -> Corporate | G72: =PROPER(TRIM(raw_orders!G72)) -> South | H72: =PROPER(TRIM(raw_orders!H72)) -> Andhra Pradesh | I72: =PROPER(TRIM(raw_orders!I72)) -> Vijayawada | J72: =PROPER(TRIM(raw_orders!J72)) -> Technology | K72: =PROPER(TRIM(raw_orders!K72)) -> Phones | L72: Max Phones 661 | M72: =PROPER(TRIM(raw_orders!M72)) -> First Class | N72: 2 | O72: 905.87 | P72: 0.15 | Q72: 1539.98 | R72: 1070.2 | S72: 469.78 | T72: =PROPER(TRIM(raw_orders!T72)) -> Paid | U72: =PROPER(TRIM(raw_orders!U72)) -> Completed | V72: =C72-B72 -> 5 | W72: =IF(AND(P72="",Q72<>"",N72<>"",S72<>""),0,IF(OR(P72<0,P72>1),P72,P72)) -> 0.15 | X72: =N72*O72*(1-P72) -> 1539.979 | Y72: =X72-R72 -> 469.779 | Z72: =Y72/X72 -> 0.30505546 | AA72: =TEXT(B72,"MMMM") -> August | AB72: =YEAR(B72) -> 2025 | AC72: =IF(OR(AF72 = "Invalid Discount",AG72="Invalid Discount",AH72="Invalid Shipping Record",AE72="Review Required"),"Invalid",IF(OR(G72="Unknown",M72="Unknown",ISBLANK(P72)),"Warning","Clean")) -> Clean | AD72: =A72&B72&C72&D72&E72&F72&G72&H72&I72&J72&K72&L72&M72&N72&O72&P72&Q72&R72&S72&T72&U72&V72 -> ORD-2025-100714589145896CUST-5582Karan MalhotraCorporateSouthAndhra PradeshVijayawadaTechnologyPhonesMax Phones 661First Class2905.870.151539.981070.2469.78PaidCompleted5 | AE72: =IF(COUNTIF($A$2:$A$933,A72)=1,"OK",IF(COUNTIF($AD$2:$AD$933,AD72)>1,"Exact Duplicate", "Review Required")) -> OK | AF72: =IF(P72<0,"Invalid Discount","") | AG72: =IF(P72>1,"Invalid Discount","") | AH72: =IF(V72<1,"Invalid Shipping Record","") | AI72: =IF(ROUND(Q72,2)=ROUND(X72,2),"Match","Mismatch") -> Match | AJ72: =IF(ROUND(S72,2)=ROUND(Y72,2),"Match","Mismatch") -> Match | AK72: =PROPER(TRIM(raw_orders!G72)) -> South | AL72: =PROPER(TRIM(raw_orders!M72)) -> First Class
A73: ORD-2025-10072 | B73: 45763 | C73: 45770 | D73: CUST-3308 | E73: =PROPER(TRIM(raw_orders!E73)) -> Mira Das | F73: =PROPER(TRIM(raw_orders!F73)) -> Small Business | G73: =PROPER(TRIM(raw_orders!G73)) -> West | H73: =PROPER(TRIM(raw_orders!H73)) -> Goa | I73: =PROPER(TRIM(raw_orders!I73)) -> Panaji | J73: =PROPER(TRIM(raw_orders!J73)) -> Technology | K73: =PROPER(TRIM(raw_orders!K73)) -> Machines | L73: Elite Machines 836 | M73: =PROPER(TRIM(raw_orders!M73)) -> Standard Class | N73: 6 | O73: 2027.32 | P73: 0.1 | Q73: 10947.53 | R73: 6447.36 | S73: 4500.17 | T73: =PROPER(TRIM(raw_orders!T73)) -> Paid | U73: =PROPER(TRIM(raw_orders!U73)) -> Completed | V73: =C73-B73 -> 7 | W73: =IF(AND(P73="",Q73<>"",N73<>"",S73<>""),0,IF(OR(P73<0,P73>1),P73,P73)) -> 0.1 | X73: =N73*O73*(1-P73) -> 10947.528 | Y73: =X73-R73 -> 4500.168 | Z73: =Y73/X73 -> 0.41106705 | AA73: =TEXT(B73,"MMMM") -> April | AB73: =YEAR(B73) -> 2025 | AC73: =IF(OR(AF73 = "Invalid Discount",AG73="Invalid Discount",AH73="Invalid Shipping Record",AE73="Review Required"),"Invalid",IF(OR(G73="Unknown",M73="Unknown",ISBLANK(P73)),"Warning","Clean")) -> Clean | AD73: =A73&B73&C73&D73&E73&F73&G73&H73&I73&J73&K73&L73&M73&N73&O73&P73&Q73&R73&S73&T73&U73&V73 -> ORD-2025-100724576345770CUST-3308Mira DasSmall BusinessWestGoaPanajiTechnologyMachinesElite Machines 836Standard Class62027.320.110947.536447.364500.17PaidCompleted7 | AE73: =IF(COUNTIF($A$2:$A$933,A73)=1,"OK",IF(COUNTIF($AD$2:$AD$933,AD73)>1,"Exact Duplicate", "Review Required")) -> OK | AF73: =IF(P73<0,"Invalid Discount","") | AG73: =IF(P73>1,"Invalid Discount","") | AH73: =IF(V73<1,"Invalid Shipping Record","") | AI73: =IF(ROUND(Q73,2)=ROUND(X73,2),"Match","Mismatch") -> Match | AJ73: =IF(ROUND(S73,2)=ROUND(Y73,2),"Match","Mismatch") -> Match | AK73: =PROPER(TRIM(raw_orders!G73)) -> West | AL73: =PROPER(TRIM(raw_orders!M73)) -> Standard Class
A74: ORD-2024-10073 | B74: 45333 | C74: 45329 | D74: CUST-5018 | E74: =PROPER(TRIM(raw_orders!E74)) -> Karan Malhotra | F74: =PROPER(TRIM(raw_orders!F74)) -> Home Office | G74: =PROPER(TRIM(raw_orders!G74)) -> South | H74: =PROPER(TRIM(raw_orders!H74)) -> Tamil Nadu | I74: =PROPER(TRIM(raw_orders!I74)) -> Chennai | J74: =PROPER(TRIM(raw_orders!J74)) -> Furniture | K74: =PROPER(TRIM(raw_orders!K74)) -> Tables | L74: Prime Tables 902 | M74: =PROPER(TRIM(raw_orders!M74)) -> First Class | N74: 7 | O74: 2287.47 | P74: 0.15 | Q74: 13610.45 | R74: 10039.05 | S74: 3571.4 | T74: =PROPER(TRIM(raw_orders!T74)) -> Paid | U74: =PROPER(TRIM(raw_orders!U74)) -> Completed | V74: =C74-B74 -> -4 | W74: =IF(AND(P74="",Q74<>"",N74<>"",S74<>""),0,IF(OR(P74<0,P74>1),P74,P74)) -> 0.15 | X74: =N74*O74*(1-P74) -> 13610.446 | Y74: =X74-R74 -> 3571.3965 | Z74: =Y74/X74 -> 0.26240113 | AA74: =TEXT(B74,"MMMM") -> February | AB74: =YEAR(B74) -> 2024 | AC74: =IF(OR(AF74 = "Invalid Discount",AG74="Invalid Discount",AH74="Invalid Shipping Record",AE74="Review Required"),"Invalid",IF(OR(G74="Unknown",M74="Unknown",ISBLANK(P74)),"Warning","Clean")) -> Invalid | AD74: =A74&B74&C74&D74&E74&F74&G74&H74&I74&J74&K74&L74&M74&N74&O74&P74&Q74&R74&S74&T74&U74&V74 -> ORD-2024-100734533345329CUST-5018Karan MalhotraHome OfficeSouthTamil NaduChennaiFurnitureTablesPrime Tables 902First Class72287.470.1513610.4510039.053571.4PaidCompleted-4 | AE74: =IF(COUNTIF($A$2:$A$933,A74)=1,"OK",IF(COUNTIF($AD$2:$AD$933,AD74)>1,"Exact Duplicate", "Review Required")) -> OK | AF74: =IF(P74<0,"Invalid Discount","") | AG74: =IF(P74>1,"Invalid Discount","") | AH74: =IF(V74<0,"Invalid Shipping Record","") -> Invalid Shipping Record | AI74: =IF(ROUND(Q74,2)=ROUND(X74,2),"Match","Mismatch") -> Match | AJ74: =IF(ROUND(S74,2)=ROUND(Y74,2),"Match","Mismatch") -> Match | AK74: =PROPER(TRIM(raw_orders!G74)) -> South | AL74: =PROPER(TRIM(raw_orders!M74)) -> First Class
A75: ORD-2025-10074 | B75: 45745 | C75: 45750 | D75: CUST-2342 | E75: =PROPER(TRIM(raw_orders!E75)) -> Sneha Kapoor | F75: =PROPER(TRIM(raw_orders!F75)) -> Corporate | G75: =PROPER(TRIM(raw_orders!G75)) -> East | H75: =PROPER(TRIM(raw_orders!H75)) -> West Bengal | I75: =PROPER(TRIM(raw_orders!I75)) -> Kolkata | J75: =PROPER(TRIM(raw_orders!J75)) -> Furniture | K75: =PROPER(TRIM(raw_orders!K75)) -> Bookcases | L75: Smart Bookcases 167 | M75: =PROPER(TRIM(raw_orders!M75)) -> First Class | N75: 5 | O75: 1425.74 | P75: 0 | Q75: 7128.7 | R75: 4382.15 | S75: 2746.55 | T75: =PROPER(TRIM(raw_orders!T75)) -> Paid | U75: =PROPER(TRIM(raw_orders!U75)) -> Completed | V75: =C75-B75 -> 5 | W75: =IF(AND(P75="",Q75<>"",N75<>"",S75<>""),0,IF(OR(P75<0,P75>1),P75,P75)) -> 0 | X75: =N75*O75*(1-P75) -> 7128.7 | Y75: =X75-R75 -> 2746.55 | Z75: =Y75/X75 -> 0.38528063 | AA75: =TEXT(B75,"MMMM") -> March | AB75: =YEAR(B75) -> 2025 | AC75: =IF(OR(AF75 = "Invalid Discount",AG75="Invalid Discount",AH75="Invalid Shipping Record",AE75="Review Required"),"Invalid",IF(OR(G75="Unknown",M75="Unknown",ISBLANK(P75)),"Warning","Clean")) -> Clean | AD75: =A75&B75&C75&D75&E75&F75&G75&H75&I75&J75&K75&L75&M75&N75&O75&P75&Q75&R75&S75&T75&U75&V75 -> ORD-2025-100744574545750CUST-2342Sneha KapoorCorporateEastWest BengalKolkataFurnitureBookcasesSmart Bookcases 167First Class51425.7407128.74382.152746.55PaidCompleted5 | AE75: =IF(COUNTIF($A$2:$A$933,A75)=1,"OK",IF(COUNTIF($AD$2:$AD$933,AD75)>1,"Exact Duplicate", "Review Required")) -> OK | AF75: =IF(P75<0,"Invalid Discount","") | AG75: =IF(P75>1,"Invalid Discount","") | AH75: =IF(V75<1,"Invalid Shipping Record","") | AI75: =IF(ROUND(Q75,2)=ROUND(X75,2),"Match","Mismatch") -> Match | AJ75: =IF(ROUND(S75,2)=ROUND(Y75,2),"Match","Mismatch") -> Match | AK75: =PROPER(TRIM(raw_orders!G75)) -> East | AL75: =PROPER(TRIM(raw_orders!M75)) -> First Class
A76: ORD-2025-10075 | B76: 45715 | C76: 45717 | D76: CUST-6201 | E76: =PROPER(TRIM(raw_orders!E76)) -> Vikram Iyer | F76: =PROPER(TRIM(raw_orders!F76)) -> Small Business | G76: =PROPER(TRIM(raw_orders!G76)) -> East | H76: =PROPER(TRIM(raw_orders!H76)) -> West Bengal | I76: =PROPER(TRIM(raw_orders!I76)) -> Kolkata | J76: =PROPER(TRIM(raw_orders!J76)) -> Furniture | K76: =PROPER(TRIM(raw_orders!K76)) -> Chairs | L76: Max Chairs 244 | M76: =PROPER(TRIM(raw_orders!M76)) -> Standard Class | N76: 6 | O76: 551.64 | P76: 0 | Q76: 3309.84 | R76: 2671.08 | S76: 638.76 | T76: =PROPER(TRIM(raw_orders!T76)) -> Paid | U76: =PROPER(TRIM(raw_orders!U76)) -> Completed | V76: =C76-B76 -> 2 | W76: =IF(AND(P76="",Q76<>"",N76<>"",S76<>""),0,IF(OR(P76<0,P76>1),P76,P76)) -> 0 | X76: =N76*O76*(1-P76) -> 3309.84 | Y76: =X76-R76 -> 638.76 | Z76: =Y76/X76 -> 0.19298818 | AA76: =TEXT(B76,"MMMM") -> February | AB76: =YEAR(B76) -> 2025 | AC76: =IF(OR(AF76 = "Invalid Discount",AG76="Invalid Discount",AH76="Invalid Shipping Record",AE76="Review Required"),"Invalid",IF(OR(G76="Unknown",M76="Unknown",ISBLANK(P76)),"Warning","Clean")) -> Clean | AD76: =A76&B76&C76&D76&E76&F76&G76&H76&I76&J76&K76&L76&M76&N76&O76&P76&Q76&R76&S76&T76&U76&V76 -> ORD-2025-100754571545717CUST-6201Vikram IyerSmall BusinessEastWest BengalKolkataFurnitureChairsMax Chairs 244Standard Class6551.6403309.842671.08638.76PaidCompleted2 | AE76: =IF(COUNTIF($A$2:$A$933,A76)=1,"OK",IF(COUNTIF($AD$2:$AD$933,AD76)>1,"Exact Duplicate", "Review Required")) -> OK | AF76: =IF(P76<0,"Invalid Discount","") | AG76: =IF(P76>1,"Invalid Discount","") | AH76: =IF(V76<1,"Invalid Shipping Record","") | AI76: =IF(ROUND(Q76,2)=ROUND(X76,2),"Match","Mismatch") -> Match | AJ76: =IF(ROUND(S76,2)=ROUND(Y76,2),"Match","Mismatch") -> Match | AK76: =PROPER(TRIM(raw_orders!G76)) -> East | AL76: =PROPER(TRIM(raw_orders!M76)) -> Standard Class
A77: ORD-2025-10076 | B77: 45891 | C77: 45896 | D77: CUST-5808 | E77: =PROPER(TRIM(raw_orders!E77)) -> Priya Menon | F77: =PROPER(TRIM(raw_orders!F77)) -> Small Business | G77: =PROPER(TRIM(raw_orders!G77)) -> East | H77: =PROPER(TRIM(raw_orders!H77)) -> Odisha | I77: =PROPER(TRIM(raw_orders!I77)) -> Bhubaneswar | J77: =PROPER(TRIM(raw_orders!J77)) -> Office Supplies | K77: =PROPER(TRIM(raw_orders!K77)) -> Labels | L77: Eco Labels 653 | M77: =PROPER(TRIM(raw_orders!M77)) -> First Class | N77: 3 | O77: 3294.82 | P77: 0.2 | Q77: 7907.57 | R77: 5391.18 | S77: 2516.39 | T77: =PROPER(TRIM(raw_orders!T77)) -> Paid | U77: =PROPER(TRIM(raw_orders!U77)) -> Completed | V77: =C77-B77 -> 5 | W77: =IF(AND(P77="",Q77<>"",N77<>"",S77<>""),0,IF(OR(P77<0,P77>1),P77,P77)) -> 0.2 | X77: =N77*O77*(1-P77) -> 7907.568 | Y77: =X77-R77 -> 2516.388 | Z77: =Y77/X77 -> 0.31822527 | AA77: =TEXT(B77,"MMMM") -> August | AB77: =YEAR(B77) -> 2025 | AC77: =IF(OR(AF77 = "Invalid Discount",AG77="Invalid Discount",AH77="Invalid Shipping Record",AE77="Review Required"),"Invalid",IF(OR(G77="Unknown",M77="Unknown",ISBLANK(P77)),"Warning","Clean")) -> Clean | AD77: =A77&B77&C77&D77&E77&F77&G77&H77&I77&J77&K77&L77&M77&N77&O77&P77&Q77&R77&S77&T77&U77&V77 -> ORD-2025-100764589145896CUST-5808Priya MenonSmall BusinessEastOdishaBhubaneswarOffice SuppliesLabelsEco Labels 653First Class33294.820.27907.575391.182516.39PaidCompleted5 | AE77: =IF(COUNTIF($A$2:$A$933,A77)=1,"OK",IF(COUNTIF($AD$2:$AD$933,AD77)>1,"Exact Duplicate", "Review Required")) -> OK | AF77: =IF(P77<0,"Invalid Discount","") | AG77: =IF(P77>1,"Invalid Discount","") | AH77: =IF(V77<1,"Invalid Shipping Record","") | AI77: =IF(ROUND(Q77,2)=ROUND(X77,2),"Match","Mismatch") -> Match | AJ77: =IF(ROUND(S77,2)=ROUND(Y77,2),"Match","Mismatch") -> Match | AK77: =PROPER(TRIM(raw_orders!G77)) -> East | AL77: =PROPER(TRIM(raw_orders!M77)) -> First Class
A78: ORD-2024-10077 | B78: 45599 | C78: 45607 | D78: CUST-2642 | E78: =PROPER(TRIM(raw_orders!E78)) -> Ananya Rao | F78: =PROPER(TRIM(raw_orders!F78)) -> Corporate | G78: =PROPER(TRIM(raw_orders!G78)) -> East | H78: =PROPER(TRIM(raw_orders!H78)) -> Jharkhand | I78: =PROPER(TRIM(raw_orders!I78)) -> Ranchi | J78: =PROPER(TRIM(raw_orders!J78)) -> Office Supplies | K78: =PROPER(TRIM(raw_orders!K78)) -> Labels | L78: Max Labels 617 | M78: =PROPER(TRIM(raw_orders!M78)) -> Second Class | N78: 3 | O78: 3406.27 | P78: 0 | Q78: 10218.81 | R78: 7616.97 | S78: 2601.84 | T78: =PROPER(TRIM(raw_orders!T78)) -> Paid | U78: =PROPER(TRIM(raw_orders!U78)) -> Completed | V78: =C78-B78 -> 8 | W78: =IF(AND(P78="",Q78<>"",N78<>"",S78<>""),0,IF(OR(P78<0,P78>1),P78,P78)) -> 0 | X78: =N78*O78*(1-P78) -> 10218.81 | Y78: =X78-R78 -> 2601.84 | Z78: =Y78/X78 -> 0.25461282 | AA78: =TEXT(B78,"MMMM") -> November | AB78: =YEAR(B78) -> 2024 | AC78: =IF(OR(AF78 = "Invalid Discount",AG78="Invalid Discount",AH78="Invalid Shipping Record",AE78="Review Required"),"Invalid",IF(OR(G78="Unknown",M78="Unknown",ISBLANK(P78)),"Warning","Clean")) -> Clean | AD78: =A78&B78&C78&D78&E78&F78&G78&H78&I78&J78&K78&L78&M78&N78&O78&P78&Q78&R78&S78&T78&U78&V78 -> ORD-2024-100774559945607CUST-2642Ananya RaoCorporateEastJharkhandRanchiOffice SuppliesLabelsMax Labels 617Second Class33406.27010218.817616.972601.84PaidCompleted8 | AE78: =IF(COUNTIF($A$2:$A$933,A78)=1,"OK",IF(COUNTIF($AD$2:$AD$933,AD78)>1,"Exact Duplicate", "Review Required")) -> OK | AF78: =IF(P78<0,"Invalid Discount","") | AG78: =IF(P78>1,"Invalid Discount","") | AH78: =IF(V78<1,"Invalid Shipping Record","") | AI78: =IF(ROUND(Q78,2)=ROUND(X78,2),"Match","Mismatch") -> Match | AJ78: =IF(ROUND(S78,2)=ROUND(Y78,2),"Match","Mismatch") -> Match | AK78: =PROPER(TRIM(raw_orders!G78)) -> East | AL78: =PROPER(TRIM(raw_orders!M78)) -> Second Class
A79: ORD-2025-10078 | B79: 45846 | C79: 45998 | D79: CUST-4385 | E79: =PROPER(TRIM(raw_orders!E79)) -> Rohan Mehta | F79: =PROPER(TRIM(raw_orders!F79)) -> Home Office | G79: =PROPER(TRIM(raw_orders!G79)) -> North | H79: =PROPER(TRIM(raw_orders!H79)) -> Uttar Pradesh | I79: =PROPER(TRIM(raw_orders!I79)) -> Noida | J79: =PROPER(TRIM(raw_orders!J79)) -> Furniture | K79: =PROPER(TRIM(raw_orders!K79)) -> Furnishings | L79: Pro Furnishings 529 | M79: =PROPER(TRIM(raw_orders!M79)) -> Standard Class | N79: 1 | O79: 2582.2 | P79: 0.15 | Q79: 2194.87 | R79: 1223.17 | S79: 971.7 | T79: =PROPER(TRIM(raw_orders!T79)) -> Refunded | U79: =PROPER(TRIM(raw_orders!U79)) -> Cancelled | V79: =C79-B79 -> 152 | W79: =IF(AND(P79="",Q79<>"",N79<>"",S79<>""),0,IF(OR(P79<0,P79>1),P79,P79)) -> 0.15 | X79: =N79*O79*(1-P79) -> 2194.87 | Y79: =X79-R79 -> 971.7 | Z79: =Y79/X79 -> 0.44271415 | AA79: =TEXT(B79,"MMMM") -> July | AB79: =YEAR(B79) -> 2025 | AC79: =IF(OR(AF79 = "Invalid Discount",AG79="Invalid Discount",AH79="Invalid Shipping Record",AE79="Review Required"),"Invalid",IF(OR(G79="Unknown",M79="Unknown",ISBLANK(P79)),"Warning","Clean")) -> Clean | AD79: =A79&B79&C79&D79&E79&F79&G79&H79&I79&J79&K79&L79&M79&N79&O79&P79&Q79&R79&S79&T79&U79&V79 -> ORD-2025-100784584645998CUST-4385Rohan MehtaHome OfficeNorthUttar PradeshNoidaFurnitureFurnishingsPro Furnishings 529Standard Class12582.20.152194.871223.17971.7RefundedCancelled152 | AE79: =IF(COUNTIF($A$2:$A$933,A79)=1,"OK",IF(COUNTIF($AD$2:$AD$933,AD79)>1,"Exact Duplicate", "Review Required")) -> OK | AF79: =IF(P79<0,"Invalid Discount","") | AG79: =IF(P79>1,"Invalid Discount","") | AH79: =IF(V79<1,"Invalid Shipping Record","") | AI79: =IF(ROUND(Q79,2)=ROUND(X79,2),"Match","Mismatch") -> Match | AJ79: =IF(ROUND(S79,2)=ROUND(Y79,2),"Match","Mismatch") -> Match | AK79: =PROPER(TRIM(raw_orders!G79)) -> North | AL79: =PROPER(TRIM(raw_orders!M79)) -> Standard Class
A80: ORD-2025-10079 | B80: 45854 | C80: 45859 | D80: CUST-8043 | E80: =PROPER(TRIM(raw_orders!E80)) -> Sneha Kapoor | F80: =PROPER(TRIM(raw_orders!F80)) -> Corporate | G80: =PROPER(TRIM(raw_orders!G80)) -> East | H80: =PROPER(TRIM(raw_orders!H80)) -> West Bengal | I80: =PROPER(TRIM(raw_orders!I80)) -> Kolkata | J80: =PROPER(TRIM(raw_orders!J80)) -> Furniture | K80: =PROPER(TRIM(raw_orders!K80)) -> Tables | L80: Smart Tables 561 | M80: =PROPER(TRIM(raw_orders!M80)) -> First Class | N80: 5 | O80: 2129.51 | P80: 0.15 | Q80: 9050.42 | R80: 6778.85 | S80: 2271.57 | T80: =PROPER(TRIM(raw_orders!T80)) -> Paid | U80: =PROPER(TRIM(raw_orders!U80)) -> Completed | V80: =C80-B80 -> 5 | W80: =IF(AND(P80="",Q80<>"",N80<>"",S80<>""),0,IF(OR(P80<0,P80>1),P80,P80)) -> 0.15 | X80: =N80*O80*(1-P80) -> 9050.4175 | Y80: =X80-R80 -> 2271.5675 | Z80: =Y80/X80 -> 0.25099035 | AA80: =TEXT(B80,"MMMM") -> July | AB80: =YEAR(B80) -> 2025 | AC80: =IF(OR(AF80 = "Invalid Discount",AG80="Invalid Discount",AH80="Invalid Shipping Record",AE80="Review Required"),"Invalid",IF(OR(G80="Unknown",M80="Unknown",ISBLANK(P80)),"Warning","Clean")) -> Clean | AD80: =A80&B80&C80&D80&E80&F80&G80&H80&I80&J80&K80&L80&M80&N80&O80&P80&Q80&R80&S80&T80&U80&V80 -> ORD-2025-100794585445859CUST-8043Sneha KapoorCorporateEastWest BengalKolkataFurnitureTablesSmart Tables 561First Class52129.510.159050.426778.852271.57PaidCompleted5 | AE80: =IF(COUNTIF($A$2:$A$933,A80)=1,"OK",IF(COUNTIF($AD$2:$AD$933,AD80)>1,"Exact Duplicate", "Review Required")) -> OK | AF80: =IF(P80<0,"Invalid Discount","") | AG80: =IF(P80>1,"Invalid Discount","") | AH80: =IF(V80<1,"Invalid Shipping Record","") | AI80: =IF(ROUND(Q80,2)=ROUND(X80,2),"Match","Mismatch") -> Match | AJ80: =IF(ROUND(S80,2)=ROUND(Y80,2),"Match","Mismatch") -> Match | AK80: =PROPER(TRIM(raw_orders!G80)) -> East | AL80: =PROPER(TRIM(raw_orders!M80)) -> First Class
A81: ORD-2025-10080 | B81: 45927 | C81: 45933 | D81: CUST-9978 | E81: =PROPER(TRIM(raw_orders!E81)) -> Diya Patel | F81: =PROPER(TRIM(raw_orders!F81)) -> Home Office | G81: =PROPER(TRIM(raw_orders!G81)) -> South | H81: =PROPER(TRIM(raw_orders!H81)) -> Tamil Nadu | I81: =PROPER(TRIM(raw_orders!I81)) -> Chennai | J81: =PROPER(TRIM(raw_orders!J81)) -> Furniture | K81: =PROPER(TRIM(raw_orders!K81)) -> Chairs | L81: Prime Chairs 838 | M81: =PROPER(TRIM(raw_orders!M81)) -> Same Day | N81: 9 | O81: 4131.52 | P81: 0.1 | Q81: 33465.31 | R81: 24781.26 | S81: 8684.05 | T81: =PROPER(TRIM(raw_orders!T81)) -> Paid | U81: =PROPER(TRIM(raw_orders!U81)) -> Completed | V81: =C81-B81 -> 6 | W81: =IF(AND(P81="",Q81<>"",N81<>"",S81<>""),0,IF(OR(P81<0,P81>1),P81,P81)) -> 0.1 | X81: =N81*O81*(1-P81) -> 33465.312 | Y81: =X81-R81 -> 8684.052 | Z81: =Y81/X81 -> 0.25949413 | AA81: =TEXT(B81,"MMMM") -> September | AB81: =YEAR(B81) -> 2025 | AC81: =IF(OR(AF81 = "Invalid Discount",AG81="Invalid Discount",AH81="Invalid Shipping Record",AE81="Review Required"),"Invalid",IF(OR(G81="Unknown",M81="Unknown",ISBLANK(P81)),"Warning","Clean")) -> Clean | AD81: =A81&B81&C81&D81&E81&F81&G81&H81&I81&J81&K81&L81&M81&N81&O81&P81&Q81&R81&S81&T81&U81&V81 -> ORD-2025-100804592745933CUST-9978Diya PatelHome OfficeSouthTamil NaduChennaiFurnitureChairsPrime Chairs 838Same Day94131.520.133465.3124781.268684.05PaidCompleted6 | AE81: =IF(COUNTIF($A$2:$A$933,A81)=1,"OK",IF(COUNTIF($AD$2:$AD$933,AD81)>1,"Exact Duplicate", "Review Required")) -> OK | AF81: =IF(P81<0,"Invalid Discount","") | AG81: =IF(P81>1,"Invalid Discount","") | AH81: =IF(V81<1,"Invalid Shipping Record","") | AI81: =IF(ROUND(Q81,2)=ROUND(X81,2),"Match","Mismatch") -> Match | AJ81: =IF(ROUND(S81,2)=ROUND(Y81,2),"Match","Mismatch") -> Match | AK81: =PROPER(TRIM(raw_orders!G81)) -> South | AL81: =PROPER(TRIM(raw_orders!M81)) -> Same Day
A82: ORD-2024-10081 | B82: 45514 | C82: 45518 | D82: CUST-2094 | E82: =PROPER(TRIM(raw_orders!E82)) -> Aarav Sharma | F82: =PROPER(TRIM(raw_orders!F82)) -> Small Business | G82: =PROPER(TRIM(raw_orders!G82)) -> North | H82: =PROPER(TRIM(raw_orders!H82)) -> Delhi | I82: =PROPER(TRIM(raw_orders!I82)) -> New Delhi | J82: =PROPER(TRIM(raw_orders!J82)) -> Office Supplies | K82: =PROPER(TRIM(raw_orders!K82)) -> Storage | L82: Elite Storage 371 | M82: =PROPER(TRIM(raw_orders!M82)) -> Second Class | N82: 4 | O82: 1182.32 | P82: 0.1 | Q82: 4256.35 | R82: 2495.33 | S82: 1761.02 | T82: =PROPER(TRIM(raw_orders!T82)) -> Pending | U82: =PROPER(TRIM(raw_orders!U82)) -> Returned | V82: =C82-B82 -> 4 | W82: =IF(AND(P82="",Q82<>"",N82<>"",S82<>""),0,IF(OR(P82<0,P82>1),P82,P82)) -> 0.1 | X82: =N82*O82*(1-P82) -> 4256.352 | Y82: =X82-R82 -> 1761.022 | Z82: =Y82/X82 -> 0.41373975 | AA82: =TEXT(B82,"MMMM") -> August | AB82: =YEAR(B82) -> 2024 | AC82: =IF(OR(AF82 = "Invalid Discount",AG82="Invalid Discount",AH82="Invalid Shipping Record",AE82="Review Required"),"Invalid",IF(OR(G82="Unknown",M82="Unknown",ISBLANK(P82)),"Warning","Clean")) -> Clean | AD82: =A82&B82&C82&D82&E82&F82&G82&H82&I82&J82&K82&L82&M82&N82&O82&P82&Q82&R82&S82&T82&U82&V82 -> ORD-2024-100814551445518CUST-2094Aarav SharmaSmall BusinessNorthDelhiNew DelhiOffice SuppliesStorageElite Storage 371Second Class41182.320.14256.352495.331761.02PendingReturned4 | AE82: =IF(COUNTIF($A$2:$A$933,A82)=1,"OK",IF(COUNTIF($AD$2:$AD$933,AD82)>1,"Exact Duplicate", "Review Required")) -> OK | AF82: =IF(P82<0,"Invalid Discount","") | AG82: =IF(P82>1,"Invalid Discount","") | AH82: =IF(V82<1,"Invalid Shipping Record","") | AI82: =IF(ROUND(Q82,2)=ROUND(X82,2),"Match","Mismatch") -> Match | AJ82: =IF(ROUND(S82,2)=ROUND(Y82,2),"Match","Mismatch") -> Match | AK82: =PROPER(TRIM(raw_orders!G82)) -> North | AL82: =PROPER(TRIM(raw_orders!M82)) -> Second Class
A83: ORD-2025-10082 | B83: 45732 | C83: 45733 | D83: CUST-7907 | E83: =PROPER(TRIM(raw_orders!E83)) -> Karan Malhotra | F83: =PROPER(TRIM(raw_orders!F83)) -> Home Office | G83: =PROPER(TRIM(raw_orders!G83)) -> West | H83: =PROPER(TRIM(raw_orders!H83)) -> Goa | I83: =PROPER(TRIM(raw_orders!I83)) -> Panaji | J83: =PROPER(TRIM(raw_orders!J83)) -> Office Supplies | K83: =PROPER(TRIM(raw_orders!K83)) -> Labels | L83: Eco Labels 662 | M83: =PROPER(TRIM(raw_orders!M83)) -> Same Day | N83: 3 | O83: 1841.91 | P83: 0 | Q83: 5525.73 | R83: 3093.42 | S83: 2432.31 | T83: =PROPER(TRIM(raw_orders!T83)) -> Paid | U83: =PROPER(TRIM(raw_orders!U83)) -> Completed | V83: =C83-B83 -> 1 | W83: =IF(AND(P83="",Q83<>"",N83<>"",S83<>""),0,IF(OR(P83<0,P83>1),P83,P83)) -> 0 | X83: =N83*O83*(1-P83) -> 5525.73 | Y83: =X83-R83 -> 2432.31 | Z83: =Y83/X83 -> 0.44017894 | AA83: =TEXT(B83,"MMMM") -> March | AB83: =YEAR(B83) -> 2025 | AC83: =IF(OR(AF83 = "Invalid Discount",AG83="Invalid Discount",AH83="Invalid Shipping Record",AE83="Review Required"),"Invalid",IF(OR(G83="Unknown",M83="Unknown",ISBLANK(P83)),"Warning","Clean")) -> Clean | AD83: =A83&B83&C83&D83&E83&F83&G83&H83&I83&J83&K83&L83&M83&N83&O83&P83&Q83&R83&S83&T83&U83&V83 -> ORD-2025-100824573245733CUST-7907Karan MalhotraHome OfficeWestGoaPanajiOffice SuppliesLabelsEco Labels 662Same Day31841.9105525.733093.422432.31PaidCompleted1 | AE83: =IF(COUNTIF($A$2:$A$933,A83)=1,"OK",IF(COUNTIF($AD$2:$AD$933,AD83)>1,"Exact Duplicate", "Review Required")) -> OK | AF83: =IF(P83<0,"Invalid Discount","") | AG83: =IF(P83>1,"Invalid Discount","") | AH83: =IF(V83<1,"Invalid Shipping Record","") | AI83: =IF(ROUND(Q83,2)=ROUND(X83,2),"Match","Mismatch") -> Match | AJ83: =IF(ROUND(S83,2)=ROUND(Y83,2),"Match","Mismatch") -> Match | AK83: =PROPER(TRIM(raw_orders!G83)) -> West | AL83: =PROPER(TRIM(raw_orders!M83)) -> Same Day
A84: ORD-2024-10083 | B84: 45507 | C84: 45390 | D84: CUST-6516 | E84: =PROPER(TRIM(raw_orders!E84)) -> Arjun Bose | F84: =PROPER(TRIM(raw_orders!F84)) -> Consumer | G84: =PROPER(TRIM(raw_orders!G84)) -> North | H84: =PROPER(TRIM(raw_orders!H84)) -> Uttar Pradesh | I84: =PROPER(TRIM(raw_orders!I84)) -> Noida | J84: =PROPER(TRIM(raw_orders!J84)) -> Technology | K84: =PROPER(TRIM(raw_orders!K84)) -> Copiers | L84: Smart Copiers 702 | M84: =PROPER(TRIM(raw_orders!M84)) -> Second Class | N84: 6 | O84: 1001.73 | P84: 0 | Q84: 6010.38 | R84: 3762.85 | S84: 2247.53 | T84: =PROPER(TRIM(raw_orders!T84)) -> Failed | U84: =PROPER(TRIM(raw_orders!U84)) -> Returned | V84: =C84-B84 -> -117 | W84: =IF(AND(P84="",Q84<>"",N84<>"",S84<>""),0,IF(OR(P84<0,P84>1),P84,P84)) -> 0 | X84: =N84*O84*(1-P84) -> 6010.38 | Y84: =X84-R84 -> 2247.53 | Z84: =Y84/X84 -> 0.37394141 | AA84: =TEXT(B84,"MMMM") -> August | AB84: =YEAR(B84) -> 2024 | AC84: =IF(OR(AF84 = "Invalid Discount",AG84="Invalid Discount",AH84="Invalid Shipping Record",AE84="Review Required"),"Invalid",IF(OR(G84="Unknown",M84="Unknown",ISBLANK(P84)),"Warning","Clean")) -> Invalid | AD84: =A84&B84&C84&D84&E84&F84&G84&H84&I84&J84&K84&L84&M84&N84&O84&P84&Q84&R84&S84&T84&U84&V84 -> ORD-2024-100834550745390CUST-6516Arjun BoseConsumerNorthUttar PradeshNoidaTechnologyCopiersSmart Copiers 702Second Class61001.7306010.383762.852247.53FailedReturned-117 | AE84: =IF(COUNTIF($A$2:$A$933,A84)=1,"OK",IF(COUNTIF($AD$2:$AD$933,AD84)>1,"Exact Duplicate", "Review Required")) -> OK | AF84: =IF(P84<0,"Invalid Discount","") | AG84: =IF(P84>1,"Invalid Discount","") | AH84: =IF(V84<0,"Invalid Shipping Record","") -> Invalid Shipping Record | AI84: =IF(ROUND(Q84,2)=ROUND(X84,2),"Match","Mismatch") -> Match | AJ84: =IF(ROUND(S84,2)=ROUND(Y84,2),"Match","Mismatch") -> Match | AK84: =PROPER(TRIM(raw_orders!G84)) -> North | AL84: =PROPER(TRIM(raw_orders!M84)) -> Second Class
A85: ORD-2024-10084 | B85: 45591 | C85: 45594 | D85: CUST-4989 | E85: =PROPER(TRIM(raw_orders!E85)) -> Aditi Sen | F85: =PROPER(TRIM(raw_orders!F85)) -> Home Office | G85: =PROPER(TRIM(raw_orders!G85)) -> West | H85: =PROPER(TRIM(raw_orders!H85)) -> Maharashtra | I85: =PROPER(TRIM(raw_orders!I85)) -> Mumbai | J85: =PROPER(TRIM(raw_orders!J85)) -> Furniture | K85: =PROPER(TRIM(raw_orders!K85)) -> Tables | L85: Elite Tables 362 | M85: =PROPER(TRIM(raw_orders!M85)) -> Second Class | N85: 9 | O85: 131.74 | P85: 0.2 | Q85: 948.53 | R85: 674.62 | S85: 273.91 | T85: =PROPER(TRIM(raw_orders!T85)) -> Paid | U85: =PROPER(TRIM(raw_orders!U85)) -> Completed | V85: =C85-B85 -> 3 | W85: =IF(AND(P85="",Q85<>"",N85<>"",S85<>""),0,IF(OR(P85<0,P85>1),P85,P85)) -> 0.2 | X85: =N85*O85*(1-P85) -> 948.528 | Y85: =X85-R85 -> 273.908 | Z85: =Y85/X85 -> 0.28877165 | AA85: =TEXT(B85,"MMMM") -> October | AB85: =YEAR(B85) -> 2024 | AC85: =IF(OR(AF85 = "Invalid Discount",AG85="Invalid Discount",AH85="Invalid Shipping Record",AE85="Review Required"),"Invalid",IF(OR(G85="Unknown",M85="Unknown",ISBLANK(P85)),"Warning","Clean")) -> Clean | AD85: =A85&B85&C85&D85&E85&F85&G85&H85&I85&J85&K85&L85&M85&N85&O85&P85&Q85&R85&S85&T85&U85&V85 -> ORD-2024-100844559145594CUST-4989Aditi SenHome OfficeWestMaharashtraMumbaiFurnitureTablesElite Tables 362Second Class9131.740.2948.53674.62273.91PaidCompleted3 | AE85: =IF(COUNTIF($A$2:$A$933,A85)=1,"OK",IF(COUNTIF($AD$2:$AD$933,AD85)>1,"Exact Duplicate", "Review Required")) -> OK | AF85: =IF(P85<0,"Invalid Discount","") | AG85: =IF(P85>1,"Invalid Discount","") | AH85: =IF(V85<1,"Invalid Shipping Record","") | AI85: =IF(ROUND(Q85,2)=ROUND(X85,2),"Match","Mismatch") -> Match | AJ85: =IF(ROUND(S85,2)=ROUND(Y85,2),"Match","Mismatch") -> Match | AK85: =PROPER(TRIM(raw_orders!G85)) -> West | AL85: =PROPER(TRIM(raw_orders!M85)) -> Second Class
A86: ORD-2024-10085 | B86: 45566 | C86: 45568 | D86: CUST-3758 | E86: =PROPER(TRIM(raw_orders!E86)) -> Rohan Mehta | F86: =PROPER(TRIM(raw_orders!F86)) -> Corporate | G86: =PROPER(TRIM(raw_orders!G86)) -> South | H86: =PROPER(TRIM(raw_orders!H86)) -> Tamil Nadu | I86: =PROPER(TRIM(raw_orders!I86)) -> Chennai | J86: =PROPER(TRIM(raw_orders!J86)) -> Technology | K86: =PROPER(TRIM(raw_orders!K86)) -> Phones | L86: Elite Phones 781 | M86: =PROPER(TRIM(raw_orders!M86)) -> Second Class | N86: 6 | O86: 570.28 | P86: 0.2 | Q86: 2737.34 | R86: 2085.44 | S86: 651.9 | T86: =PROPER(TRIM(raw_orders!T86)) -> Paid | U86: =PROPER(TRIM(raw_orders!U86)) -> Completed | V86: =C86-B86 -> 2 | W86: =IF(AND(P86="",Q86<>"",N86<>"",S86<>""),0,IF(OR(P86<0,P86>1),P86,P86)) -> 0.2 | X86: =N86*O86*(1-P86) -> 2737.344 | Y86: =X86-R86 -> 651.904 | Z86: =Y86/X86 -> 0.23815202 | AA86: =TEXT(B86,"MMMM") -> October | AB86: =YEAR(B86) -> 2024 | AC86: =IF(OR(AF86 = "Invalid Discount",AG86="Invalid Discount",AH86="Invalid Shipping Record",AE86="Review Required"),"Invalid",IF(OR(G86="Unknown",M86="Unknown",ISBLANK(P86)),"Warning","Clean")) -> Clean | AD86: =A86&B86&C86&D86&E86&F86&G86&H86&I86&J86&K86&L86&M86&N86&O86&P86&Q86&R86&S86&T86&U86&V86 -> ORD-2024-100854556645568CUST-3758Rohan MehtaCorporateSouthTamil NaduChennaiTechnologyPhonesElite Phones 781Second Class6570.280.22737.342085.44651.9PaidCompleted2 | AE86: =IF(COUNTIF($A$2:$A$933,A86)=1,"OK",IF(COUNTIF($AD$2:$AD$933,AD86)>1,"Exact Duplicate", "Review Required")) -> OK | AF86: =IF(P86<0,"Invalid Discount","") | AG86: =IF(P86>1,"Invalid Discount","") | AH86: =IF(V86<1,"Invalid Shipping Record","") | AI86: =IF(ROUND(Q86,2)=ROUND(X86,2),"Match","Mismatch") -> Match | AJ86: =IF(ROUND(S86,2)=ROUND(Y86,2),"Match","Mismatch") -> Match | AK86: =PROPER(TRIM(raw_orders!G86)) -> South | AL86: =PROPER(TRIM(raw_orders!M86)) -> Second Class
A87: ORD-2024-10086 | B87: 45503 | C87: 45509 | D87: CUST-6702 | E87: =PROPER(TRIM(raw_orders!E87)) -> Kabir Singh | F87: =PROPER(TRIM(raw_orders!F87)) -> Corporate | G87: =PROPER(TRIM(raw_orders!G87)) -> North | H87: =PROPER(TRIM(raw_orders!H87)) -> Delhi | I87: =PROPER(TRIM(raw_orders!I87)) -> New Delhi | J87: =PROPER(TRIM(raw_orders!J87)) -> Office Supplies | K87: =PROPER(TRIM(raw_orders!K87)) -> Binders | L87: Eco Binders 456 | M87: =PROPER(TRIM(raw_orders!M87)) -> Standard Class | N87: 1 | O87: 608.64 | P87: 0 | Q87: 608.64 | R87: 343.99 | S87: 264.65 | T87: =PROPER(TRIM(raw_orders!T87)) -> Paid | U87: =PROPER(TRIM(raw_orders!U87)) -> Cancelled | V87: =C87-B87 -> 6 | W87: =IF(AND(P87="",Q87<>"",N87<>"",S87<>""),0,IF(OR(P87<0,P87>1),P87,P87)) -> 0 | X87: =N87*O87*(1-P87) -> 608.64 | Y87: =X87-R87 -> 264.65 | Z87: =Y87/X87 -> 0.4348219 | AA87: =TEXT(B87,"MMMM") -> July | AB87: =YEAR(B87) -> 2024 | AC87: =IF(OR(AF87 = "Invalid Discount",AG87="Invalid Discount",AH87="Invalid Shipping Record",AE87="Review Required"),"Invalid",IF(OR(G87="Unknown",M87="Unknown",ISBLANK(P87)),"Warning","Clean")) -> Clean | AD87: =A87&B87&C87&D87&E87&F87&G87&H87&I87&J87&K87&L87&M87&N87&O87&P87&Q87&R87&S87&T87&U87&V87 -> ORD-2024-100864550345509CUST-6702Kabir SinghCorporateNorthDelhiNew DelhiOffice SuppliesBindersEco Binders 456Standard Class1608.640608.64343.99264.65PaidCancelled6 | AE87: =IF(COUNTIF($A$2:$A$933,A87)=1,"OK",IF(COUNTIF($AD$2:$AD$933,AD87)>1,"Exact Duplicate", "Review Required")) -> OK | AF87: =IF(P87<0,"Invalid Discount","") | AG87: =IF(P87>1,"Invalid Discount","") | AH87: =IF(V87<1,"Invalid Shipping Record","") | AI87: =IF(ROUND(Q87,2)=ROUND(X87,2),"Match","Mismatch") -> Match | AJ87: =IF(ROUND(S87,2)=ROUND(Y87,2),"Match","Mismatch") -> Match | AK87: =PROPER(TRIM(raw_orders!G87)) -> North | AL87: =PROPER(TRIM(raw_orders!M87)) -> Standard Class
A88: ORD-2024-10087 | B88: 45474 | C88: 45474 | D88: CUST-9148 | E88: =PROPER(TRIM(raw_orders!E88)) -> Ananya Rao | F88: =PROPER(TRIM(raw_orders!F88)) -> Small Business | G88: =PROPER(TRIM(raw_orders!G88)) -> North | H88: =PROPER(TRIM(raw_orders!H88)) -> Delhi | I88: =PROPER(TRIM(raw_orders!I88)) -> New Delhi | J88: =PROPER(TRIM(raw_orders!J88)) -> Technology | K88: =PROPER(TRIM(raw_orders!K88)) -> Copiers | L88: Basic Copiers 525 | M88: =PROPER(TRIM(raw_orders!M88)) -> Second Class | N88: 3 | O88: 885.28 | P88: 0.1 | Q88: 2390.26 | R88: 1495.94 | S88: 894.32 | T88: =PROPER(TRIM(raw_orders!T88)) -> Refunded | U88: =PROPER(TRIM(raw_orders!U88)) -> Cancelled | V88: =C88-B88 -> 0 | W88: =IF(AND(P88="",Q88<>"",N88<>"",S88<>""),0,IF(OR(P88<0,P88>1),P88,P88)) -> 0.1 | X88: =N88*O88*(1-P88) -> 2390.256 | Y88: =X88-R88 -> 894.316 | Z88: =Y88/X88 -> 0.37415072 | AA88: =TEXT(B88,"MMMM") -> July | AB88: =YEAR(B88) -> 2024 | AC88: =IF(OR(AF88 = "Invalid Discount",AG88="Invalid Discount",AH88="Invalid Shipping Record",AE88="Review Required"),"Invalid",IF(OR(G88="Unknown",M88="Unknown",ISBLANK(P88)),"Warning","Clean")) -> Clean | AD88: =A88&B88&C88&D88&E88&F88&G88&H88&I88&J88&K88&L88&M88&N88&O88&P88&Q88&R88&S88&T88&U88&V88 -> ORD-2024-100874547445474CUST-9148Ananya RaoSmall BusinessNorthDelhiNew DelhiTechnologyCopiersBasic Copiers 525Second Class3885.280.12390.261495.94894.32RefundedCancelled0 | AE88: =IF(COUNTIF($A$2:$A$933,A88)=1,"OK",IF(COUNTIF($AD$2:$AD$933,AD88)>1,"Exact Duplicate", "Review Required")) -> OK | AF88: =IF(P88<0,"Invalid Discount","") | AG88: =IF(P88>1,"Invalid Discount","") | AH88: =IF(V88<0,"Invalid Shipping Record","") | AI88: =IF(ROUND(Q88,2)=ROUND(X88,2),"Match","Mismatch") -> Match | AJ88: =IF(ROUND(S88,2)=ROUND(Y88,2),"Match","Mismatch") -> Match | AK88: =PROPER(TRIM(raw_orders!G88)) -> North | AL88: =PROPER(TRIM(raw_orders!M88)) -> Second Class
A89: ORD-2024-10088 | B89: 45330 | C89: 45507 | D89: CUST-5829 | E89: =PROPER(TRIM(raw_orders!E89)) -> Vikram Iyer | F89: =PROPER(TRIM(raw_orders!F89)) -> Consumer | G89: =PROPER(TRIM(raw_orders!G89)) -> East | H89: =PROPER(TRIM(raw_orders!H89)) -> Assam | I89: =PROPER(TRIM(raw_orders!I89)) -> Guwahati | J89: =PROPER(TRIM(raw_orders!J89)) -> Office Supplies | K89: =PROPER(TRIM(raw_orders!K89)) -> Binders | L89: Eco Binders 258 | M89: =PROPER(TRIM(raw_orders!M89)) -> Standard Class | N89: 7 | O89: 3345.22 | P89: 0 | Q89: 23416.54 | R89: 15490.89 | S89: 7925.65 | T89: =PROPER(TRIM(raw_orders!T89)) -> Paid | U89: =PROPER(TRIM(raw_orders!U89)) -> Completed | V89: =C89-B89 -> 177 | W89: =IF(AND(P89="",Q89<>"",N89<>"",S89<>""),0,IF(OR(P89<0,P89>1),P89,P89)) -> 0 | X89: =N89*O89*(1-P89) -> 23416.54 | Y89: =X89-R89 -> 7925.65 | Z89: =Y89/X89 -> 0.33846375 | AA89: =TEXT(B89,"MMMM") -> February | AB89: =YEAR(B89) -> 2024 | AC89: =IF(OR(AF89 = "Invalid Discount",AG89="Invalid Discount",AH89="Invalid Shipping Record",AE89="Review Required"),"Invalid",IF(OR(G89="Unknown",M89="Unknown",ISBLANK(P89)),"Warning","Clean")) -> Clean | AD89: =A89&B89&C89&D89&E89&F89&G89&H89&I89&J89&K89&L89&M89&N89&O89&P89&Q89&R89&S89&T89&U89&V89 -> ORD-2024-100884533045507CUST-5829Vikram IyerConsumerEastAssamGuwahatiOffice SuppliesBindersEco Binders 258Standard Class73345.22023416.5415490.897925.65PaidCompleted177 | AE89: =IF(COUNTIF($A$2:$A$933,A89)=1,"OK",IF(COUNTIF($AD$2:$AD$933,AD89)>1,"Exact Duplicate", "Review Required")) -> OK | AF89: =IF(P89<0,"Invalid Discount","") | AG89: =IF(P89>1,"Invalid Discount","") | AH89: =IF(V89<1,"Invalid Shipping Record","") | AI89: =IF(ROUND(Q89,2)=ROUND(X89,2),"Match","Mismatch") -> Match | AJ89: =IF(ROUND(S89,2)=ROUND(Y89,2),"Match","Mismatch") -> Match | AK89: =PROPER(TRIM(raw_orders!G89)) -> East | AL89: =PROPER(TRIM(raw_orders!M89)) -> Standard Class
A90: ORD-2024-10089 | B90: 45375 | C90: 45378 | D90: CUST-6059 | E90: =PROPER(TRIM(raw_orders!E90)) -> Rohan Mehta | F90: =PROPER(TRIM(raw_orders!F90)) -> Small Business | G90: =PROPER(TRIM(raw_orders!G90)) -> West | H90: =PROPER(TRIM(raw_orders!H90)) -> Maharashtra | I90: =PROPER(TRIM(raw_orders!I90)) -> Mumbai | J90: =PROPER(TRIM(raw_orders!J90)) -> Furniture | K90: =PROPER(TRIM(raw_orders!K90)) -> Bookcases | L90: Max Bookcases 398 | M90: =PROPER(TRIM(raw_orders!M90)) -> Standard Class | N90: 2 | O90: 3284.75 | P90: 0.05 | Q90: 6241.02 | R90: 5345.88 | S90: 895.14 | T90: =PROPER(TRIM(raw_orders!T90)) -> Paid | U90: =PROPER(TRIM(raw_orders!U90)) -> Completed | V90: =C90-B90 -> 3 | W90: =IF(AND(P90="",Q90<>"",N90<>"",S90<>""),0,IF(OR(P90<0,P90>1),P90,P90)) -> 0.05 | X90: =N90*O90*(1-P90) -> 6241.025 | Y90: =X90-R90 -> 895.145 | Z90: =Y90/X90 -> 0.14342916 | AA90: =TEXT(B90,"MMMM") -> March | AB90: =YEAR(B90) -> 2024 | AC90: =IF(OR(AF90 = "Invalid Discount",AG90="Invalid Discount",AH90="Invalid Shipping Record",AE90="Review Required"),"Invalid",IF(OR(G90="Unknown",M90="Unknown",ISBLANK(P90)),"Warning","Clean")) -> Clean | AD90: =A90&B90&C90&D90&E90&F90&G90&H90&I90&J90&K90&L90&M90&N90&O90&P90&Q90&R90&S90&T90&U90&V90 -> ORD-2024-100894537545378CUST-6059Rohan MehtaSmall BusinessWestMaharashtraMumbaiFurnitureBookcasesMax Bookcases 398Standard Class23284.750.056241.025345.88895.14PaidCompleted3 | AE90: =IF(COUNTIF($A$2:$A$933,A90)=1,"OK",IF(COUNTIF($AD$2:$AD$933,AD90)>1,"Exact Duplicate", "Review Required")) -> OK | AF90: =IF(P90<0,"Invalid Discount","") | AG90: =IF(P90>1,"Invalid Discount","") | AH90: =IF(V90<1,"Invalid Shipping Record","") | AI90: =IF(ROUND(Q90,2)=ROUND(X90,2),"Match","Mismatch") -> Mismatch | AJ90: =IF(ROUND(S90,2)=ROUND(Y90,2),"Match","Mismatch") -> Mismatch | AK90: =PROPER(TRIM(raw_orders!G90)) -> West | AL90: =PROPER(TRIM(raw_orders!M90)) -> Standard Class
A91: ORD-2024-10090 | B91: 45540 | C91: 45540 | D91: CUST-7744 | E91: =PROPER(TRIM(raw_orders!E91)) -> Kabir Singh | F91: =PROPER(TRIM(raw_orders!F91)) -> Consumer | G91: =PROPER(TRIM(raw_orders!G91)) -> South | H91: =PROPER(TRIM(raw_orders!H91)) -> Andhra Pradesh | I91: =PROPER(TRIM(raw_orders!I91)) -> Vijayawada | J91: =PROPER(TRIM(raw_orders!J91)) -> Furniture | K91: =PROPER(TRIM(raw_orders!K91)) -> Bookcases | L91: Smart Bookcases 857 | M91: =PROPER(TRIM(raw_orders!M91)) -> Standard Class | N91: 7 | O91: 3761.09 | P91: 0.2 | Q91: 21062.1 | R91: 12057.13 | S91: 9004.97 | T91: =PROPER(TRIM(raw_orders!T91)) -> Pending | U91: =PROPER(TRIM(raw_orders!U91)) -> Cancelled | V91: =C91-B91 -> 0 | W91: =IF(AND(P91="",Q91<>"",N91<>"",S91<>""),0,IF(OR(P91<0,P91>1),P91,P91)) -> 0.2 | X91: =N91*O91*(1-P91) -> 21062.104 | Y91: =X91-R91 -> 9004.974 | Z91: =Y91/X91 -> 0.4275439 | AA91: =TEXT(B91,"MMMM") -> September | AB91: =YEAR(B91) -> 2024 | AC91: =IF(OR(AF91 = "Invalid Discount",AG91="Invalid Discount",AH91="Invalid Shipping Record",AE91="Review Required"),"Invalid",IF(OR(G91="Unknown",M91="Unknown",ISBLANK(P91)),"Warning","Clean")) -> Clean | AD91: =A91&B91&C91&D91&E91&F91&G91&H91&I91&J91&K91&L91&M91&N91&O91&P91&Q91&R91&S91&T91&U91&V91 -> ORD-2024-100904554045540CUST-7744Kabir SinghConsumerSouthAndhra PradeshVijayawadaFurnitureBookcasesSmart Bookcases 857Standard Class73761.090.221062.112057.139004.97PendingCancelled0 | AE91: =IF(COUNTIF($A$2:$A$933,A91)=1,"OK",IF(COUNTIF($AD$2:$AD$933,AD91)>1,"Exact Duplicate", "Review Required")) -> OK | AF91: =IF(P91<0,"Invalid Discount","") | AG91: =IF(P91>1,"Invalid Discount","") | AH91: =IF(V91<0,"Invalid Shipping Record","") | AI91: =IF(ROUND(Q91,2)=ROUND(X91,2),"Match","Mismatch") -> Match | AJ91: =IF(ROUND(S91,2)=ROUND(Y91,2),"Match","Mismatch") -> Match | AK91: =PROPER(TRIM(raw_orders!G91)) -> South | AL91: =PROPER(TRIM(raw_orders!M91)) -> Standard Class
A92: ORD-2025-10091 | B92: 45893 | C92: 45898 | D92: CUST-5909 | E92: =PROPER(TRIM(raw_orders!E92)) -> Aarav Sharma | F92: =PROPER(TRIM(raw_orders!F92)) -> Small Business | G92: =PROPER(TRIM(raw_orders!G92)) -> East | H92: =PROPER(TRIM(raw_orders!H92)) -> Bihar | I92: =PROPER(TRIM(raw_orders!I92)) -> Patna | J92: =PROPER(TRIM(raw_orders!J92)) -> Technology | K92: =PROPER(TRIM(raw_orders!K92)) -> Copiers | L92: Smart Copiers 556 | M92: =PROPER(TRIM(raw_orders!M92)) -> First Class | N92: 3 | O92: 3703.96 | P92: 0.15 | Q92: 9445.1 | R92: 5586.28 | S92: 3858.82 | T92: =PROPER(TRIM(raw_orders!T92)) -> Paid | U92: =PROPER(TRIM(raw_orders!U92)) -> Completed | V92: =C92-B92 -> 5 | W92: =IF(AND(P92="",Q92<>"",N92<>"",S92<>""),0,IF(OR(P92<0,P92>1),P92,P92)) -> 0.15 | X92: =N92*O92*(1-P92) -> 9445.098 | Y92: =X92-R92 -> 3858.818 | Z92: =Y92/X92 -> 0.40855246 | AA92: =TEXT(B92,"MMMM") -> August | AB92: =YEAR(B92) -> 2025 | AC92: =IF(OR(AF92 = "Invalid Discount",AG92="Invalid Discount",AH92="Invalid Shipping Record",AE92="Review Required"),"Invalid",IF(OR(G92="Unknown",M92="Unknown",ISBLANK(P92)),"Warning","Clean")) -> Invalid | AD92: =A92&B92&C92&D92&E92&F92&G92&H92&I92&J92&K92&L92&M92&N92&O92&P92&Q92&R92&S92&T92&U92&V92 -> ORD-2025-100914589345898CUST-5909Aarav SharmaSmall BusinessEastBiharPatnaTechnologyCopiersSmart Copiers 556First Class33703.960.159445.15586.283858.82PaidCompleted5 | AE92: =IF(COUNTIF($A$2:$A$933,A92)=1,"OK",IF(COUNTIF($AD$2:$AD$933,AD92)>1,"Exact Duplicate", "Review Required")) -> Review Required | AF92: =IF(P92<0,"Invalid Discount","") | AG92: =IF(P92>1,"Invalid Discount","") | AH92: =IF(V92<1,"Invalid Shipping Record","") | AI92: =IF(ROUND(Q92,2)=ROUND(X92,2),"Match","Mismatch") -> Match | AJ92: =IF(ROUND(S92,2)=ROUND(Y92,2),"Match","Mismatch") -> Match | AK92: =PROPER(TRIM(raw_orders!G92)) -> East | AL92: =PROPER(TRIM(raw_orders!M92)) -> First Class
A93: ORD-2025-10092 | B93: 45691 | C93: 45724 | D93: CUST-6409 | E93: =PROPER(TRIM(raw_orders!E93)) -> Sneha Kapoor | F93: =PROPER(TRIM(raw_orders!F93)) -> Corporate | G93: =PROPER(TRIM(raw_orders!G93)) -> West | H93: =PROPER(TRIM(raw_orders!H93)) -> Madhya Pradesh | I93: =PROPER(TRIM(raw_orders!I93)) -> Indore | J93: =PROPER(TRIM(raw_orders!J93)) -> Technology | K93: =PROPER(TRIM(raw_orders!K93)) -> Copiers | L93: Prime Copiers 575 | M93: =PROPER(TRIM(raw_orders!M93)) -> Second Class | N93: 9 | O93: 269.68 | P93: 0 | Q93: 2427.12 | R93: 1538.35 | S93: 804.53 | T93: =PROPER(TRIM(raw_orders!T93)) -> Paid | U93: =PROPER(TRIM(raw_orders!U93)) -> Completed | V93: =C93-B93 -> 33 | W93: =IF(AND(P93="",Q93<>"",N93<>"",S93<>""),0,IF(OR(P93<0,P93>1),P93,P93)) -> 0 | X93: =N93*O93*(1-P93) -> 2427.12 | Y93: =X93-R93 -> 888.77 | Z93: =Y93/X93 -> 0.36618297 | AA93: =TEXT(B93,"MMMM") -> February | AB93: =YEAR(B93) -> 2025 | AC93: =IF(OR(AF93 = "Invalid Discount",AG93="Invalid Discount",AH93="Invalid Shipping Record",AE93="Review Required"),"Invalid",IF(OR(G93="Unknown",M93="Unknown",ISBLANK(P93)),"Warning","Clean")) -> Clean | AD93: =A93&B93&C93&D93&E93&F93&G93&H93&I93&J93&K93&L93&M93&N93&O93&P93&Q93&R93&S93&T93&U93&V93 -> ORD-2025-100924569145724CUST-6409Sneha KapoorCorporateWestMadhya PradeshIndoreTechnologyCopiersPrime Copiers 575Second Class9269.6802427.121538.35804.53PaidCompleted33 | AE93: =IF(COUNTIF($A$2:$A$933,A93)=1,"OK",IF(COUNTIF($AD$2:$AD$933,AD93)>1,"Exact Duplicate", "Review Required")) -> OK | AF93: =IF(P93<0,"Invalid Discount","") | AG93: =IF(P93>1,"Invalid Discount","") | AH93: =IF(V93<1,"Invalid Shipping Record","") | AI93: =IF(ROUND(Q93,2)=ROUND(X93,2),"Match","Mismatch") -> Match | AJ93: =IF(ROUND(S93,2)=ROUND(Y93,2),"Match","Mismatch") -> Mismatch | AK93: =PROPER(TRIM(raw_orders!G93)) -> West | AL93: =PROPER(TRIM(raw_orders!M93)) -> Second Class
A94: ORD-2025-10093 | B94: 45680 | C94: 45683 | D94: CUST-3014 | E94: =PROPER(TRIM(raw_orders!E94)) -> Aarav Sharma | F94: =PROPER(TRIM(raw_orders!F94)) -> Consumer | G94: =PROPER(TRIM(raw_orders!G94)) -> West | H94: =PROPER(TRIM(raw_orders!H94)) -> Madhya Pradesh | I94: =PROPER(TRIM(raw_orders!I94)) -> Indore | J94: =PROPER(TRIM(raw_orders!J94)) -> Office Supplies | K94: =PROPER(TRIM(raw_orders!K94)) -> Paper | L94: Elite Paper 669 | M94: =PROPER(TRIM(raw_orders!M94)) -> Standard Class | N94: 9 | O94: 4458.26 | P94: 0.1 | Q94: 36111.91 | R94: 29194.5 | S94: 6917.41 | T94: =PROPER(TRIM(raw_orders!T94)) -> Paid | U94: =PROPER(TRIM(raw_orders!U94)) -> Completed | V94: =C94-B94 -> 3 | W94: =IF(AND(P94="",Q94<>"",N94<>"",S94<>""),0,IF(OR(P94<0,P94>1),P94,P94)) -> 0.1 | X94: =N94*O94*(1-P94) -> 36111.906 | Y94: =X94-R94 -> 6917.406 | Z94: =Y94/X94 -> 0.19155472 | AA94: =TEXT(B94,"MMMM") -> January | AB94: =YEAR(B94) -> 2025 | AC94: =IF(OR(AF94 = "Invalid Discount",AG94="Invalid Discount",AH94="Invalid Shipping Record",AE94="Review Required"),"Invalid",IF(OR(G94="Unknown",M94="Unknown",ISBLANK(P94)),"Warning","Clean")) -> Clean | AD94: =A94&B94&C94&D94&E94&F94&G94&H94&I94&J94&K94&L94&M94&N94&O94&P94&Q94&R94&S94&T94&U94&V94 -> ORD-2025-100934568045683CUST-3014Aarav SharmaConsumerWestMadhya PradeshIndoreOffice SuppliesPaperElite Paper 669Standard Class94458.260.136111.9129194.56917.41PaidCompleted3 | AE94: =IF(COUNTIF($A$2:$A$933,A94)=1,"OK",IF(COUNTIF($AD$2:$AD$933,AD94)>1,"Exact Duplicate", "Review Required")) -> OK | AF94: =IF(P94<0,"Invalid Discount","") | AG94: =IF(P94>1,"Invalid Discount","") | AH94: =IF(V94<1,"Invalid Shipping Record","") | AI94: =IF(ROUND(Q94,2)=ROUND(X94,2),"Match","Mismatch") -> Match | AJ94: =IF(ROUND(S94,2)=ROUND(Y94,2),"Match","Mismatch") -> Match | AK94: =PROPER(TRIM(raw_orders!G94)) -> West | AL94: =PROPER(TRIM(raw_orders!M94)) -> Standard Class
A95: ORD-2024-10094 | B95: 45298 | C95: 45304 | D95: CUST-6106 | E95: =PROPER(TRIM(raw_orders!E95)) -> Rohan Mehta | F95: =PROPER(TRIM(raw_orders!F95)) -> Corporate | G95: =PROPER(TRIM(raw_orders!G95)) -> North | H95: =PROPER(TRIM(raw_orders!H95)) -> Uttar Pradesh | I95: =PROPER(TRIM(raw_orders!I95)) -> Noida | J95: =PROPER(TRIM(raw_orders!J95)) -> Office Supplies | K95: =PROPER(TRIM(raw_orders!K95)) -> Binders | L95: Eco Binders 780 | M95: =PROPER(TRIM(raw_orders!M95)) -> Standard Class | N95: 7 | O95: 2788.97 | P95: -0.09 | Q95: 19522.79 | R95: 12455.78 | S95: 7067.01 | T95: =PROPER(TRIM(raw_orders!T95)) -> Paid | U95: =PROPER(TRIM(raw_orders!U95)) -> Completed | V95: =C95-B95 -> 6 | W95: =IF(AND(P95="",Q95<>"",N95<>"",S95<>""),0,IF(OR(P95<0,P95>1),P95,P95)) -> -0.09 | X95: =N95*O95*(1-P95) -> 21279.841 | Y95: =X95-R95 -> 8824.0611 | Z95: =Y95/X95 -> 0.41466762 | AA95: =TEXT(B95,"MMMM") -> January | AB95: =YEAR(B95) -> 2024 | AC95: =IF(OR(AF95 = "Invalid Discount",AG95="Invalid Discount",AH95="Invalid Shipping Record",AE95="Review Required"),"Invalid",IF(OR(G95="Unknown",M95="Unknown",ISBLANK(P95)),"Warning","Clean")) -> Invalid | AD95: =A95&B95&C95&D95&E95&F95&G95&H95&I95&J95&K95&L95&M95&N95&O95&P95&Q95&R95&S95&T95&U95&V95 -> ORD-2024-100944529845304CUST-6106Rohan MehtaCorporateNorthUttar PradeshNoidaOffice SuppliesBindersEco Binders 780Standard Class72788.97-0.0919522.7912455.787067.01PaidCompleted6 | AE95: =IF(COUNTIF($A$2:$A$933,A95)=1,"OK",IF(COUNTIF($AD$2:$AD$933,AD95)>1,"Exact Duplicate", "Review Required")) -> OK | AF95: =IF(P95<0,"Invalid Discount","") -> Invalid Discount | AG95: =IF(P95>1,"Invalid Discount","") | AH95: =IF(V95<1,"Invalid Shipping Record","") | AI95: =IF(ROUND(Q95,2)=ROUND(X95,2),"Match","Mismatch") -> Mismatch | AJ95: =IF(ROUND(S95,2)=ROUND(Y95,2),"Match","Mismatch") -> Mismatch | AK95: =PROPER(TRIM(raw_orders!G95)) -> North | AL95: =PROPER(TRIM(raw_orders!M95)) -> Standard Class
A96: ORD-2024-10095 | B96: 45541 | C96: 45544 | D96: CUST-1926 | E96: =PROPER(TRIM(raw_orders!E96)) -> Diya Patel | F96: =PROPER(TRIM(raw_orders!F96)) -> Consumer | G96: =PROPER(TRIM(raw_orders!G96)) -> North | H96: =PROPER(TRIM(raw_orders!H96)) -> Haryana | I96: =PROPER(TRIM(raw_orders!I96)) -> Gurugram | J96: =PROPER(TRIM(raw_orders!J96)) -> Technology | K96: =PROPER(TRIM(raw_orders!K96)) -> Phones | L96: Elite Phones 723 | M96: =PROPER(TRIM(raw_orders!M96)) -> Second Class | N96: 7 | O96: 3781.53 | P96: 0 | Q96: 26470.71 | R96: 21367.6 | S96: 5103.11 | T96: =PROPER(TRIM(raw_orders!T96)) -> Pending | U96: =PROPER(TRIM(raw_orders!U96)) -> Cancelled | V96: =C96-B96 -> 3 | W96: =IF(AND(P96="",Q96<>"",N96<>"",S96<>""),0,IF(OR(P96<0,P96>1),P96,P96)) -> 0 | X96: =N96*O96*(1-P96) -> 26470.71 | Y96: =X96-R96 -> 5103.11 | Z96: =Y96/X96 -> 0.19278327 | AA96: =TEXT(B96,"MMMM") -> September | AB96: =YEAR(B96) -> 2024 | AC96: =IF(OR(AF96 = "Invalid Discount",AG96="Invalid Discount",AH96="Invalid Shipping Record",AE96="Review Required"),"Invalid",IF(OR(G96="Unknown",M96="Unknown",ISBLANK(P96)),"Warning","Clean")) -> Clean | AD96: =A96&B96&C96&D96&E96&F96&G96&H96&I96&J96&K96&L96&M96&N96&O96&P96&Q96&R96&S96&T96&U96&V96 -> ORD-2024-100954554145544CUST-1926Diya PatelConsumerNorthHaryanaGurugramTechnologyPhonesElite Phones 723Second Class73781.53026470.7121367.65103.11PendingCancelled3 | AE96: =IF(COUNTIF($A$2:$A$933,A96)=1,"OK",IF(COUNTIF($AD$2:$AD$933,AD96)>1,"Exact Duplicate", "Review Required")) -> OK | AF96: =IF(P96<0,"Invalid Discount","") | AG96: =IF(P96>1,"Invalid Discount","") | AH96: =IF(V96<1,"Invalid Shipping Record","") | AI96: =IF(ROUND(Q96,2)=ROUND(X96,2),"Match","Mismatch") -> Match | AJ96: =IF(ROUND(S96,2)=ROUND(Y96,2),"Match","Mismatch") -> Match | AK96: =PROPER(TRIM(raw_orders!G96)) -> North | AL96: =PROPER(TRIM(raw_orders!M96)) -> Second Class
A97: ORD-2025-10096 | B97: 45786 | C97: 45910 | D97: CUST-2687 | E97: =PROPER(TRIM(raw_orders!E97)) -> Sneha Kapoor | F97: =PROPER(TRIM(raw_orders!F97)) -> Corporate | G97: =PROPER(TRIM(raw_orders!G97)) -> West | H97: =PROPER(TRIM(raw_orders!H97)) -> Goa | I97: =PROPER(TRIM(raw_orders!I97)) -> Panaji | J97: =PROPER(TRIM(raw_orders!J97)) -> Furniture | K97: =PROPER(TRIM(raw_orders!K97)) -> Bookcases | L97: Classic Bookcases 988 | M97: =PROPER(TRIM(raw_orders!M97)) -> Same Day | N97: 6 | O97: 1754.13 | P97: 0 | Q97: 10524.78 | R97: 8841.05 | S97: 1683.73 | T97: =PROPER(TRIM(raw_orders!T97)) -> Paid | U97: =PROPER(TRIM(raw_orders!U97)) -> Completed | V97: =C97-B97 -> 124 | W97: =IF(AND(P97="",Q97<>"",N97<>"",S97<>""),0,IF(OR(P97<0,P97>1),P97,P97)) -> 0 | X97: =N97*O97*(1-P97) -> 10524.78 | Y97: =X97-R97 -> 1683.73 | Z97: =Y97/X97 -> 0.15997769 | AA97: =TEXT(B97,"MMMM") -> May | AB97: =YEAR(B97) -> 2025 | AC97: =IF(OR(AF97 = "Invalid Discount",AG97="Invalid Discount",AH97="Invalid Shipping Record",AE97="Review Required"),"Invalid",IF(OR(G97="Unknown",M97="Unknown",ISBLANK(P97)),"Warning","Clean")) -> Clean | AD97: =A97&B97&C97&D97&E97&F97&G97&H97&I97&J97&K97&L97&M97&N97&O97&P97&Q97&R97&S97&T97&U97&V97 -> ORD-2025-100964578645910CUST-2687Sneha KapoorCorporateWestGoaPanajiFurnitureBookcasesClassic Bookcases 988Same Day61754.13010524.788841.051683.73PaidCompleted124 | AE97: =IF(COUNTIF($A$2:$A$933,A97)=1,"OK",IF(COUNTIF($AD$2:$AD$933,AD97)>1,"Exact Duplicate", "Review Required")) -> OK | AF97: =IF(P97<0,"Invalid Discount","") | AG97: =IF(P97>1,"Invalid Discount","") | AH97: =IF(V97<1,"Invalid Shipping Record","") | AI97: =IF(ROUND(Q97,2)=ROUND(X97,2),"Match","Mismatch") -> Match | AJ97: =IF(ROUND(S97,2)=ROUND(Y97,2),"Match","Mismatch") -> Match | AK97: =PROPER(TRIM(raw_orders!G97)) -> West | AL97: =PROPER(TRIM(raw_orders!M97)) -> Same Day
A98: ORD-2024-10097 | B98: 45448 | C98: 45479 | D98: CUST-7283 | E98: =PROPER(TRIM(raw_orders!E98)) -> Rahul Verma | F98: =PROPER(TRIM(raw_orders!F98)) -> Home Office | G98: =PROPER(TRIM(raw_orders!G98)) -> East | H98: =PROPER(TRIM(raw_orders!H98)) -> Odisha | I98: =PROPER(TRIM(raw_orders!I98)) -> Bhubaneswar | J98: =PROPER(TRIM(raw_orders!J98)) -> Technology | K98: =PROPER(TRIM(raw_orders!K98)) -> Copiers | L98: Smart Copiers 547 | M98: =PROPER(TRIM(raw_orders!M98)) -> Second Class | N98: 2 | O98: 2259.24 | P98: 0.15 | Q98: 3840.71 | R98: 2516.29 | S98: 1324.42 | T98: =PROPER(TRIM(raw_orders!T98)) -> Paid | U98: =PROPER(TRIM(raw_orders!U98)) -> Completed | V98: =C98-B98 -> 31 | W98: =IF(AND(P98="",Q98<>"",N98<>"",S98<>""),0,IF(OR(P98<0,P98>1),P98,P98)) -> 0.15 | X98: =N98*O98*(1-P98) -> 3840.708 | Y98: =X98-R98 -> 1324.418 | Z98: =Y98/X98 -> 0.34483694 | AA98: =TEXT(B98,"MMMM") -> June | AB98: =YEAR(B98) -> 2024 | AC98: =IF(OR(AF98 = "Invalid Discount",AG98="Invalid Discount",AH98="Invalid Shipping Record",AE98="Review Required"),"Invalid",IF(OR(G98="Unknown",M98="Unknown",ISBLANK(P98)),"Warning","Clean")) -> Clean | AD98: =A98&B98&C98&D98&E98&F98&G98&H98&I98&J98&K98&L98&M98&N98&O98&P98&Q98&R98&S98&T98&U98&V98 -> ORD-2024-100974544845479CUST-7283Rahul VermaHome OfficeEastOdishaBhubaneswarTechnologyCopiersSmart Copiers 547Second Class22259.240.153840.712516.291324.42PaidCompleted31 | AE98: =IF(COUNTIF($A$2:$A$933,A98)=1,"OK",IF(COUNTIF($AD$2:$AD$933,AD98)>1,"Exact Duplicate", "Review Required")) -> OK | AF98: =IF(P98<0,"Invalid Discount","") | AG98: =IF(P98>1,"Invalid Discount","") | AH98: =IF(V98<1,"Invalid Shipping Record","") | AI98: =IF(ROUND(Q98,2)=ROUND(X98,2),"Match","Mismatch") -> Match | AJ98: =IF(ROUND(S98,2)=ROUND(Y98,2),"Match","Mismatch") -> Match | AK98: =PROPER(TRIM(raw_orders!G98)) -> East | AL98: =PROPER(TRIM(raw_orders!M98)) -> Second Class
A99: ORD-2025-10098 | B99: 45877 | C99: 45880 | D99: CUST-8111 | E99: =PROPER(TRIM(raw_orders!E99)) -> Diya Patel | F99: =PROPER(TRIM(raw_orders!F99)) -> Small Business | G99: =PROPER(TRIM(raw_orders!G99)) -> West | H99: =PROPER(TRIM(raw_orders!H99)) -> Gujarat | I99: =PROPER(TRIM(raw_orders!I99)) -> Ahmedabad | J99: =PROPER(TRIM(raw_orders!J99)) -> Office Supplies | K99: =PROPER(TRIM(raw_orders!K99)) -> Storage | L99: Basic Storage 656 | M99: =PROPER(TRIM(raw_orders!M99)) -> Same Day | N99: 5 | O99: 3602.36 | P99: 0.2 | Q99: 14409.44 | R99: 8809.97 | S99: 5599.47 | T99: =PROPER(TRIM(raw_orders!T99)) -> Pending | U99: =PROPER(TRIM(raw_orders!U99)) -> Returned | V99: =C99-B99 -> 3 | W99: =IF(AND(P99="",Q99<>"",N99<>"",S99<>""),0,IF(OR(P99<0,P99>1),P99,P99)) -> 0.2 | X99: =N99*O99*(1-P99) -> 14409.44 | Y99: =X99-R99 -> 5599.47 | Z99: =Y99/X99 -> 0.38859734 | AA99: =TEXT(B99,"MMMM") -> August | AB99: =YEAR(B99) -> 2025 | AC99: =IF(OR(AF99 = "Invalid Discount",AG99="Invalid Discount",AH99="Invalid Shipping Record",AE99="Review Required"),"Invalid",IF(OR(G99="Unknown",M99="Unknown",ISBLANK(P99)),"Warning","Clean")) -> Clean | AD99: =A99&B99&C99&D99&E99&F99&G99&H99&I99&J99&K99&L99&M99&N99&O99&P99&Q99&R99&S99&T99&U99&V99 -> ORD-2025-100984587745880CUST-8111Diya PatelSmall BusinessWestGujaratAhmedabadOffice SuppliesStorageBasic Storage 656Same Day53602.360.214409.448809.975599.47PendingReturned3 | AE99: =IF(COUNTIF($A$2:$A$933,A99)=1,"OK",IF(COUNTIF($AD$2:$AD$933,AD99)>1,"Exact Duplicate", "Review Required")) -> OK | AF99: =IF(P99<0,"Invalid Discount","") | AG99: =IF(P99>1,"Invalid Discount","") | AH99: =IF(V99<1,"Invalid Shipping Record","") | AI99: =IF(ROUND(Q99,2)=ROUND(X99,2),"Match","Mismatch") -> Match | AJ99: =IF(ROUND(S99,2)=ROUND(Y99,2),"Match","Mismatch") -> Match | AK99: =PROPER(TRIM(raw_orders!G99)) -> West | AL99: =PROPER(TRIM(raw_orders!M99)) -> Same Day
A100: ORD-2024-10099 | B100: 45317 | C100: 45323 | D100: CUST-5434 | E100: =PROPER(TRIM(raw_orders!E100)) -> Rohan Mehta | F100: =PROPER(TRIM(raw_orders!F100)) -> Home Office | G100: =PROPER(TRIM(raw_orders!G100)) -> South | H100: =PROPER(TRIM(raw_orders!H100)) -> Kerala | I100: =PROPER(TRIM(raw_orders!I100)) -> Kochi | J100: =PROPER(TRIM(raw_orders!J100)) -> Technology | K100: =PROPER(TRIM(raw_orders!K100)) -> Copiers | L100: Elite Copiers 785 | M100: Unknown | N100: 8 | O100: 2108.93 | P100: 0.1 | Q100: 15184.3 | R100: 11270.74 | S100: 3913.56 | T100: =PROPER(TRIM(raw_orders!T100)) -> Paid | U100: =PROPER(TRIM(raw_orders!U100)) -> Completed | V100: =C100-B100 -> 6 | W100: =IF(AND(P100="",Q100<>"",N100<>"",S100<>""),0,IF(OR(P100<0,P100>1),P100,P100)) -> 0.1 | X100: =N100*O100*(1-P100) -> 15184.296 | Y100: =X100-R100 -> 3913.556 | Z100: =Y100/X100 -> 0.25773707 | AA100: =TEXT(B100,"MMMM") -> January | AB100: =YEAR(B100) -> 2024 | AC100: =IF(OR(AF100 = "Invalid Discount",AG100="Invalid Discount",AH100="Invalid Shipping Record",AE100="Review Required"),"Invalid",IF(OR(G100="Unknown",M100="Unknown",ISBLANK(P100)),"Warning","Clean")) -> Warning | AD100: =A100&B100&C100&D100&E100&F100&G100&H100&I100&J100&K100&L100&M100&N100&O100&P100&Q100&R100&S100&T100&U100&V100 -> ORD-2024-100994531745323CUST-5434Rohan MehtaHome OfficeSouthKeralaKochiTechnologyCopiersElite Copiers 785Unknown82108.930.115184.311270.743913.56PaidCompleted6 | AE100: =IF(COUNTIF($A$2:$A$933,A100)=1,"OK",IF(COUNTIF($AD$2:$AD$933,AD100)>1,"Exact Duplicate", "Review Required")) -> OK | AF100: =IF(P100<0,"Invalid Discount","") | AG100: =IF(P100>1,"Invalid Discount","") | AH100: =IF(V100<1,"Invalid Shipping Record","") | AI100: =IF(ROUND(Q100,2)=ROUND(X100,2),"Match","Mismatch") -> Match | AJ100: =IF(ROUND(S100,2)=ROUND(Y100,2),"Match","Mismatch") -> Match | AK100: =PROPER(TRIM(raw_orders!G100)) -> South | AL100: =PROPER(TRIM(raw_orders!M100))
...

Sheet Pivot Summary
A1: 1. Sales and profit by region | G1: 4. Profit margin by customer segment
G2: order_status | H2: (Multiple Items)
A3: order_status | B3: (Multiple Items) | G3: payment_status | H3: (Multiple Items)
A4: payment_status | B4: (Multiple Items)
G5: Customer Segment | H5: Profit Margin
A6: Region | B6: Total Sales | C6: Total Profit | G6: Small Business | H6: 54.453462
A7: South | B7: 1727877.2 | C7: 435406.81 | G7: Home Office | H7: 52.910054
A8: West | B8: 1726773.1 | C8: 503393.35 | G8: Corporate | H8: 44.968902
A9: East | B9: 1697077 | C9: 516619.95 | G9: Consumer | H9: 40.816441
A10: North | B10: 1516649.9 | C10: 448467.61
A11: Unknown | B11: 198465.57 | C11: 69154.367
A12: Grand Total | B12: 6866842.9 | C12: 1973042.1
A16: 2. Sales and profit by category and sub-category | G16: 5. Refunded/cancelled/failed orders by region | O16: Refunded Orders Summary (Task 5)
G18: region | H18: East | O18: payment_status | P18: Refunded
A19: order_status | B19: (Multiple Items)
A20: payment_status | B20: (Multiple Items) | H20: Column Labels | O20: Region | P20: Total Sales | Q20: Total Profit
H21: Failed | I21: Paid | J21: Pending | K21: Refunded | L21: Grand Total | O21: South | P21: 224891.77 | Q21: 71572.274
A22: Sub-category | B22: Total Sales | C22: Total Profit | G22: Order Count | H22: 13 | I22: 169 | J22: 28 | K22: 14 | L22: 224 | O22: West | P22: 130225.72 | Q22: 30460.851
A23: Technology | B23: 2417325.5 | C23: 679406.11 | O23: North | P23: 128373.78 | Q23: 36077.761
A24: Copiers | B24: 739834.44 | C24: 217948.14 | O24: East | P24: 124124.29 | Q24: 35714.084
A25: Accessories | B25: 607501.75 | C25: 173990.34 | O25: Unknown | P25: 69199.253 | Q25: 22399.153
A26: Phones | B26: 599901.77 | C26: 152977.09 | O26: Grand Total | P26: 676814.82 | Q26: 196224.12
A27: Machines | B27: 470087.56 | C27: 134490.54
A28: Furniture | B28: 2285229.7 | C28: 670152.02
A29: Chairs | B29: 674212.79 | C29: 207910.68
A30: Furnishings | B30: 608469.82 | C30: 176979.34
A31: Bookcases | B31: 526112.9 | C31: 142795.95
A32: Tables | B32: 476434.2 | C32: 142466.06
A33: Office Supplies | B33: 2164287.7 | C33: 623483.96
A34: Storage | B34: 626982.38 | C34: 160443.23 | G34: 6. Monthly sales trend
A35: Paper | B35: 540212.42 | C35: 157518.66 | G35: order_status | H35: (Multiple Items)
A36: Binders | B36: 420145.1 | C36: 134574.66 | G36: payment_status | H36: (Multiple Items)
A37: Art | B37: 363040.13 | C37: 103002.21
A38: Labels | B38: 213907.64 | C38: 67945.201 | G38: Month | H38: Total Sales
A39: Grand Total | B39: 6866842.9 | C39: 1973042.1 | G39: 2024 | H39: 3747196.6
G40: Jan | H40: 349366.62
A41: 3. Order count by ship mode | G41: Feb | H41: 368133.11
A42: order_status | B42: (All) | G42: Mar | H42: 264208.97
A43: payment_status | B43: (Multiple Items) | G43: Apr | H43: 319388.78
G44: May | H44: 329213.41
A45: Ship Mode | B45: Order Count | G45: Jun | H45: 395975.09
A46: First Class | B46: 192 | G46: Jul | H46: 263345.8
A47: Same Day | B47: 171 | G47: Aug | H47: 256312.01
A48: Second Class | B48: 187 | G48: Sep | H48: 296156.81
A49: Standard Class | B49: 204 | G49: Oct | H49: 406136.92
A50: Unknown | B50: 18 | G50: Nov | H50: 299464.04
A51: Grand Total | B51: 772 | G51: Dec | H51: 199494.98
G52: 2025 | H52: 3119646.3
G53: Jan | H53: 337762.1
G54: Feb | H54: 387247.71
G55: Mar | H55: 347121.8
G56: Apr | H56: 302433.52
G57: May | H57: 305572.02
G58: Jun | H58: 218940.15
G59: Jul | H59: 309511.1
G60: Aug | H60: 369054.39
G61: Sep | H61: 369398.22
G62: Oct | H62: 136758.05
G63: Nov | H63: 23474.847
... G65: Grand Total | H65: 6866842.9

Sheet initial_working_sheet
A1: order_id | B1: order_date | C1: ship_date | D1: customer_id | E1: customer_name | F1: segment | G1: region | H1: state | I1: city | J1: category | K1: sub_category | L1: product_name | M1: ship_mode | N1: quantity | O1: unit_price | P1: discount | Q1: sales | R1: cost | S1: profit | T1: payment_status | U1: order_status | V1: shipping_delay_days | W1: row_text | X1: review_flag
A2: ORD-2024-10001 | B2: 45494 | C2: 45500 | D2: CUST-4655 | E2: =PROPER(TRIM(raw_orders!E2)) -> Karan Malhotra | F2: =PROPER(TRIM(raw_orders!F2)) -> Consumer | G2: =PROPER(TRIM(raw_orders!G2)) -> North | H2: =PROPER(TRIM(raw_orders!H2)) -> Rajasthan | I2: =PROPER(TRIM(raw_orders!I2)) -> Jaipur | J2: =PROPER(TRIM(raw_orders!J2)) -> Office Supplies | K2: =PROPER(TRIM(raw_orders!K2)) -> Paper | L2: Pro Paper 122 | M2: =PROPER(TRIM(raw_orders!M2)) -> Second Class | N2: 8 | O2: 2976.45 | P2: 0.2 | Q2: 19049.28 | R2: 15841.89 | S2: 3207.39 | T2: =PROPER(TRIM(raw_orders!T2)) -> Paid | U2: =PROPER(TRIM(raw_orders!U2)) -> Completed | V2: =C2-B2 -> 6 | W2: =A2&B2&C2&D2&E2&F2&G2&H2&I2&J2&K2&L2&M2&N2&O2&P2&Q2&R2&S2&T2&U2&V2 -> ORD-2024-100014549445500CUST-4655Karan MalhotraConsumerNorthRajasthanJaipurOffice SuppliesPaperPro Paper 122Second Class82976.450.219049.2815841.893207.39PaidCompleted6 | X2: =IF(COUNTIF($A$2:$A$933,A2)=1,"OK",IF(COUNTIF($W$2:$W$933,W2)>1,"Exact Duplicate", "Review Required")) -> OK | AB2: Count of missing valuesin order_date column | AC2: =COUNTBLANK(B2:B933) -> 0
A3: ORD-2024-10002 | B3: 45535 | C3: 45540 | D3: CUST-2054 | E3: =PROPER(TRIM(raw_orders!E3)) -> Mira Das | F3: =PROPER(TRIM(raw_orders!F3)) -> Small Business | G3: =PROPER(TRIM(raw_orders!G3)) -> East | H3: =PROPER(TRIM(raw_orders!H3)) -> Odisha | I3: =PROPER(TRIM(raw_orders!I3)) -> Bhubaneswar | J3: =PROPER(TRIM(raw_orders!J3)) -> Furniture | K3: =PROPER(TRIM(raw_orders!K3)) -> Tables | L3: Pro Tables 258 | M3: =PROPER(TRIM(raw_orders!M3)) -> Same Day | N3: 3 | O3: 2437.5 | P3: 0 | Q3: 7312.5 | R3: 4904.73 | S3: 2407.77 | T3: =PROPER(TRIM(raw_orders!T3)) -> Paid | U3: =PROPER(TRIM(raw_orders!U3)) -> Completed | V3: =C3-B3 -> 5 | W3: =A3&B3&C3&D3&E3&F3&G3&H3&I3&J3&K3&L3&M3&N3&O3&P3&Q3&R3&S3&T3&U3&V3 -> ORD-2024-100024553545540CUST-2054Mira DasSmall BusinessEastOdishaBhubaneswarFurnitureTablesPro Tables 258Same Day32437.507312.54904.732407.77PaidCompleted5 | X3: =IF(COUNTIF($A$2:$A$933,A3)=1,"OK",IF(COUNTIF($W$2:$W$933,W3)>1,"Exact Duplicate", "Review Required")) -> OK | AB3: Count of missing values in ship_date column | AC3: =COUNTBLANK(C2:C933) -> 0
A4: ORD-2024-10003 | B4: 45451 | C4: 45458 | D4: CUST-6843 | E4: =PROPER(TRIM(raw_orders!E4)) -> Isha Nair | F4: =PROPER(TRIM(raw_orders!F4)) -> Consumer | G4: =PROPER(TRIM(raw_orders!G4)) -> East | H4: =PROPER(TRIM(raw_orders!H4)) -> Odisha | I4: =PROPER(TRIM(raw_orders!I4)) -> Bhubaneswar | J4: =PROPER(TRIM(raw_orders!J4)) -> Office Supplies | K4: =PROPER(TRIM(raw_orders!K4)) -> Art | L4: Elite Art 525 | M4: =PROPER(TRIM(raw_orders!M4)) -> First Class | N4: 4 | O4: 1065.43 | P4: 0.55 | Q4: 4261.72 | R4: 2465.69 | S4: 1796.03 | T4: =PROPER(TRIM(raw_orders!T4)) -> Paid | U4: =PROPER(TRIM(raw_orders!U4)) -> Completed | V4: =C4-B4 -> 7 | W4: =A4&B4&C4&D4&E4&F4&G4&H4&I4&J4&K4&L4&M4&N4&O4&P4&Q4&R4&S4&T4&U4&V4 -> ORD-2024-100034545145458CUST-6843Isha NairConsumerEastOdishaBhubaneswarOffice SuppliesArtElite Art 525First Class41065.430.554261.722465.691796.03PaidCompleted7 | X4: =IF(COUNTIF($A$2:$A$933,A4)=1,"OK",IF(COUNTIF($W$2:$W$933,W4)>1,"Exact Duplicate", "Review Required")) -> OK
A5: ORD-2024-10004 | B5: 45624 | C5: 45625 | D5: CUST-3722 | E5: =PROPER(TRIM(raw_orders!E5)) -> Arjun Bose | F5: =PROPER(TRIM(raw_orders!F5)) -> Small Business | G5: =PROPER(TRIM(raw_orders!G5)) -> South | H5: =PROPER(TRIM(raw_orders!H5)) -> Telangana | I5: =PROPER(TRIM(raw_orders!I5)) -> Hyderabad | J5: =PROPER(TRIM(raw_orders!J5)) -> Furniture | K5: =PROPER(TRIM(raw_orders!K5)) -> Furnishings | L5: Smart Furnishings 294 | M5: =PROPER(TRIM(raw_orders!M5)) -> Standard Class | N5: 6 | O5: 1848.43 | P5: 0.25 | Q5: 8317.93 | R5: 6796.77 | S5: 1521.16 | T5: =PROPER(TRIM(raw_orders!T5)) -> Paid | U5: =PROPER(TRIM(raw_orders!U5)) -> Completed | V5: =C5-B5 -> 1 | W5: =A5&B5&C5&D5&E5&F5&G5&H5&I5&J5&K5&L5&M5&N5&O5&P5&Q5&R5&S5&T5&U5&V5 -> ORD-2024-100044562445625CUST-3722Arjun BoseSmall BusinessSouthTelanganaHyderabadFurnitureFurnishingsSmart Furnishings 294Standard Class61848.430.258317.936796.771521.16PaidCompleted1 | X5: =IF(COUNTIF($A$2:$A$933,A5)=1,"OK",IF(COUNTIF($W$2:$W$933,W5)>1,"Exact Duplicate", "Review Required")) -> OK | AB5: Count of Invalid/Text Values in order_date column | AC5: =COUNTA(B2:B933)-COUNT(B2:B933) -> 0
A6: ORD-2025-10005 | B6: 45898 | C6: 45901 | D6: CUST-8130 | E6: =PROPER(TRIM(raw_orders!E6)) -> Ananya Rao | F6: =PROPER(TRIM(raw_orders!F6)) -> Small Business | G6: =PROPER(TRIM(raw_orders!G6)) -> West | H6: =PROPER(TRIM(raw_orders!H6)) -> Maharashtra | I6: =PROPER(TRIM(raw_orders!I6)) -> Mumbai | J6: =PROPER(TRIM(raw_orders!J6)) -> Furniture | K6: =PROPER(TRIM(raw_orders!K6)) -> Chairs | L6: Elite Chairs 543 | M6: =PROPER(TRIM(raw_orders!M6)) -> First Class | N6: 7 | O6: 2973.76 | P6: 0 | Q6: 20816.32 | R6: 17705.37 | S6: 3110.95 | T6: =PROPER(TRIM(raw_orders!T6)) -> Paid | U6: =PROPER(TRIM(raw_orders!U6)) -> Cancelled | V6: =C6-B6 -> 3 | W6: =A6&B6&C6&D6&E6&F6&G6&H6&I6&J6&K6&L6&M6&N6&O6&P6&Q6&R6&S6&T6&U6&V6 -> ORD-2025-100054589845901CUST-8130Ananya RaoSmall BusinessWestMaharashtraMumbaiFurnitureChairsElite Chairs 543First Class72973.76020816.3217705.373110.95PaidCancelled3 | X6: =IF(COUNTIF($A$2:$A$933,A6)=1,"OK",IF(COUNTIF($W$2:$W$933,W6)>1,"Exact Duplicate", "Review Required")) -> OK | AB6: Count of Invalid/Text Values in ship_date column | AC6: =COUNTA(C2:C933)-COUNT(C2:C933) -> 0
A7: ORD-2024-10006 | B7: 45436 | C7: 45440 | D7: CUST-6056 | E7: =PROPER(TRIM(raw_orders!E7)) -> Vikram Iyer | F7: =PROPER(TRIM(raw_orders!F7)) -> Small Business | G7: =PROPER(TRIM(raw_orders!G7)) -> West | H7: =PROPER(TRIM(raw_orders!H7)) -> Madhya Pradesh | I7: =PROPER(TRIM(raw_orders!I7)) -> Indore | J7: =PROPER(TRIM(raw_orders!J7)) -> Technology | K7: =PROPER(TRIM(raw_orders!K7)) -> Accessories | L7: Pro Accessories 821 | M7: =PROPER(TRIM(raw_orders!M7)) -> Same Day | N7: 3 | O7: 1053.11 | P7: 0.2 | Q7: 2527.46 | R7: 1533.58 | S7: 993.88 | T7: =PROPER(TRIM(raw_orders!T7)) -> Paid | U7: =PROPER(TRIM(raw_orders!U7)) -> Completed | V7: =C7-B7 -> 4 | W7: =A7&B7&C7&D7&E7&F7&G7&H7&I7&J7&K7&L7&M7&N7&O7&P7&Q7&R7&S7&T7&U7&V7 -> ORD-2024-100064543645440CUST-6056Vikram IyerSmall BusinessWestMadhya PradeshIndoreTechnologyAccessoriesPro Accessories 821Same Day31053.110.22527.461533.58993.88PaidCompleted4 | X7: =IF(COUNTIF($A$2:$A$933,A7)=1,"OK",IF(COUNTIF($W$2:$W$933,W7)>1,"Exact Duplicate", "Review Required")) -> OK
A8: ORD-2025-10007 | B8: 45757 | C8: 45763 | D8: CUST-3656 | E8: =PROPER(TRIM(raw_orders!E8)) -> Neha Gupta | F8: =PROPER(TRIM(raw_orders!F8)) -> Consumer | G8: =PROPER(TRIM(raw_orders!G8)) -> East | H8: =PROPER(TRIM(raw_orders!H8)) -> Odisha | I8: =PROPER(TRIM(raw_orders!I8)) -> Bhubaneswar | J8: =PROPER(TRIM(raw_orders!J8)) -> Technology | K8: =PROPER(TRIM(raw_orders!K8)) -> Copiers | L8: Eco Copiers 790 | M8: =PROPER(TRIM(raw_orders!M8)) -> Standard Class | N8: 4 | O8: 1719.87 | P8: 0.15 | Q8: 5847.56 | R8: 4727.25 | S8: 1120.31 | T8: =PROPER(TRIM(raw_orders!T8)) -> Paid | U8: =PROPER(TRIM(raw_orders!U8)) -> Completed | V8: =C8-B8 -> 6 | W8: =A8&B8&C8&D8&E8&F8&G8&H8&I8&J8&K8&L8&M8&N8&O8&P8&Q8&R8&S8&T8&U8&V8 -> ORD-2025-100074575745763CUST-3656Neha GuptaConsumerEastOdishaBhubaneswarTechnologyCopiersEco Copiers 790Standard Class41719.870.155847.564727.251120.31PaidCompleted6 | X8: =IF(COUNTIF($A$2:$A$933,A8)=1,"OK",IF(COUNTIF($W$2:$W$933,W8)>1,"Exact Duplicate", "Review Required")) -> Exact Duplicate | AB8: Count of ship dates earlier than order dates | AC8: =COUNTIF(V2:V933, "< 0") -> 94
